Workbook

Sheet Pot
B2: Cashflow Analysis | C2: 2025 | D2: 2024 | E2: MAR Code
B3: Winst van het boekjaar voor belastingen | C3: =201022.54+69442.88 -> 270465.42 | D3: 56127.31 | E3: [9904]+[67/77]
B4: PLUS niet-kaskosten | C4: =SUM(C5:C8) -> 221886.72 | D4: =SUM(D5:D8) -> 172158.41
B5: Afschrijvingen | C5: 152975.39 | D5: 155871.43 | E5: [630]
B6: Waardeverminderingen op handelsvorderingen en voorraden | C6: 40766 | D6: 7360 | E6: [631/4] | G6: MAR CODE 744 VMA winst?
B7: Voorzieningen voor risico’s en kosten | C7: 12614.08 | D7: 8926.98 | E7: [635/8]
B8: Overboeking naar de uitgestelde belastingen | C8: 15531.25 | E8: [680] | G8: 201022.54
B9: MIN niet-kasopbrengsten | C9: =C10+C11 -> -973.67 | G9: 69442.88
B10: Onttrekking aan de uitgestelde belastingen | C10: =-743.15 -> -743.15 | E10: [780] | G10: 15531.25
B11: Aangerekende kapitaalsubsidies in resultaat | C11: =-230.52 -> -230.52 | G11: -743.15
B12: Cashflow van het eigen vermogen | C12: =C3+C4+C9 -> 491378.47 | D12: =D3+D4+D9 -> 228285.72 | G12: =SUM(G8:G11) -> 285253.52
B13: PLUS intresten uit vreemd vermogen | C13: 64704.91 | D13: 62433.75 | E13: [65] | G13: -69442.88
B14: Potentiële operationele cashflow voor belasting | C14: =C12+C13 -> 556083.38 | D14: =D12+D13 -> 290719.47 | G14: -15531.25
B15: Vennootschapsbelasting | C15: 69442.88 | D15: 17837.65 | G15: 743.15
B16: Potentiële operationele cashflow | C16: =C14-C15 -> 486640.5 | D16: =D14-D15 -> 272881.82 | G16: =SUM(G12:G15) -> 201022.54
B19: [9125] vol Model,
B20: pag 146
B23: Cashflow Analysis | C23: 2025 | D23: 2024 | E23: MAR Code
B24: Winst van het boekjaar voor belastingen | C24: 285253.52 | D24: 56127.31 | E24: [9903]
B25: PLUS niet-kaskosten | C25: =C26+C27+C28+C29+C30 -> 226533.33 | D25: =D26+D27+D28+D29+D30 -> 172158.41
B26: Afschrijvingen | C26: 152975.39 | D26: 155871.43 | E26: [630] | G26: [6300/2, 660,- 760- 761, 6501]
B27: Waardeverminderingen op handelsvorderingen en voorraden | C27: 40766 | D27: 7360 | E27: [631/4]
B28: Minderwaarde realisatie voordering | C28: 4646.61 | D28: 0 | E28: [641/2]
B29: Voorzieningen voor risico’s en kosten | C29: 12614.08 | D29: 8926.98 | E29: [635/8]
B30: Overboeking naar de uitgestelde belastingen | C30: 15531.25 | E30: [680]
B31: MIN niet-kasopbrengsten | C31: =C32+C33 -> -973.67 | D31: =D32+D33 -> 0
B32: Onttrekking aan de uitgestelde belastingen | C32: =-743.15 -> -743.15 | E32: [780]
B33: Aangerekende kapitaalsubsidies in resultaat | C33: =-230.52 -> -230.52
B34: Cashflow van het eigen vermogen voor belasting | C34: =C24+C25+C31 -> 510813.18 | D34: =D24+D25+D31 -> 228285.72
B35: Belastingen | E35: [67/77]
B36: Vennootschapsbelasting | C36: 69442.88 | D36: 17837.65
B37: Cashflow van het eigen vermogen | C37: =C34-C36 -> 441370.3 | D37: =D34-D36 -> 210448.07
B38: PLUS intresten uit vreemd vermogen | C38: 64704.91 | D38: 62433.75 | E38: [65]
B39: Potentiële operationele cashflow | C39: =C37+C38 -> 506075.21 | D39: =D37+D38 -> 272881.82

Sheet Op
A1: Component | B1: Bedrag (€) | C1: Code | D1: Type | E1: 2025 | F1: 2024
A2: Potentiële operationele cashflow | B2: =Pot!C16 -> 486640.5
A3: Toename (-) van operationele activa korte termijn | B3: =B4+B5+B6 -> -33188.21
A4: Mutatie | B4: =-(E4-F4) -> 10904.42 | C4: [30/36] | D4: mutatie | E4: 36661.58 | F4: 47566 | H4: Toename: geld om activa te financiering
A5: Mutatie | B5: =-(E5-F5) -> -37523.25 | C5: [40/41] | D5: mutatie | E5: =407047.76+131.61 -> 407179.37 | F5: 369656.12
A6: Mutatie | B6: =-(E6-F6) -> -6569.38 | C6: [490/1] | D6: mutatie | E6: 6569.38 | F6: 0
A7: Toename/afname van operationele passiva | B7: =B8+B9+B11+B10+B12 -> 140716.34
A8: Mutatie | B8: =E8-F8 -> 35708.12 | C8: [42] | D8: mutatie | E8: 172029.55 | F8: 136321.43
A9: Mutatie | B9: =E9-F9 -> -4182.15 | C9: [44] | D9: mutatie | E9: 144903.83 | F9: 149085.98 | H9: Afname, geld om passiva te betalen
A10: Mutatie | B10: =E10-F10 -> 105949.21 | C10: [45] | D10: mutatie | E10: 145359.25 | F10: 39410.04
A11: Mutatie | B11: =E11-F11 -> 1000 | C11: [46] | D11: mutatie | E11: 1000 | F11: 0
A12: Mutatie | B12: =E12-F12 -> 2241.16 | C12: [492/3] | D12: mutatie | E12: 4490.54 | F12: 2249.38
A13: Cashflow uit operationele activiteiten | B13: =B2+B3+B7 -> 594168.63
M14: Liquide middelen | N14: 54/58 | O14: 162734.99 | P14: 4665.03 | Q14: =O14-P14 -> 158069.96
A16: Toename (-) van operationele activa korte termijn | B16: =B3 -> -33188.21
A17: Toename/afname van operationele passiva | B17: =B7 -> 140716.34
B18: =SUM(B16:B17) -> 107528.13
A23: Component | B23: Bedrag (€) | C23: Code | D23: Type | E23: 2025 | F23: 2024
A24: Potentiële operationele cashflow | B24: =Pot!C39 -> 506075.21
A25: MIN Toename van operationele activa korte termijn | B25: =B26+B27+B28 -> -33188.21
A26: Mutatie | B26: =-(E26-F26) -> 10904.42 | C26: [30/36] | D26: mutatie | E26: 36661.58 | F26: 47566
A27: Mutatie | B27: =-(E27-F27) -> -37523.25 | C27: [40/41] | D27: mutatie | E27: =407047.76+131.61 -> 407179.37 | F27: 369656.12
A28: Mutatie | B28: =-(E28-F28) -> -6569.38 | C28: [490/1] | D28: mutatie | E28: 6569.38 | F28: 0
A29: Toename van operationele passiva | B29: =B30+B31+B32+B33+B34 -> 172399.86
A30: Mutatie | B30: =E30-F30 -> -4182.15 | C30: [44] | D30: mutatie | E30: 144903.83 | F30: 149085.98
A31: Mutatie | B31: =E31-F31 -> 8700 | C31: [454/49] | D31: mutatie | E31: 13524.62 | F31: 4824.62
A32: Mutatie | B32: =E32-F32 -> 97249.21 | C32: [450/3] | D32: mutatie | E32: 131834.63 | F32: 34585.42
A33: Mutatie | B33: =E33-F33 -> 1000 | C33: [46] | D33: mutatie | E33: 1000 | F33: 0
A34: Mutatie | B34: =E34-F34 -> 69632.8 | C34: [47/8] | D34: mutatie | E34: 69632.8 | F34: 0 | G34: Uitkering
A35: Mutatie | B35: =E35-F35 -> 2241.16 | C35: [492/3] | D35: mutatie | E35: 4490.54 | F35: 2249.38
A36: Correcties
A37: Waardeverminderingen op handelsvorderingen en voorraden | B37: -40766 | E37: 7360 | F37: [631/4]
A38: Cashflow uit operationele activiteiten | B38: =B24+B25+B29 -> 645286.86
A50: Toename (-) van operationele activa korte termijn | B50: =B25 -> -33188.21
A51: Toename/afname van operationele passiva | B51: =B29 -> 172399.86
A52: Verschil | B52: =SUM(B50:B51) -> 139211.65

Sheet invest
A1: Indirecte Methode
A2: Omschrijving | B2: Bedrag (€) | C2: Code | D2: Toelichting | E2: 2025 | F2: 2024
A3: Mutatie immateriële vaste activa | B3: =(E3-F3) -> 48133.52 | C3: [20/21] | D3: Balansmutatie | E3: 48133.52 | F3: 0
A4: Mutatie materiële vaste activa | B4: =E4-F4 -> 350939.59 | C4: [22/27] | D4: Balansmutatie | E4: 1600763.4 | F4: 1249823.8
A5: Correctie: afschrijvingen MVA | B5: -151310.91 | C5: [8279] | D5: Tegenboeking afschrijvingen
A6: Correctie: afschrijvingen IMVA | B6: -1664.48 | C6: [8079] | D6: Tegenboeking afschrijvingen
A7: Totaal correcties | B7: =SUM(B3:B7) -> 246097.72
A11: Indirecte Methode
A12: Omschrijving | B12: Bedrag (€) | C12: Code | D12: Toelichting | E12: 2025 | F12: 2024
A13: Mutatie immateriële vaste activa | B13: =(E13-F13) -> 48133.52 | C13: [20/21] | D13: Balansmutatie | E13: 48133.52 | F13: 0
A14: Mutatie materiële vaste activa | B14: =E14-F14 -> 350939.59 | C14: [22/27] | D14: Balansmutatie | E14: 1600763.4 | F14: 1249823.8
A15: Correcties
A16: Correctie: afschrijvingen MVA | B16: -151310.91 | C16: [8279]
A17: Correctie: afschrijvingen IMVA | B17: -1664.48 | C17: [8079]
A18: Waardeverminderingen op handelsvorderingen en voorraden | B18: -40766 | C18: [631/4]
A19: Minderwrde realisatie vorder. | B19: -4646.61 | C19: [642]
A20: Herwaarderingsmeerwaarden | B20: -180673.33 | C20: [12]
A21: Totaal correcties | B21: =SUM(B16:B20) -> -379061.33
B22: =B13+B14+B21 -> 20011.78

Sheet Vrije
A1: Component | B1: Bedrag (€)
A2: Cashflow uit operationele activiteiten | B2: =Op!B13 -> 594168.63
A3: Cashflow uit investeringsactiviteiten | B3: -246097.72
A4: Vrije cashflow | B4: =B2+B3 -> 348070.91
B8: 2025 | C8: 2024
A9: Liquide middelen | B9: 162734.99 | C9: 4665.03
A10: Cashflow | B10: =B9-C9 -> 158069.96
A14: Component | B14: Bedrag (€)
A15: Cashflow uit operationele activiteiten | B15: =Op!B38 -> 645286.86
A16: Cashflow uit investeringsactiviteiten | B16: =-invest!B22 -> -20011.78
A17: Vrije cashflow | B17: =B15+B16 -> 625275.08

Sheet Fin
B1: Omschrijving | C1: € | D1: MAR-Code | E1: 2025 | F1: 2024
B2: A Toename Eigen Vermogen | C2: =E2-F2 -> 320968.82 | E2: 645456.8 | F2: 324487.98
B3: Herwaarderingsmeerwaarden | C3: =E3-F3 -> 180673.33 | D3: [12] | E3: 180673.33 | F3: 0
B4: Reserves | C4: =E4-F4 -> 201603.73 | D4: [13] | E4: 201603.73
B5: Overgedragen winst/verlies | C5: =E5-F5 -> -80077.72 | D5: [140/141] | E5: 194410.26 | F5: 274487.98
B6: Kapitaalsubsidies | C6: =E6-F6 -> 18769.48 | D6: [15] | E6: 18769.48
B7: B Correctie te bestemmen resultaat | C7: =C8+C9+C10 -> -121175.34
B8: – Winst van het boekjaar/+verlies van het boekjaar | C8: -201022.54 | D8: [9904]
B9: Uit te keren winst | C9: 80077.72 | D9: [694/7]
B10: Verrekende kapitaalsubsidies in resultaat | C10: =-230.52 -> -230.52 | D10: [9125]
B11: 1 Kasstroom uit financieringsactiviteiten met het eigen vermogen (A+B) | C11: =C2+C7 -> 199793.48
B12: Toename Voorzieningen en belastingen | C12: =E12-F12 -> 12614.08 | D12: [16] | E12: 21541.06 | F12: 8926.98
B13: Correcties
B14: – Voorzieningen voor risico’s en kosten | C14: -12614.08 | D14: [635/9]
B15: Onttrekkingen aan de uitgestelde belastingen | C15: 743.15 | D15: [780]
B16: – Overboekingen naar de uitgestelde belastingen | C16: -15531.25 | D16: [680]
B17: 2 Kasstroom uit financieringsactiviteiten met voorzieningen en belastingen | C17: =SUM(C12:C16) -> -14788.1
B18: Toename financiële schuld LT | C18: =E18-F18 -> 31053.78 | D18: [170/4] | E18: 1042282.9 | F18: 1011229.2
B19: Toename financiële schuld KT | C19: 172029.55 | D19: [42]
B20: Correcties intresten (berekend als TRK) | C20: 3740.54 | D20: [492]
B21: Toename schuld aandeelhouder | C21: 69632.8 | D21: [47]
B22: Correcties
B23: – Uit te keren winst | C23: -80077.72 | D23: [694/7]
B24: 3 Kasstroom uit financieringsactiviteiten met financiële schulden | C24: =SUM(C18:C23) -> 196378.95
B25: Cashflow uit financieringsactiviteit (1+2+3) | C25: =C11+C17+C24 -> 381384.33
B35: Omschrijving | C35: € | D35: MAR-Code | E35: 2025 | F35: 2024
B36: 1 Eigen Vermogen | C36: =C37+C41 -> -9306.37
B37: Mutatie | C37: =C38+C39+C40 -> 302199.34 | E37: 645456.8 | F37: 324487.98
B38: Herwaarderingsmeerwaarden | C38: =E38-F38 -> 180673.33 | D38: [12] | E38: 180673.33 | F38: 0
B39: Reserves | C39: =E39-F39 -> 201603.73 | D39: [13] | E39: 201603.73
B40: Overgedragen winst/verlies | C40: =E40-F40 -> -80077.72 | D40: [140/141] | E40: 194410.26 | F40: 274487.98
B41: Correcties | C41: =C42+C43+C44+C45 -> -311505.71
B42: – Winst van het boekjaar/+verlies van het boekjaar | C42: -154428.79 | D42: [9905]
B43: – Herwaarderingsmeerwaarden | C43: =-C38 -> -180673.33 | D43: [12]
B44: – Belastingvrije reserves | C44: -46036.39 | D44: [132]
B45: – Dividend uitkering | C45: 69632.8 | D45: [47]
B46: 2 Kapitaalsubsidies | C46: =C48 -> 18769.48
B47: Mutatie
B48: Kapitaalsubsidies | C48: =E48-F41 -> 18769.48 | D48: [15] | E48: 18769.48
B49: 3 Voorzieningen en uitgestelde belasting | C49: =C51+C53+C54 -> 0
B50: Mutatie
B51: Voorzieningen en uitgestelde belasting | C51: =E51-F51 -> 27959.54 | D51: [16] | E51: 36886.52 | F51: 8926.98
B52: Correcties
B53: – Voorzieningen voor risico’s en kosten | C53: -12614.08 | D53: [635/9]
B54: – Uitgestelde belastingen | C54: -15345.46 | D54: [168]
B55: 4 Financiële schulden | C55: =C57+C58+C60 -> -69359.25
B56: Mutaties
B57: Financiële schuld LT | C57: =E57-F57 -> 31053.78 | D57: [170/4] | E57: 1042282.9 | F57: 1011229.2
B58: – Financiële schuld KT | C58: =-(E58-F58) -> -35708.12 | D58: [42] | E58: 172029.55 | F58: 136321.43
B59: Correcties
B60: – Intresten uit vreemd vermogen | C60: -64704.91 | D60: [65]
B61: Cashflow uit financieringsactiviteit (1+2+3+4) | C61: =C36+C46+C49+C55 -> -59896.14
B66: B Correctie te bestemmen resultaat | C66: =C42+C68+C69 -> -74581.59
B68: Uit te keren winst | C68: 80077.72 | D68: [694/7]
B69: Verrekende kapitaalsubsidies in resultaat | C69: =-230.52 -> -230.52 | D69: [9125]
B70: 1 Kasstroom uit financieringsactiviteiten met het eigen vermogen (A+B) | C70: =C37+C66 -> 227617.75
B71: Onttrekkingen aan de uitgestelde belastingen | C71: 743.15 | D71: [780]
B72: – Overboekingen naar de uitgestelde belastingen | C72: -15531.25 | D72: [680]
B73: 2 Kasstroom uit financieringsactiviteiten met voorzieningen en belastingen | C73: =SUM(C51:C72) -> 19480.62
B76: Correcties intresten (berekend als TRK) | C76: 3740.54 | D76: [492]
B77: Toename schuld aandeelhouder | C77: 69632.8 | D77: [47]
B78: Correcties
B79: – Uit te keren winst | C79: -80077.72 | D79: [694/7]
B80: 3 Kasstroom uit financieringsactiviteiten met financiële schulden | C80: =SUM(C57:C79) -> 101616.11
B81: Cashflow uit financieringsactiviteit (1+2+3) | C81: =C70+C73+C80 -> 348714.48

Sheet KSS
A1: Component | B1: Bedrag (€)
A2: Vrije Cashflow | B2: =Vrije!B4 -> 348070.91
A3: Cashflow uit financieringsactiviteit | B3: =Fin!C25 -> 381384.33
A4: Totale Cashflow | B4: =SUM(B2:B3) -> 729455.24
A12: Component | B12: Bedrag (€)
A13: Vrije Cashflow | B13: =Vrije!B15 -> 645286.86
A14: Cashflow uit financieringsactiviteit | B14: =Fin!C61 -> -59896.14
A15: Totale Cashflow | B15: =B13-B14 -> 705183
D21: 158070
D22: =B15-D21 -> 547113

Sheet KSS_full
A1: Cashflow Analysis | B1: 2025 | C1: 2024 | D1: MAR Code | E1: 2025 | F1: 2024
A2: Winst van het boekjaar voor belastingen | B2: 285253.52 | C2: 56127.31 | D2: [9903]
A3: PLUS niet-kaskosten | B3: =B4+B5+B6+B7 -> 221886.72 | C3: =C4+C5+C6+C7 -> 172158.41
A4: Afschrijvingen | B4: 152975.39 | C4: 155871.43 | D4: [630]
A5: Waardeverminderingen op handelsvorderingen en voorraden | B5: 40766 | C5: 7360 | D5: [631/4]
A6: Voorzieningen voor risico’s en kosten | B6: 12614.08 | C6: 8926.98 | D6: [635/8]
A7: Overboeking naar de uitgestelde belastingen | B7: 15531.25 | D7: [680]
A8: MIN niet-kasopbrengsten | B8: 0 | C8: 0
A9: Cashflow van het eigen vermogen voor belasting | B9: =B2+B3 -> 507140.24 | C9: =C2+C3+C8 -> 228285.72 | I9: Investering
A10: Belastingen | D10: [67/77] | I10: Aankoop
A11: Vennootschapsbelasting | B11: 69442.88 | C11: 17837.65 | I11: Goodwil | J11: 49798
A12: Cashflow van het eigen vermogen | B12: =B9-B11 -> 437697.36 | C12: =C9-C11 -> 210448.07 | I12: Correctie | J12: -1664.48
A13: PLUS intresten uit vreemd vermogen | B13: 64704.91 | C13: 62433.75 | D13: [65] | I13: Machine Overname | J13: 150000
A14: Potentiële operationele cashflow | B14: =B12+B13 -> 502402.27 | C14: =C12+C13 -> 272881.82 | I14: Correctie | J14: -10027.4
A15: Potentiële operationele cashflow | B15: =B14 -> 502402.27 | I15: Boermachine | J15: 2800
A16: Min Mutaties bedrijfsactiva (operationele activa korte termijn) | B16: =B17+B18+B19 -> -33188.21 | E16: 2025 | F16: 2024 | I16: Correctie | J16: -47.56
A17: Voorraden en BIU | B17: =-(E17-F17) -> 10904.42 | C17: [30/36] | D17: mutatie | E17: 36661.58 | F17: 47566 | I17: Freesmachine | J17: =165000+1750+100 -> 166850
A18: Voorderingen | B18: =-(E18-F18) -> -37523.25 | C18: [40/41] | D18: mutatie | E18: =407047.76+131.61 -> 407179.37 | F18: 369656.12 | I18: correctie | J18: =-2001.96-21.23-1.21 -> -2024.4
A19: Overlopende rekeningen | B19: =-(E19-F19) -> -6569.38 | C19: [490/1] | D19: mutatie | E19: 6569.38 | F19: 0 | I19: Leasing | J19: 68035.12
A20: Plus Mutatie bedrijfspasiva (operationele passiva) | B20: =B21+B22+B23+B24+B25+B26 -> 174641.02 | I20: Correctie | J20: -6000
A21: Leveranciers | B21: =E21-F21 -> -4182.15 | C21: [44] | D21: mutatie | E21: 144903.83 | F21: 149085.98 | I21: Inrichtinge gebouwen | J21: 20628.5
A22: Bezoldigingen | B22: =E22-F22 -> 8700 | C22: [454/9] | D22: mutatie | E22: 13524.62 | F22: 4824.62 | I22: Correctie | J22: -51.78
A23: Belastingen | B23: =E23-F23 -> 97249.21 | C23: [450/3] | D23: mutatie | E23: 131834.63 | F23: 34585.42 | I23: Totaal Aankoop | J23: =SUM(J11:J22) -> 438296
A24: Vooruitbetalingen op bestellingen | B24: =E24-F24 -> 1000 | C24: [46] | D24: mutatie | E24: 1000 | F24: 0 | I24: Verkoop
A25: Overige schulden | B25: =E25-F25 -> 69632.8 | C25: [48] | E25: 69632.8 | F25: 0 | I25: Machine B | J25: -185000
A26: Overlopende rekeningen | B26: =E26-F26 -> 2241.16 | C26: [492/3] | D26: mutatie | E26: 4490.54 | F26: 2249.38 | I26: Correctie | J26: 87875
A27: Correcties | B27: =B28 -> -40766 | I27: Totaal Verkoop | J27: =SUM(J25:J26) -> -97125
A28: Waardeverminderingen op handelsvorderingen en voorraden | B28: -40766 | C28: [631/4] | I28: Cashflow uit inv.act | J28: =J23+J27 -> 341171
A29: Cashflow uit operationele activiteiten | B29: =B15+B16+B20+B27 -> 603089.08 | I29: Cashflow uit operationele activiteiten | J29: =B29 -> 603089.08
A30: Indirecte Methode | I30: Vrije cashflow' | J30: =J29-J28 -> 261918.08
A31: Omschrijving | B31: Bedrag (€) | C31: Code | D31: Toelichting | E31: 2025 | F31: 2024 | I31: fin
A32: Mutaties | B32: =B33+B34 -> 399073.11
A33: Immateriële vaste activa | B33: =(E33-F33) -> 48133.52 | C33: [20/21] | D33: Balansmutatie | E33: 48133.52 | F33: 0 | I33: verschil | J33: =J30-B76 -> 103848.12
A34: Materiële vaste activa | B34: =E34-F34 -> 350939.59 | C34: [22/27] | D34: Balansmutatie | E34: 1600763.4 | F34: 1249823.8
A35: Correcties | B35: =B36+B37+B38 -> -333648.72
A36: Afschrijvingen MVA | B36: -151310.91 | C36: [6300/2] | D36: [8279]
A37: Afschrijvingen IMVA | B37: -1664.48 | C37: [8079]
A38: Herwaarderingsmeerwaarden | B38: -180673.33 | C38: [12]
A39: cashflow uit investeringsactiviteiten | B39: =B32+B35 -> 65424.39
A40: Cashflow uit operationele activiteiten | B40: =B29 -> 603089.08
A41: cashflow uit investeringsactiviteiten | B41: =B39 -> 65424.39
A42: Vrije cashflow | B42: =B29-B39 -> 537664.69
A44: 1 Eigen Vermogen | B44: =B45+B49 -> -9306.37
A45: Mutatie | B45: =B46+B47+B48 -> 302199.34 | D45: 645456.8 | E45: 324487.98
A46: Herwaarderingsmeerwaarden | B46: =D46-E46 -> 180673.33 | C46: [12] | D46: 180673.33 | E46: 0
A47: Reserves | B47: =D47-E47 -> 201603.73 | C47: [13] | D47: 201603.73
A48: Overgedragen winst/verlies | B48: =D48-E48 -> -80077.72 | C48: [140/141] | D48: 194410.26 | E48: 274487.98
A49: Correcties | B49: =B50+B51+B52+B53 -> -311505.71
A50: – Winst van het boekjaar/+verlies van het boekjaar | B50: -154428.79 | C50: [9905]
A51: – Herwaarderingsmeerwaarden | B51: =-B46 -> -180673.33 | C51: [12]
A52: – Belastingvrije reserves | B52: -46036.39 | C52: [132]
A53: – Dividend uitkering | B53: 69632.8 | C53: [47] | D53: of [694]
A54: 2 Kapitaalsubsidies | B54: =B56 -> 18769.48
A55: Mutatie
A56: Kapitaalsubsidies | B56: =D56-E49 -> 18769.48 | C56: [15] | D56: 18769.48
A57: 3 Voorzieningen en uitgestelde belasting | B57: =B59+B61+B62 -> 0
A58: Mutatie
A59: Voorzieningen en uitgestelde belasting | B59: =D59-E59 -> 27959.54 | C59: [16] | D59: 36886.52 | E59: 8926.98
A60: Correcties
A61: – Voorzieningen voor risico’s en kosten | B61: -12614.08 | C61: [635/9]
A62: – Uitgestelde belastingen | B62: -15345.46 | C62: [168]
A63: 4 Financiële schulden | B63: =B65+B66+B68 -> -69359.25
A64: Mutaties
A65: Financiële schuld LT | B65: =D65-E65 -> 31053.78 | C65: [170/4] | D65: 1042282.9 | E65: 1011229.2
A66: – Financiële schuld KT | B66: =-(D66-E66) -> -35708.12 | C66: [42] | D66: 172029.55 | E66: 136321.43
A67: Correcties
A68: – Intresten uit vreemd vermogen | B68: -64704.91 | C68: [65]
A69: Cashflow uit financieringsactiviteit (1+2+3+4) | B69: =B44+B54+B57+B63 -> -59896.14
A72: Component | B72: Bedrag (€)
A73: Vrije Cashflow | B73: =B42 -> 537664.69
A74: Cashflow uit financieringsactiviteit | B74: =B69 -> -59896.14
A75: Totale Cashflow | B75: =B73-B74 -> 597560.83 | C75: 2025 | D75: 2024
A76: Mutatie liquide middelen | B76: =C76-D76 -> 158069.96 | C76: 162734.99 | D76: 4665.03
A77: Verschil | B77: =B75-B76 -> 439490.87

Sheet KSS_FF
B1: Cashflow Analysis | C1: 2025 | D1: 2024 | E1: MAR Code
B2: Winst van het boekjaar voor belastingen | C2: =201022.54+69442.88 -> 270465.42 | D2: 56127.31 | E2: [9904]+[67/77]
B3: PLUS niet-kaskosten | C3: =SUM(C4:C7) -> 221886.72 | D3: =SUM(D4:D7) -> 172158.41
B4: Afschrijvingen | C4: 152975.39 | D4: 155871.43 | E4: [630]
B5: Waardeverminderingen op handelsvorderingen en voorraden | C5: 40766 | D5: 7360 | E5: [631/4] | G5: MAR CODE 744 VMA winst?
B6: Voorzieningen voor risico’s en kosten | C6: 12614.08 | D6: 8926.98 | E6: [635/8]
B7: Overboeking naar de uitgestelde belastingen | C7: 15531.25 | E7: [680] | G7: 201022.54
B8: MIN niet-kasopbrengsten | C8: =C9+C10 -> -973.67 | G8: 69442.88
B9: Onttrekking aan de uitgestelde belastingen | C9: =-743.15 -> -743.15 | E9: [780] | G9: 15531.25
B10: Aangerekende kapitaalsubsidies in resultaat | C10: =-230.52 -> -230.52 | G10: -743.15
B11: Cashflow van het eigen vermogen | C11: =C2+C3+C8 -> 491378.47 | D11: =D2+D3+D8 -> 228285.72 | G11: =SUM(G7:G10) -> 285253.52
B12: PLUS intresten uit vreemd vermogen | C12: 64704.91 | D12: 62433.75 | E12: [65] | G12: -69442.88
B13: Potentiële operationele cashflow voor belasting | C13: =C11+C12 -> 556083.38 | D13: =D11+D12 -> 290719.47 | G13: -15531.25
B14: Vennootschapsbelasting | C14: 69442.88 | D14: 17837.65 | G14: 743.15
B15: Potentiële operationele cashflow | C15: =C13-C14 -> 486640.5 | D15: =D13-D14 -> 272881.82 | G15: =SUM(G11:G14) -> 201022.54
B18: Potentiële operationele cashflow | C18: =C15 -> 486640.5
B19: Min Mutaties bedrijfsactiva (operationele activa korte termijn) | C19: =C20+C21+C22 -> -33188.21 | F19: 2025 | G19: 2024
B20: Voorraden en BIU | C20: =-(F20-G20) -> 10904.42 | D20: [30/36] | E20: mutatie | F20: 36661.58 | G20: 47566
B21: Voorderingen | C21: =-(F21-G21) -> -37523.25 | D21: [40/41] | E21: mutatie | F21: =407047.76+131.61 -> 407179.37 | G21: 369656.12
B22: Overlopende rekeningen | C22: =-(F22-G22) -> -6569.38 | D22: [490/1] | E22: mutatie | F22: 6569.38 | G22: 0
B23: Plus Mutatie bedrijfspasiva (operationele passiva) | C23: =C24+C25+C26+C27+C28+C29 -> 174641.02
B24: Leveranciers | C24: =F24-G24 -> -4182.15 | D24: [44] | E24: mutatie | F24: 144903.83 | G24: 149085.98
B25: Bezoldigingen | C25: =F25-G25 -> 8700 | D25: [454/9] | E25: mutatie | F25: 13524.62 | G25: 4824.62
B26: Belastingen | C26: =F26-G26 -> 97249.21 | D26: [450/3] | E26: mutatie | F26: 131834.63 | G26: 34585.42
B27: Vooruitbetalingen op bestellingen | C27: =F27-G27 -> 1000 | D27: [46] | E27: mutatie | F27: 1000 | G27: 0
B28: Overige schulden | C28: =F28-G28 -> 69632.8 | D28: [48] | F28: 69632.8 | G28: 0
B29: Overlopende rekeningen | C29: =F29-G29 -> 2241.16 | D29: [492/3] | E29: mutatie | F29: 4490.54 | G29: 2249.38
B30: Correcties | C30: =C31 -> -40766
B31: Waardeverminderingen op handelsvorderingen en voorraden | C31: -40766 | D31: [631/4]
B32: Cashflow uit operationele activiteiten | C32: =C18+C19+C23+C30 -> 587327.31
B34: Indirecte Methode
B35: Omschrijving | C35: Bedrag (€) | D35: Code | E35: Toelichting | F35: 2025 | G35: 2024
B36: Mutaties | C36: =C37+C38 -> 399073.11
B37: Immateriële vaste activa | C37: =(F37-G37) -> 48133.52 | D37: [20/21] | E37: Balansmutatie | F37: 48133.52 | G37: 0
B38: Materiële vaste activa | C38: =F38-G38 -> 350939.59 | D38: [22/27] | E38: Balansmutatie | F38: 1600763.4 | G38: 1249823.8
B39: Correcties | C39: =C40+C41+C42 -> -333648.72
B40: Afschrijvingen MVA | C40: -151310.91 | D40: [6300/2] | E40: [8279]
B41: Afschrijvingen IMVA | C41: -1664.48 | D41: [8079]
B42: Herwaarderingsmeerwaarden | C42: -180673.33 | D42: [12]
B43: cashflow uit investeringsactiviteiten | C43: =C36+C39 -> 65424.39
B44: Cashflow uit operationele activiteiten | C44: =C32 -> 587327.31
B45: cashflow uit investeringsactiviteiten | C45: =C43 -> 65424.39
B46: Vrije cashflow | C46: =C44-C45 -> 521902.92
B49: Omschrijving | C49: € | D49: MAR-Code | E49: 2025 | F49: 2024
B50: A Toename Eigen Vermogen | C50: =E50-F50 -> 320968.82 | E50: 645456.8 | F50: 324487.98
B51: Herwaarderingsmeerwaarden | C51: =E51-F51 -> 180673.33 | D51: [12] | E51: 180673.33 | F51: 0
B52: Reserves | C52: =E52-F52 -> 201603.73 | D52: [13] | E52: 201603.73
B53: Overgedragen winst/verlies | C53: =E53-F53 -> -80077.72 | D53: [140/141] | E53: 194410.26 | F53: 274487.98
B54: Kapitaalsubsidies | C54: =E54-F54 -> 18769.48 | D54: [15] | E54: 18769.48
B55: B Correctie te bestemmen resultaat | C55: =C56+C57+C58 -> -121175.34
B56: – Winst van het boekjaar/+verlies van het boekjaar | C56: -201022.54 | D56: [9904]
B57: Uit te keren winst | C57: 80077.72 | D57: [694/7]
B58: Verrekende kapitaalsubsidies in resultaat | C58: =-230.52 -> -230.52 | D58: [9125]
B59: 1 Kasstroom uit financieringsactiviteiten met het eigen vermogen (A+B) | C59: =C50+C55 -> 199793.48
B60: Toename Voorzieningen en uitgestelde belastingen | C60: =E60-F60 -> 27959.54 | D60: [16] | E60: 36886.52 | F60: 8926.98
B61: Correcties
B62: – Voorzieningen voor risico’s en kosten | C62: -12614.08 | D62: [635/9]
B63: Onttrekkingen aan de uitgestelde belastingen | C63: 743.15 | D63: [780]
B64: – Overboekingen naar de uitgestelde belastingen | C64: -15531.25 | D64: [680]
B65: 2 Kasstroom uit financieringsactiviteiten met voorzieningen en belastingen | C65: =SUM(C60:C64) -> 557.36
A66: – Financiële kaskosten van het vreemd vermogen voor | B66: – Financiële kaskosten van het vreemd vermogen voor belasting | C66: -64704.91 | D66: [65/66B]
A67: belasting | B67: Toename financiële schuld LT | C67: =E67-F67 -> 31053.78 | D67: [170/4] | E67: 1042282.9 | F67: 1011229.2
B68: Toename financiële schuld KT | C68: =E68-F68 -> 35708.12 | D68: [42] | E68: 172029.55 | F68: 136321.43
B69: Toename schuld aandeelhouder | C69: 69632.8 | D69: [47]
B70: Correcties
B71: – Uit te keren winst | C71: -80077.72 | D71: [694/7]
B72: 3 Kasstroom uit financieringsactiviteiten met financiële schulden | C72: =SUM(C66:C71) -> -8387.93
B73: Cashflow uit financieringsactiviteit (1+2+3) | C73: =C59+C65+C72 -> 191962.91
B75: Component | C75: Bedrag (€)
B76: Vrije Cashflow | C76: =C46 -> 521902.92
B77: Cashflow uit financieringsactiviteit | C77: =C73 -> 191962.91
B78: Totale Cashflow | C78: =C76-C77 -> 329940.01 | D78: 2025 | E78: 2024
B79: Mutatie liquide middelen | C79: =D79-E79 -> 158069.96 | D79: 162734.99 | E79: 4665.03
B80: Verschil | C80: =C78-C79 -> 171870.05

Sheet KSS_FF (2)
B1: Cashflow Analysis | C1: 2025 | D1: 2024 | E1: MAR Code
B2: Winst van het boekjaar voor belastingen | C2: 285253.52 | D2: 56127.31 | E2: [9903]
B3: PLUS niet-kaskosten | C3: =SUM(C4:C8) -> 226533.33 | D3: =SUM(D4:D7) -> 172158.41
B4: Afschrijvingen | C4: 152975.39 | D4: 155871.43 | E4: [630]
B5: Waardeverminderingen op handelsvorderingen en voorraden | C5: 40766 | D5: 7360 | E5: [631/4] | G5: MAR CODE 744 VMA winst?
B6: Voorzieningen voor risico’s en kosten | C6: 12614.08 | D6: 8926.98 | E6: [635/8]
B7: Overboeking naar de uitgestelde belastingen | C7: 15531.25 | E7: [680] | G7: 201022.54
B8: Minderwaarde handelsvorderingen | C8: 4646.61
B9: MIN niet-kasopbrengsten | C9: =C10+C11 -> -973.67 | G9: 69442.88
B10: Onttrekking aan de uitgestelde belastingen | C10: =-743.15 -> -743.15 | E10: [780] | G10: 15531.25
B11: Aangerekende kapitaalsubsidies in resultaat | C11: =-230.52 -> -230.52 | G11: -743.15
B12: Cashflow van het eigen vermogen | C12: =C2+C3+C9 -> 510813.18 | D12: =D2+D3+D9 -> 228285.72 | G12: =SUM(G7:G11) -> 285253.52
B13: PLUS intresten uit vreemd vermogen | C13: 64704.91 | D13: 62433.75 | E13: [65] | G13: -69442.88
B14: Potentiële operationele cashflow voor belasting | C14: =C12+C13 -> 575518.09 | D14: =D12+D13 -> 290719.47 | G14: -15531.25
B15: Vennootschapsbelasting | C15: 69442.88 | D15: 17837.65 | G15: 743.15
B16: Potentiële operationele cashflow | C16: =C14-C15 -> 506075.21 | D16: =D14-D15 -> 272881.82 | G16: =SUM(G12:G15) -> 201022.54
B19: Potentiële operationele cashflow | C19: =C16 -> 506075.21
B20: Min Mutaties bedrijfsactiva (operationele activa korte termijn) | C20: =C21+C22+C23 -> -33188.21 | F20: 2025 | G20: 2024
B21: Voorraden en BIU | C21: =-(F21-G21) -> 10904.42 | D21: [30/36] | E21: mutatie | F21: 36661.58 | G21: 47566
B22: Voorderingen | C22: =-(F22-G22) -> -37523.25 | D22: [40/41] | E22: mutatie | F22: =407047.76+131.61 -> 407179.37 | G22: 369656.12
B23: Overlopende rekeningen | C23: =-(F23-G23) -> -6569.38 | D23: [490/1] | E23: mutatie | F23: 6569.38 | G23: 0
B24: Plus Mutatie bedrijfspasiva (operationele passiva) | C24: =C25+C26+C27+C28+C29+C30 -> 105008.22
B25: Leveranciers | C25: =F25-G25 -> -4182.15 | D25: [44] | E25: mutatie | F25: 144903.83 | G25: 149085.98
B26: Bezoldigingen | C26: =F26-G26 -> 8700 | D26: [454/9] | E26: mutatie | F26: 13524.62 | G26: 4824.62
B27: Belastingen | C27: =F27-G27 -> 97249.21 | D27: [450/3] | E27: mutatie | F27: 131834.63 | G27: 34585.42
B28: Vooruitbetalingen op bestellingen | C28: =F28-G28 -> 1000 | D28: [46] | E28: mutatie | F28: 1000 | G28: 0
B29: Overige schulden | D29: [48] | F29: 69632.8 | G29: 0
B30: Overlopende rekeningen | C30: =F30-G30 -> 2241.16 | D30: [492/3] | E30: mutatie | F30: 4490.54 | G30: 2249.38
B31: Correcties | C31: =C32+C33 -> -45412.61
B32: Waardeverminderingen op voorraden | C32: -40766 | D32: [631/2]
B33: Waardeverminderingen op handelsvorderingen | C33: =-C8 -> -4646.61 | D33: [633/4]
B34: Cashflow uit operationele activiteiten | C34: =C19+C20+C24+C31 -> 532482.61
B36: Indirecte Methode
B37: Omschrijving | C37: Bedrag (€) | D37: Code | E37: Toelichting | F37: 2025 | G37: 2024
B38: Mutaties | C38: =C39+C40 -> 399073.11
B39: Immateriële vaste activa | C39: =(F39-G39) -> 48133.52 | D39: [20/21] | E39: Balansmutatie | F39: 48133.52 | G39: 0
B40: Materiële vaste activa | C40: =F40-G40 -> 350939.59 | D40: [22/27] | E40: Balansmutatie | F40: 1600763.4 | G40: 1249823.8
B41: Correcties | C41: =C42+C43+C44+G45 -> -271523.72
B42: Afschrijvingen MVA | C42: -151310.91 | D42: [6300/2] | E42: [8279]
B43: Afschrijvingen IMVA | C43: -1664.48 | D43: [8079]
B44: Herwaarderingsmeerwaarden | C44: -180673.33 | D44: [12]
B45: Meerwaarden | G45: 62125
B46: cashflow uit investeringsactiviteiten | C46: =C38+C41 -> 127549.39
B47: Cashflow uit operationele activiteiten | C47: =C34 -> 532482.61
B48: cashflow uit investeringsactiviteiten | C48: =C46 -> 127549.39
B49: Vrije cashflow | C49: =C47-C48 -> 404933.22
B52: Omschrijving | C52: € | D52: MAR-Code | E52: 2025 | F52: 2024
B53: A Toename Eigen Vermogen | C53: =E53-F53 -> 320968.82 | E53: 645456.8 | F53: 324487.98
B54: Herwaarderingsmeerwaarden | C54: =E54-F54 -> 180673.33 | D54: [12] | E54: 180673.33 | F54: 0
B55: Reserves | C55: 201603.73 | D55: [13] | E55: 201603.73
B56: Overgedragen winst/verlies | C56: =E56-F56 -> -80077.72 | D56: [140/141] | E56: 194410.26 | F56: 274487.98
B57: Kapitaalsubsidies | C57: =E57-F57 -> 18769.48 | D57: [15] | E57: 18769.48
B58: B Correctie te bestemmen resultaat | C58: =C59+C60+C61 -> -121175.34
B59: – Winst van het boekjaar/+verlies van het boekjaar | C59: -201022.54 | D59: [9904]
B60: Uit te keren winst | C60: 80077.72 | D60: [694/7]
B61: Verrekende kapitaalsubsidies in resultaat | C61: =-230.52 -> -230.52 | D61: [9125]
B62: 1 Kasstroom uit financieringsactiviteiten met het eigen vermogen (A+B) | C62: =C53+C58 -> 199793.48
B63: Toename Voorzieningen en uitgestelde belastingen | C63: =E63-F63 -> 27959.54 | D63: [16] | E63: 36886.52 | F63: 8926.98
B64: Correcties
B65: – Voorzieningen voor risico’s en kosten | C65: -12614.08 | D65: [635/9]
B66: Onttrekkingen aan de uitgestelde belastingen | C66: 743.15 | D66: [780]
B67: – Overboekingen naar de uitgestelde belastingen | C67: -15531.25 | D67: [680]
B68: 2 Kasstroom uit financieringsactiviteiten met voorzieningen en belastingen | C68: =SUM(C63:C67) -> 557.36
A69: – Financiële kaskosten van het vreemd vermogen voor | B69: – Financiële kaskosten van het vreemd vermogen voor belasting | C69: -64704.91 | D69: [65/66B]
A70: belasting | B70: Toename financiële schuld LT | C70: =E70-F70 -> 31053.78 | D70: [170/4] | E70: 1042282.9 | F70: 1011229.2
B71: Toename financiële schuld KT | C71: =E71-F71 -> 35708.12 | D71: [42] | E71: 172029.55 | F71: 136321.43
B72: Toename schuld aandeelhouder | C72: 69632.8 | D72: [47]
B73: Correcties
B74: – Uit te keren winst | C74: -80077.72 | D74: [694/7]
B75: 3 Kasstroom uit financieringsactiviteiten met financiële schulden | C75: =SUM(C69:C74) -> -8387.93
B76: Cashflow uit financieringsactiviteit (1+2+3) | C76: =C62+C68+C75 -> 191962.91
B78: Component | C78: Bedrag (€)
B79: Vrije Cashflow | C79: =C49 -> 404933.22
B80: Cashflow uit financieringsactiviteit | C80: =C76 -> 191962.91
B81: Totale Cashflow | C81: =C79-C80 -> 212970.31 | D81: 2025 | E81: 2024
B82: Mutatie liquide middelen | C82: =D82-E82 -> 158069.96 | D82: 162734.99 | E82: 4665.03
B83: Verschil | C83: =C81-C82 -> 54900.35

Sheet KSS_FF (3)
B1: Cashflow Analysis | C1: 2025 | E1: MAR Code
B2: Winst van het boekjaar voor belastingen | C2: 201022.54 | E2: [9904]
B3: PLUS niet-kaskosten | C3: =SUM(C4:C7) -> 221886.72
B4: Afschrijvingen | C4: 152975.39 | E4: [630]
B5: Waardeverminderingen op handelsvorderingen en voorraden | C5: 40766 | E5: [631/4] | G5: MAR CODE 744 VMA winst?
B6: Voorzieningen voor risico’s en kosten | C6: 12614.08 | E6: [635/8]
B7: Overboeking naar de uitgestelde belastingen | C7: 15531.25 | E7: [680] | G7: 201022.54
B8: MIN niet-kasopbrengsten | C8: =C9 -> -743.15 | G8: 69442.88
B9: Onttrekking aan de uitgestelde belastingen | C9: =-743.15 -> -743.15 | E9: [780] | G9: 15531.25
B10: Cashflow van het eigen vermogen | C10: =C2+C3+C8 -> 422166.11 | G10: =SUM(G7:G9) -> 285996.67
B11: PLUS intresten uit vreemd vermogen | C11: 64704.91 | E11: [65] | G11: -69442.88
B12: Potentiële operationele cashflow voor belasting | C12: =C10+C11 -> 486871.02 | G12: -15531.25
B13: Vennootschapsbelasting | C13: 69442.88 | G13: 743.15
B14: Potentiële operationele cashflow | C14: =C12-C13 -> 417428.14 | G14: =SUM(G10:G13) -> 201765.69
B17: Potentiële operationele cashflow | C17: =C14 -> 417428.14
B18: Min Mutaties bedrijfsactiva (operationele activa korte termijn) | C18: =C19+C20+C21 -> -33188.21 | F18: 2025 | G18: 2024
B19: Voorraden en BIU | C19: =-(F19-G19) -> 10904.42 | D19: [30/36] | E19: mutatie | F19: 36661.58 | G19: 47566
B20: Voorderingen | C20: =-(F20-G20) -> -37523.25 | D20: [40/41] | E20: mutatie | F20: =407047.76+131.61 -> 407179.37 | G20: 369656.12
B21: Overlopende rekeningen | C21: =-(F21-G21) -> -6569.38 | D21: [490/1] | E21: mutatie | F21: 6569.38 | G21: 0
B22: Plus Mutatie bedrijfspasiva (operationele passiva) | C22: =C23+C24+C25+C26+C27+C28 -> 174641.02
B23: Leveranciers | C23: =F23-G23 -> -4182.15 | D23: [44] | E23: mutatie | F23: 144903.83 | G23: 149085.98
B24: Bezoldigingen | C24: =F24-G24 -> 8700 | D24: [454/9] | E24: mutatie | F24: 13524.62 | G24: 4824.62
B25: Belastingen | C25: =F25-G25 -> 97249.21 | D25: [450/3] | E25: mutatie | F25: 131834.63 | G25: 34585.42
B26: Vooruitbetalingen op bestellingen | C26: =F26-G26 -> 1000 | D26: [46] | E26: mutatie | F26: 1000 | G26: 0
B27: Overige schulden | C27: =F27-G27 -> 69632.8 | D27: [48] | F27: 69632.8 | G27: 0
B28: Overlopende rekeningen | C28: =F28-G28 -> 2241.16 | D28: [492/3] | E28: mutatie | F28: 4490.54 | G28: 2249.38
B29: Correcties | C29: 0
B30: Waardeverminderingen op handelsvorderingen en voorraden | C30: 0
B31: Cashflow uit operationele activiteiten | C31: =C17+C18+C22 -> 558880.95
B33: Indirecte Methode
B34: Omschrijving | C34: Bedrag (€) | D34: Code | E34: Toelichting | F34: 2025 | G34: 2024
B35: Mutaties | C35: =C36+C37 -> 400737.59
B36: Aankoop | C36: 49798 | D36: [20/21] | E36: Balansmutatie | F36: 48133.52 | G36: 0
B37: Materiële vaste activa | C37: =F37-G37 -> 350939.59 | D37: [22/27] | E37: Balansmutatie | F37: 1600763.4 | G37: 1249823.8
B38: Correcties | C38: =C39+C40+C41+C42 -> -338295.33
B39: Afschrijvingen MVA | C39: -151310.91 | D39: [6300/2] | E39: [8279]
B40: Afschrijvingen IMVA | C40: -1664.48 | D40: [8079]
B41: Herwaarderingsmeerwaarden | C41: -180673.33 | D41: [12]
B42: Min Geboekte waardevermindering op vordering | C42: -4646.61 | J42: Investering
B43: cashflow uit investeringsactiviteiten | C43: =C35+C38 -> 62442.26 | J43: Aankoop
B44: Cashflow uit operationele activiteiten | C44: =C31 -> 558880.95 | J44: Goodwil | K44: 49798
B45: cashflow uit investeringsactiviteiten | C45: =C43 -> 62442.26 | J45: Correctie | K45: -1664.48
B46: Vrije cashflow | C46: =C44-C45 -> 496438.69 | J46: Machine Overname | K46: 150000
J47: Correctie | K47: -10027.4
J48: Boermachine | K48: 2800
B49: Omschrijving | C49: € | D49: MAR-Code | E49: 2025 | F49: 2024 | J49: Correctie | K49: -47.56
B50: A Toename Eigen Vermogen | C50: =E50-F50 -> 320968.82 | E50: 645456.8 | F50: 324487.98 | J50: Freesmachine | K50: =165000+1750+100 -> 166850
B51: Herwaarderingsmeerwaarden | C51: =E51-F51 -> 180673.33 | D51: [12] | E51: 180673.33 | F51: 0 | J51: correctie | K51: =-2001.96-21.23-1.21 -> -2024.4
B52: Reserves | C52: 201603.73 | D52: [13] | E52: 201603.73 | J52: Leasing | K52: 68035.12
B53: Overgedragen winst/verlies | C53: =E53-F53 -> -80077.72 | D53: [140/141] | E53: 194410.26 | F53: 274487.98 | J53: Correctie | K53: -6000
B54: Kapitaalsubsidies | C54: =E54-F54 -> 18769.48 | D54: [15] | E54: 18769.48 | J54: Inrichtinge gebouwen | K54: 20628.5
B55: B Correctie te bestemmen resultaat | C55: =C56+C57+C58 -> -120714.3 | J55: Correctie | K55: -51.78
B56: – Winst van het boekjaar/+verlies van het boekjaar | C56: -201022.54 | D56: [9904] | J56: Totaal Aankoop | K56: =SUM(K44:K55) -> 438296
B57: Uit te keren winst | C57: 80077.72 | D57: [694/7] | J57: Verkoop
B58: Verrekende kapitaalsubsidies in resultaat | C58: =230.52 -> 230.52 | D58: [9125] | J58: Machine B | K58: -185000
B59: 1 Kasstroom uit financieringsactiviteiten met het eigen vermogen (A+B) | C59: =C50+C55 -> 200254.52 | J59: Correctie | K59: 87875
B60: Toename Voorzieningen en uitgestelde belastingen | C60: =E60-F60 -> 27959.54 | D60: [16] | E60: 36886.52 | F60: 8926.98 | J60: Totaal Verkoop | K60: =SUM(K58:K59) -> -97125
B61: Correcties | J61: Cashflow uit inv.act | K61: =K56+K60 -> 341171
B62: – Voorzieningen voor risico’s en kosten | C62: -12614.08 | D62: [635/9]
B63: Onttrekkingen aan de uitgestelde belastingen | C63: 743.15 | D63: [780] | J63: Vrije cashflow' | K63: =C44-K61 -> 217709.95
B64: – Overboekingen naar de uitgestelde belastingen | C64: -15531.25 | D64: [680] | J64: fin | K64: =C73 -> 192423.95
B65: 2 Kasstroom uit financieringsactiviteiten met voorzieningen en belastingen | C65: =SUM(C60:C64) -> 557.36 | K65: =K63-K64 -> 25286
A66: – Financiële kaskosten van het vreemd vermogen voor | B66: – Financiële kaskosten van het vreemd vermogen voor belasting | C66: -64704.91 | D66: [65/66B] | J66: verschil | K66: =K65-C79 -> -132783.96
A67: belasting | B67: Toename financiële schuld LT | C67: =E67-F67 -> 31053.78 | D67: [170/4] | E67: 1042282.9 | F67: 1011229.2
B68: Toename financiële schuld KT | C68: =E68-F68 -> 35708.12 | D68: [42] | E68: 172029.55 | F68: 136321.43
B69: Toename schuld aandeelhouder | C69: 69632.8 | D69: [47] | K69: =K63-C79 -> 59639.99
B70: Correcties | K70: 59896.14
B71: – Uit te keren winst | C71: -80077.72 | D71: [694/7] | K71: =K70-K69 -> 256.15
B72: 3 Kasstroom uit financieringsactiviteiten met financiële schulden | C72: =SUM(C66:C71) -> -8387.93
B73: Cashflow uit financieringsactiviteit (1+2+3) | C73: =C59+C65+C72 -> 192423.95
B75: Component | C75: Bedrag (€)
B76: Vrije Cashflow | C76: =C46 -> 496438.69
B77: Cashflow uit financieringsactiviteit | C77: =C73 -> 192423.95
B78: Totale Cashflow | C78: =C76-C77 -> 304014.74 | D78: 2025 | E78: 2024
B79: Mutatie liquide middelen | C79: =D79-E79 -> 158069.96 | D79: 162734.99 | E79: 4665.03 | K79: =K63-C79 -> 59639.99
B80: Verschil | C80: =C78-C79 -> 145944.78

Sheet KSS_full (2)
A1: Cashflow Analysis | B1: 2025 | C1: 2024 | D1: MAR Code | E1: 2025 | F1: 2024
A2: Winst van het boekjaar voor belastingen | B2: 285000 | C2: 56127.31 | D2: [9903]
A3: PLUS niet-kaskosten | B3: =B4+B5+B6+B7 -> 221886.72 | C3: =C4+C5+C6+C7 -> 172158.41
A4: Afschrijvingen | B4: 152975.39 | C4: 155871.43 | D4: [630]
A5: Waardeverminderingen op handelsvorderingen en voorraden | B5: 40766 | C5: 7360 | D5: [631/4]
A6: Voorzieningen voor risico’s en kosten | B6: 12614.08 | C6: 8926.98 | D6: [635/8]
A7: Overboeking naar de uitgestelde belastingen | B7: 15531.25 | D7: [680]
A8: MIN niet-kasopbrengsten | B8: 0 | C8: 0
A9: Cashflow van het eigen vermogen voor belasting | B9: =B2+B3 -> 506886.72 | C9: =C2+C3+C8 -> 228285.72 | I9: Investering
A10: Belastingen | D10: [67/77] | I10: Aankoop
A11: Vennootschapsbelasting | B11: 69442.88 | C11: 17837.65 | I11: Goodwil | J11: 49798 | N11: =J11+J13+J15+J17+J19+J21 -> 458111.62
A12: Cashflow van het eigen vermogen | B12: =B9-B11 -> 437443.84 | C12: =C9-C11 -> 210448.07 | I12: Correctie | J12: -1664.48 | L12: =J14+J18+J20+J22 -> -18103.58
A13: PLUS intresten uit vreemd vermogen | B13: 64704.91 | C13: 62433.75 | D13: [65] | I13: Machine Overname | J13: 150000
A14: Potentiële operationele cashflow | B14: =B12+B13 -> 502148.75 | C14: =C12+C13 -> 272881.82 | I14: Correctie | J14: -10027.4
A15: Potentiële operationele cashflow | B15: =B14 -> 502148.75 | I15: Boermachine | J15: 2800
A16: Min Mutaties bedrijfsactiva (operationele activa korte termijn) | B16: =B17+B18+B19 -> -33188.21 | E16: 2025 | F16: 2024 | I16: Correctie | J16: -47.56
A17: Voorraden en BIU | B17: =-(E17-F17) -> 10904.42 | C17: [30/36] | D17: mutatie | E17: 36661.58 | F17: 47566 | I17: Freesmachine | J17: =165000+1750+100 -> 166850
A18: Voorderingen | B18: =-(E18-F18) -> -37523.25 | C18: [40/41] | D18: mutatie | E18: =407047.76+131.61 -> 407179.37 | F18: 369656.12 | I18: correctie | J18: =-2001.96-21.23-1.21 -> -2024.4
A19: Overlopende rekeningen | B19: =-(E19-F19) -> -6569.38 | C19: [490/1] | D19: mutatie | E19: 6569.38 | F19: 0 | I19: Leasing | J19: 68035.12
A20: Plus Mutatie bedrijfspasiva (operationele passiva) | B20: =B21+B22+B23+B24+B25+B26 -> 174641.02 | I20: Correctie | J20: -6000
A21: Leveranciers | B21: =E21-F21 -> -4182.15 | C21: [44] | D21: mutatie | E21: 144903.83 | F21: 149085.98 | I21: Inrichtinge gebouwen | J21: 20628.5
A22: Bezoldigingen | B22: =E22-F22 -> 8700 | C22: [454/9] | D22: mutatie | E22: 13524.62 | F22: 4824.62 | I22: Correctie | J22: -51.78
A23: Belastingen | B23: =E23-F23 -> 97249.21 | C23: [450/3] | D23: mutatie | E23: 131834.63 | F23: 34585.42 | I23: Totaal Aankoop | J23: =SUM(J11:J22) -> 438296
A24: Vooruitbetalingen op bestellingen | B24: =E24-F24 -> 1000 | C24: [46] | D24: mutatie | E24: 1000 | F24: 0 | I24: Verkoop
A25: Overige schulden | B25: =E25-F25 -> 69632.8 | C25: [48] | E25: 69632.8 | F25: 0 | I25: Machine B | J25: -185000
A26: Overlopende rekeningen | B26: =E26-F26 -> 2241.16 | C26: [492/3] | D26: mutatie | E26: 4490.54 | F26: 2249.38 | I26: Correctie | J26: 87875
A27: Correcties | B27: =B28 -> -40766 | I27: Totaal Verkoop | J27: =SUM(J25:J26) -> -97125
A28: Waardeverminderingen op handelsvorderingen en voorraden | B28: -40766 | C28: [631/4] | I28: Cashflow uit inv.act | J28: =J23+J27 -> 341171
A29: Cashflow uit operationele activiteiten | B29: =B15+B16+B20+B27 -> 602835.56 | I29: Cashflow uit operationele activiteiten | J29: =B29 -> 602835.56
A30: Indirecte Methode | I30: Vrije cashflow' | J30: =J29-J28 -> 261664.56
A31: Omschrijving | B31: Bedrag (€) | C31: Code | D31: Toelichting | E31: 2025 | F31: 2024 | I31: fin | J31: =B40 -> 602835.56 | M31: =2473923.5 -> 2473923.5
A32: Mutaties | B32: 367048.5 | J32: =J30-J31 -> -341171 | M32: 2288923.5
A33: Immateriële vaste activa | B33: =(E33-F33) -> 48133.52 | C33: [20/21] | D33: Balansmutatie | E33: 48133.52 | F33: 0 | I33: verschil | J33: =J32-B46 -> -521844.33 | M33: 1648896.9
A34: Materiële vaste activa | B34: =E34-F34 -> 350939.59 | C34: [22/27] | D34: Balansmutatie | E34: 1600763.4 | F34: 1249823.8 | M34: =M31-M32 -> 185000
A35: Correcties | B35: =B36+B37+B38 -> -200441.39 | J35: =J30+B76 -> 419734.52 | M35: =M31-M33 -> 825026.58
A36: Afschrijvingen MVA | B36: =L12 -> -18103.58 | C36: [6300/2] | D36: [8279] | M36: =M35-M34+B35 -> 439585.19
A37: Afschrijvingen IMVA | B37: -1664.48 | C37: [8079] | J37: =B32+B36+B37 -> 347280.44 | M37: -87250
A38: Herwaarderingsmeerwaarden | B38: -180673.33 | C38: [12] | M38: =M36+M37 -> 352335.19
A39: cashflow uit investeringsactiviteiten | B39: =B32+B35 -> 166607.11 | J39: 2288923.5
A40: Cashflow uit operationele activiteiten | B40: =B29 -> 602835.56 | J40: 1834000
A41: cashflow uit investeringsactiviteiten | B41: =B39 -> 166607.11 | J41: =J26 -> 87875
A42: Vrije cashflow | B42: =B29-B39 -> 436228.45 | J42: =J39-J40-J41 -> 367048.5
J43: =J42+B38 -> 186375.17
A44: 1 Eigen Vermogen | B44: =B45+B49 -> -9306.37 | J44: =J43-J28 -> -154795.83
A45: Mutatie | B45: =B46+B47+B48 -> 302199.34 | D45: 645456.8 | E45: 324487.98
A46: Herwaarderingsmeerwaarden | B46: =D46-E46 -> 180673.33 | C46: [12] | D46: 180673.33 | E46: 0
A47: Reserves | B47: =D47-E47 -> 201603.73 | C47: [13] | D47: 201603.73
A48: Overgedragen winst/verlies | B48: =D48-E48 -> -80077.72 | C48: [140/141] | D48: 194410.26 | E48: 274487.98
A49: Correcties | B49: =B50+B51+B52+B53 -> -311505.71
A50: – Winst van het boekjaar/+verlies van het boekjaar | B50: -154428.79 | C50: [9905]
A51: – Herwaarderingsmeerwaarden | B51: =-B46 -> -180673.33 | C51: [12]
A52: – Belastingvrije reserves | B52: -46036.39 | C52: [132]
A53: – Dividend uitkering | B53: 69632.8 | C53: [47] | D53: of [694]
A54: 2 Kapitaalsubsidies | B54: =B56 -> 18769.48
A55: Mutatie
A56: Kapitaalsubsidies | B56: =D56-E49 -> 18769.48 | C56: [15] | D56: 18769.48
A57: 3 Voorzieningen en uitgestelde belasting | B57: =B59+B61+B62 -> 0
A58: Mutatie
A59: Voorzieningen en uitgestelde belasting | B59: =D59-E59 -> 27959.54 | C59: [16] | D59: 36886.52 | E59: 8926.98
A60: Correcties
A61: – Voorzieningen voor risico’s en kosten | B61: -12614.08 | C61: [635/9]
A62: – Uitgestelde belastingen | B62: -15345.46 | C62: [168]
A63: 4 Financiële schulden | B63: =B65+B66+B68 -> -69359.25
A64: Mutaties
A65: Financiële schuld LT | B65: =D65-E65 -> 31053.78 | C65: [170/4] | D65: 1042282.9 | E65: 1011229.2
A66: – Financiële schuld KT | B66: =-(D66-E66) -> -35708.12 | C66: [42] | D66: 172029.55 | E66: 136321.43
A67: Correcties
A68: – Intresten uit vreemd vermogen | B68: -64704.91 | C68: [65]
A69: Cashflow uit financieringsactiviteit (1+2+3+4) | B69: =B44+B54+B57+B63 -> -59896.14
B70: -3740.54
B71: =B69+B70 -> -63636.68
A72: Component | B72: Bedrag (€)
A73: Vrije Cashflow | B73: =B42 -> 436228.45
A74: Cashflow uit financieringsactiviteit | B74: =B69 -> -59896.14
A75: Totale Cashflow | B75: =B73-B74 -> 496124.59 | C75: 2025 | D75: 2024
A76: Mutatie liquide middelen | B76: =C76-D76 -> 158069.96 | C76: 162734.99 | D76: 4665.03
A77: Verschil | B77: =B75-B76 -> 338054.63

Sheet Actie
B2: Cashflow Analysis | C2: 2025 | D2: 2024 | E2: MAR Code
B3: Winst van het boekjaar voor belastingen | C3: 285253.52 | D3: 56127.31 | E3: [9903]
B4: PLUS niet-kaskosten | C4: =C5+C6+C7+C8+C9 -> 226533.33 | D4: =D5+D6+D7+D8+D9 -> 172158.41
B5: Afschrijvingen | C5: 152975.39 | D5: 155871.43 | E5: [630]
B6: Waardeverminderingen op handelsvorderingen en voorraden | C6: 40766 | D6: 7360 | E6: [631/4]
B7: Minderwaarde realisatie voordering | C7: 4646.61 | D7: 0 | E7: [641/2]
B8: Voorzieningen voor risico’s en kosten | C8: 12614.08 | D8: 8926.98 | E8: [635/8]
B9: Overboeking naar de uitgestelde belastingen | C9: 15531.25 | E9: [680]
B10: MIN niet-kasopbrengsten | C10: =C11+C12 -> -973.67 | D10: =D11+D12 -> 0
B11: Onttrekking aan de uitgestelde belastingen | C11: =-743.15 -> -743.15 | E11: [780]
B12: Aangerekende kapitaalsubsidies in resultaat | C12: =-230.52 -> -230.52
B13: Cashflow van het eigen vermogen voor belasting | C13: =C3+C4+C10 -> 510813.18 | D13: =D3+D4+D10 -> 228285.72
B14: Belastingen | E14: [67/77]
B15: Vennootschapsbelasting | C15: 69442.88 | D15: 17837.65
B16: Cashflow van het eigen vermogen | C16: =C13-C15 -> 441370.3 | D16: =D13-D15 -> 210448.07
B17: PLUS intresten uit vreemd vermogen | C17: 64704.91 | D17: 62433.75 | E17: [65]
B18: Potentiële operationele cashflow | C18: =C16+C17 -> 506075.21 | D18: =D16+D17 -> 272881.82
B20: Potentiële operationele cashflow | C20: =C18 -> 506075.21
B21: Min Mutaties bedrijfsactiva (operationele activa korte termijn) | C21: =C22+C23+C24 -> -33188.21 | F21: 2025 | G21: 2024
B22: Voorraden en BIU | C22: =-(F22-G22) -> 10904.42 | D22: [30/36] | E22: mutatie | F22: 36661.58 | G22: 47566
B23: Voorderingen | C23: =-(F23-G23) -> -37523.25 | D23: [40/41] | E23: mutatie | F23: =407047.76+131.61 -> 407179.37 | G23: 369656.12
B24: Overlopende rekeningen | C24: =-(F24-G24) -> -6569.38 | D24: [490/1] | E24: mutatie | F24: 6569.38 | G24: 0
B25: Plus Mutatie bedrijfspasiva (operationele passiva) | C25: =C26+C27+C28+C29+C30+C31 -> 174641.02
B26: Leveranciers | C26: =F26-G26 -> -4182.15 | D26: [44] | E26: mutatie | F26: 144903.83 | G26: 149085.98
B27: Bezoldigingen | C27: =F27-G27 -> 8700 | D27: [454/9] | E27: mutatie | F27: 13524.62 | G27: 4824.62
B28: Belastingen | C28: =F28-G28 -> 97249.21 | D28: [450/3] | E28: mutatie | F28: 131834.63 | G28: 34585.42
B29: Vooruitbetalingen op bestellingen | C29: =F29-G29 -> 1000 | D29: [46] | E29: mutatie | F29: 1000 | G29: 0
B30: Overige schulden | C30: =F30-G30 -> 69632.8 | D30: [48] | F30: 69632.8 | G30: 0
B31: Overlopende rekeningen | C31: =F31-G31 -> 2241.16 | D31: [492/3] | E31: mutatie | F31: 4490.54 | G31: 2249.38
B32: Correcties | C32: =C33 -> -40766
B33: Waardeverminderingen op handelsvorderingen en voorraden | C33: -40766 | D33: [631/4] | I33: Investering
B34: Cashflow uit operationele activiteiten | C34: =C20+C21+C25+C32 -> 606762.02 | I34: Aankoop
I35: Goodwil | J35: 49798
I36: Correctie | J36: -1664.48
B37: Indirecte Methode | I37: VA | J37: =J39+J41+J43+J45+J47 -> 408313.62
B38: Omschrijving | C38: Bedrag (€) | D38: Code | E38: Toelichting | F38: 2025 | G38: 2024 | I38: VA correctie | J38: =J40+J42+J44+J46+J48 -> -18151.14 | L38: 590125.5
B39: Mutaties | C39: =C41+C40 -> 454923.5 | I39: Machine Overname | J39: 150000 | L39: 185000
B40: Immateriële vaste activa | C40: =F40-G40 -> 49798 | D40: [20/21] | E40: Balansmutatie | F40: 49798 | G40: 0 | I40: Correctie | J40: -10027.4 | L40: =L38-L39 -> 405125.5
B41: Materiële vaste activa | C41: =F41-G41 -> 405125.5 | D41: [22/27] | E41: Balansmutatie | F41: 2239125.5 | G41: 1834000 | I41: Boermachine | J41: 2800
B42: Correcties | C42: =C43+C44+C45 -> -333648.72 | I42: Correctie | J42: -47.56
B43: Afschrijvingen MVA | C43: -151310.91 | D43: [6300/2] | E43: [8279] | F43: =J38 -> -18151.14 | I43: Freesmachine | J43: =165000+1750+100 -> 166850
B44: Afschrijvingen IMVA | C44: -1664.48 | D44: [8079] | I44: correctie | J44: =-2001.96-21.23-1.21 -> -2024.4
B45: Herwaarderingsmeerwaarden | C45: -180673.33 | D45: [12] | I45: Leasing | J45: 68035.12
B46: cashflow uit investeringsactiviteiten | C46: =C39+C42 -> 121274.78 | I46: Correctie | J46: -6000
I47: Inrichtinge gebouwen | J47: 20628.5
C48: =C38 -> Bedrag (€) | I48: Correctie | J48: -51.78
B49: Cashflow uit operationele activiteiten | C49: =C34 -> 606762.02 | D49: =C49 -> 606762.02 | I49: Totaal Aankoop | J49: =J37+J35-J36-J38 -> 477927.24
B50: cashflow uit investeringsactiviteiten | C50: =C46 -> 121274.78 | D50: =J54 -> 380802.24 | I50: Verkoop
B51: Vrije cashflow | C51: =C49-C50 -> 485487.24 | D51: =D49-D50 -> 225959.78 | I51: Machine B | J51: -185000
I52: Correctie | J52: 87875
B53: Mutatie liquide middelen | C53: 158069.96 | I53: Totaal Verkoop | J53: =SUM(J51:J52) -> -97125
I54: Cashflow uit inv.act | J54: =J49+J53 -> 380802.24
I55: =C34-J54 -> 225959.78 | J55: vrije cashflow
B56: 1 Eigen Vermogen | C56: =C57+C61 -> 142122.42
B57: Mutatie | C57: =C58+C59+C60 -> 302199.34 | E57: 645456.8 | F57: 324487.98
B58: Herwaarderingsmeerwaarden | C58: =E58-F58 -> 180673.33 | D58: [12] | E58: 180673.33 | F58: 0
B59: Reserves | C59: =E59-F59 -> 201603.73 | D59: [13] | E59: 201603.73 | I59: =C34-J54 -> 225959.78
B60: Overgedragen winst/verlies | C60: =E60-F60 -> -80077.72 | D60: [140/141] | E60: 194410.26 | F60: 274487.98 | I60: =I59-C81 -> -29653.56
B61: Correcties | C61: =C62+C63+C64+C65 -> -160076.92 | I61: =C53-I60 -> 187723.52
B62: – Winst van het boekjaar/+verlies van het boekjaar | D62: [9905]
B63: – Herwaarderingsmeerwaarden | C63: =-C58 -> -180673.33 | D63: [12]
B64: – Belastingvrije reserves | C64: -49036.39 | D64: [132]
B65: – Dividend uitkering | C65: 69632.8 | D65: [47] | E65: of [694]
B66: 2 Kapitaalsubsidies | C66: =C68 -> 18769.48
B67: Mutatie
B68: Kapitaalsubsidies | C68: =E68-F61 -> 18769.48 | D68: [15] | E68: 18769.48
B69: 3 Voorzieningen en uitgestelde belasting | C69: =C71+C73+C74 -> 27959.54
B70: Mutatie
B71: Voorzieningen en uitgestelde belasting | C71: =E71-F71 -> 27959.54 | D71: [16] | E71: 36886.52 | F71: 8926.98
B72: Correcties
B73: – Voorzieningen voor risico’s en kosten | D73: [635/9]
B74: – Uitgestelde belastingen | D74: [168]
B75: 4 Financiële schulden | C75: =C77+C78+C80 -> 66761.9
B76: Mutaties
B77: Financiële schuld LT | C77: =E77-F77 -> 31053.78 | D77: [170/4] | E77: 1042282.9 | F77: 1011229.2
B78: – Financiële schuld KT | C78: =(E78-F78) -> 35708.12 | D78: [42] | E78: 172029.55 | F78: 136321.43
B79: Correcties
B80: – Intresten uit vreemd vermogen | D80: [65] | F80: -3740.54
B81: Cashflow uit financieringsactiviteit (1+2+3+4) | C81: =C56+C66+C69+C75 -> 255613.34
C83: =C51-C81 -> 229873.9 | F83: =F60-C53 -> 116418.02
C84: =C83-C53 -> 71803.94

Sheet Actie 2
B2: Cashflow Analysis | C2: 2025 | D2: 2024 | E2: MAR Code
B3: Winst van het boekjaar voor belastingen | C3: 285253.52 | D3: 56127.31 | E3: [9903]
B4: PLUS niet-kaskosten | C4: =C5+C6+C7+C8+C9 -> 221886.72 | D4: =D5+D6+D7+D8+D9 -> 172158.41
B5: Afschrijvingen | C5: 152975.39 | D5: 155871.43 | E5: [630]
B6: Waardeverminderingen op handelsvorderingen en voorraden | C6: 40766 | D6: 7360 | E6: [631/4]
B8: Voorzieningen voor risico’s en kosten | C8: 12614.08 | D8: 8926.98 | E8: [635/8]
B9: Overboeking naar de uitgestelde belastingen | C9: 15531.25 | E9: [680]
B10: MIN niet-kasopbrengsten | C10: =C11+C12 -> -973.67 | D10: =D11+D12 -> 0
B11: Onttrekking aan de uitgestelde belastingen | C11: =-743.15 -> -743.15 | E11: [780]
B12: Aangerekende kapitaalsubsidies in resultaat | C12: =-230.52 -> -230.52
B13: Cashflow van het eigen vermogen voor belasting | C13: =C3+C4+C10 -> 506166.57 | D13: =D3+D4+D10 -> 228285.72
B14: Belastingen | E14: [67/77]
B15: Vennootschapsbelasting | C15: 69442.88 | D15: 17837.65
B16: Cashflow van het eigen vermogen | C16: =C13-C15 -> 436723.69 | D16: =D13-D15 -> 210448.07
B17: PLUS intresten uit vreemd vermogen | C17: 64704.91 | D17: 62433.75 | E17: [65]
B18: Potentiële operationele cashflow | C18: =C16+C17 -> 501428.6 | D18: =D16+D17 -> 272881.82
B20: Potentiële operationele cashflow | C20: =C18 -> 501428.6
B22: Min Mutaties bedrijfsactiva (operationele activa korte termijn) | C22: =C23+C24+C25 -> -33188.21 | F22: 2025 | G22: 2024
B23: Voorraden en BIU | C23: =-(F23-G23) -> 10904.42 | D23: [30/36] | E23: mutatie | F23: 36661.58 | G23: 47566
B24: Voorderingen | C24: =-(F24-G24) -> -37523.25 | D24: [40/41] | E24: mutatie | F24: =407047.76+131.61 -> 407179.37 | G24: 369656.12
B25: Overlopende rekeningen | C25: =-(F25-G25) -> -6569.38 | D25: [490/1] | E25: mutatie | F25: 6569.38 | G25: 0
B26: Plus Mutatie bedrijfspasiva (operationele passiva) | C26: =C27+C28+C29+C30+C31+C32 -> 174641.02
B27: Leveranciers | C27: =F27-G27 -> -4182.15 | D27: [44] | E27: mutatie | F27: 144903.83 | G27: 149085.98
B28: Bezoldigingen | C28: =F28-G28 -> 8700 | D28: [454/9] | E28: mutatie | F28: 13524.62 | G28: 4824.62
B29: Belastingen | C29: =F29-G29 -> 97249.21 | D29: [450/3] | E29: mutatie | F29: 131834.63 | G29: 34585.42
B30: Vooruitbetalingen op bestellingen | C30: =F30-G30 -> 1000 | D30: [46] | E30: mutatie | F30: 1000 | G30: 0
B31: Overige schulden | C31: =F31-G31 -> 69632.8 | D31: [48] | E31: mutatie | F31: 69632.8 | G31: 0
B32: Overlopende rekeningen | C32: =F32-G32 -> 2241.16 | D32: [492/3] | E32: mutatie | F32: 4490.54 | G32: 2249.38
B33: Correcties | C33: =C34 -> -40766
B34: Waardeverminderingen op handelsvorderingen en voorraden | C34: -40766 | D34: [631/4]
C35: =C21+C22+C26+C33 -> 100686.81
B36: Cashflow uit operationele activiteiten | C36: =C20+C22+C26+C33 -> 602115.41
B38: Indirecte Methode | I38: Direct Methode
B39: Omschrijving | C39: Bedrag (€) | D39: Code | E39: Toelichting | F39: 2025 | G39: 2024 | I39: cashflow uit investeringsactiviteiten
B40: Mutaties | C40: =C41+C42 -> 639923.5 | I40: Aankoop
B41: Immateriële vaste activa | C41: =F41-G41 -> 49798 | D41: [20/21] | E41: Balansmutatie | F41: 49798 | G41: 0 | I41: Goodwil | J41: 49798 | K41: =J41+J42 -> 48133.52
B42: Materiële vaste activa | C42: =F42-G42 -> 590125.5 | D42: [22/27] | E42: Balansmutatie | F42: 2424125.5 | G42: 1834000 | I42: Correctie | J42: -1664.48
B43: Correcties | C43: =C44+C45+C46 -> -196261.25 | E43: Afshrijving | F43: 638362.1 | G43: 584176.19 | I43: VA | J43: =J45+J47+J49+J51+J53 -> 408313.62 | K43: =J43+J44 -> 395528.73
B44: Afschrijvingen MVA | C44: =J44 -> -12784.89 | D44: [6300/2] | E44: [8279] | I44: VA correctie | J44: =J46+J48+J50+J52+J54 -> -12784.89
B45: Afschrijvingen IMVA | C45: -1664.48 | D45: [8079] | I45: Machine Overname | J45: 150000
B46: Herwaarderingsmeerwaarden | C46: -181811.88 | D46: [12] | I46: Correctie | J46: -10027.4
B47: cashflow uit investeringsactiviteiten | C47: =C40+C43 -> 443662.25 | I47: Boermachine | J47: 2800
I48: Correctie | J48: -47.56
C49: =C39 -> Bedrag (€) | I49: Freesmachine | J49: =165000+1750+100 -> 166850
B50: Cashflow uit operationele activiteiten | C50: =C36 -> 602115.41 | I50: correctie | J50: =-2001.96-21.23-1.21 -> -2024.4
B51: cashflow uit investeringsactiviteiten | C51: =C47 -> 443662.25 | I51: Leasing | J51: 68035.12
B52: Vrije cashflow | C52: =C50-C51 -> 158453.16 | I52: Correctie | J52: -633.75
B53: Mutatie liquide middelen | C53: 158069.96 | I53: Inrichtinge gebouwen | J53: 20628.5
I54: Correctie | J54: -51.78
I55: Totaal Aankoop | J55: =J41+J42+J43+J44 -> 443662.25 | K55: =SUM(K41:K54) -> 443662.25
B56: 1 Eigen Vermogen | C56: =C57+C61 -> -9306.37 | I56: cashflow uit investeringsactiviteiten | J56: =J55 -> 443662.25
B57: Mutatie | C57: =C58+C59+C60 -> 302199.34 | E57: 645456.8 | F57: 324487.98
B58: Herwaarderingsmeerwaarden | C58: =E58-F58 -> 180673.33 | D58: [12] | E58: 180673.33 | F58: 0
B59: Reserves | C59: =E59-F59 -> 201603.73 | D59: [13] | E59: 201603.73
B60: Overgedragen winst/verlies | C60: =E60-F60 -> -80077.72 | D60: [140/141] | E60: 194410.26 | F60: 274487.98
B61: Correcties | C61: =C62+C63+C64+C65 -> -311505.71
B62: – Winst van het boekjaar/+verlies van het boekjaar | C62: -154428.79 | D62: [9905]
B63: – Herwaarderingsmeerwaarden | C63: =-C58 -> -180673.33 | D63: [12]
B64: – Belastingvrije reserves | C64: -46036.39 | D64: [132]
B65: – Dividend uitkering | C65: 69632.8 | D65: [47] | E65: of [694]
B66: 2 Kapitaalsubsidies | C66: =C68+C70 -> 19000
B67: Mutatie
B68: Kapitaalsubsidies | C68: =E68-F61 -> 18769.48 | D68: [15] | E68: 18769.48
B69: Correcties
B70: Niet kasopbrengst | C70: 230.52
B71: 3 Voorzieningen en uitgestelde belasting | C71: =C73+C75+C76 -> 0
B72: Mutatie
B73: Voorzieningen en uitgestelde belasting | C73: =E73-F73 -> 27959.54 | D73: [16] | E73: 36886.52 | F73: 8926.98
B74: Correcties
B75: – Voorzieningen voor risico’s en kosten | C75: -12614.08 | D75: [635/9]
B76: – Uitgestelde belastingen | C76: -15345.46 | D76: [168]
B77: 4 Financiële schulden | C77: =C79+C80+C82 -> 2056.99
B78: Mutaties
B79: Financiële schuld LT | C79: =E79-F79 -> 31053.78 | D79: [170/4] | E79: 1042282.9 | F79: 1011229.2
B80: – Financiële schuld KT | C80: =(E80-F80) -> 35708.12 | D80: [42] | E80: 172029.55 | F80: 136321.43
B81: Correcties
B82: – Intresten uit vreemd vermogen | C82: -64704.91 | D82: [65]
B83: Cashflow uit financieringsactiviteit (1+2+3+4) | C83: =C56+C66+C71+C77 -> 11750.62
I85: =15345.46-4646.6 -> 10698.86
B86: Component | C86: Bedrag (€)
B87: Vrije Cashflow | C87: =C52 -> 158453.16
B88: Cashflow uit financieringsactiviteit | C88: =C83 -> 11750.62
B89: Totale Cashflow | C89: =C87-C88 -> 146702.54 | D89: 2025 | E89: 2024
B90: Mutatie liquide middelen | C90: =D90-E90 -> 158069.96 | D90: 162734.99 | E90: 4665.03
B91: Verschil | C91: =C89-C90 -> -11367.42
