Workbook

Sheet ACTIVA
A1: VDO
A2: BALANS NA WINSTVERDELING
A4: ACTIVA | B4: Jaar 1 | D4: Jaar 2 | F4: Jaar 3 | I4: Mutaties
C5: % | E5: % | G5: % | I5: jaar 1 -> 2 | J5: jaar 2 -> 3
A6: Oprichtingskosten | C6: =B6/B$44*100 -> 0 | E6: =D6/D$44*100 -> 0 | G6: =F6/F$44*100 -> 0
A8: VASTE ACTIVA | B8: =B10+B15+B24 -> 304000 | C8: =B8/B$44*100 -> 64.158071 | D8: =D10+D15+D24 -> 262000 | E8: =D8/D$44*100 -> 52.670728 | F8: =F10+F15+F24 -> 220000 | G8: =F8/F$44*100 -> 41.369223 | I8: =D8-B8 -> -42000 | J8: =F8-D8 -> -42000
A10: Immateriële Vaste Activa | B10: =B12+B13 -> 0 | C10: =B10/B$44*100 -> 0 | D10: =D12+D13 -> 0 | E10: =D10/D$44*100 -> 0 | F10: =F12+F13 -> 0 | G10: =F10/F$44*100 -> 0
A12: Octrooien, concessies, … | C12: =B12/B$44*100 -> 0 | E12: =D12/D$44*100 -> 0 | G12: =F12/F$44*100 -> 0 | I12: =D12-B12 -> 0 | J12: =F12-D12 -> 0
A13: Goodwill | C13: =B13/B$44*100 -> 0 | E13: =D13/D$44*100 -> 0 | G13: =F13/F$44*100 -> 0 | I13: =D13-B13 -> 0 | J13: =F13-D13 -> 0
A15: Materiële Vaste Activa | B15: =SUM(B17:B22) -> 304000 | C15: =B15/B$44*100 -> 64.158071 | D15: =SUM(D17:D22) -> 262000 | E15: =D15/D$44*100 -> 52.670728 | F15: =SUM(F17:F22) -> 220000 | G15: =F15/F$44*100 -> 41.369223 | I15: =D15-B15 -> -42000 | J15: =F15-D15 -> -42000
A17: Terrein en gebouwen | B17: ='INVEST TABEL'!C7-'INVEST TABEL'!E7 -> 0 | C17: =B17/B$44*100 -> 0 | D17: =B17-'INVEST TABEL'!F7 -> 0 | E17: =D17/D$44*100 -> 0 | F17: ='INVEST TABEL'!J7 -> 0 | G17: =F17/F$44*100 -> 0 | I17: =D17-B17 -> 0 | J17: =F17-D17 -> 0
A18: Machines, Installaties, Uitrusting | B18: ='INVEST TABEL'!C11-'INVEST TABEL'!E11 -> 270000 | C18: =B18/B$44*100 -> 56.982497 | D18: =B18-'INVEST TABEL'!F11 -> 240000 | E18: =C18-'INVEST TABEL'!G11 -> -29943.018 | F18: =D18-'INVEST TABEL'!G11 -> 210000 | G18: =F18/F$44*100 -> 39.488804 | I18: =D18-B18 -> -30000 | J18: =F18-D18 -> -30000
A19: Meubilair, Inrichting | B19: ='INVEST TABEL'!C16-'INVEST TABEL'!E16 -> 34000 | C19: =B19/B$44*100 -> 7.1755737 | D19: =B19-'INVEST TABEL'!F16 -> 22000 | E19: =C19-'INVEST TABEL'!G16 -> -11992.824 | F19: =D19-'INVEST TABEL'!G16 -> 10000 | G19: =F19/F$44*100 -> 1.8804192 | I19: =D19-B19 -> -12000 | J19: =F19-D19 -> -12000
A20: Rollend Materieel | B20: ='INVEST TABEL'!C20-'INVEST TABEL'!E20 -> 0 | C20: =B20/B$44*100 -> 0 | D20: =B20-'INVEST TABEL'!F20 -> 0 | E20: =D20/D$44*100 -> 0 | F20: ='INVEST TABEL'!J20 -> 0 | G20: =F20/F$44*100 -> 0 | I20: =D20-B20 -> 0 | J20: =F20-D20 -> 0
A21: Leasing en soortgelijke rechten | B21: ='INVEST TABEL'!C24-'INVEST TABEL'!E24 -> 0 | C21: =B21/B$44*100 -> 0 | D21: =B21-'INVEST TABEL'!F24 -> 0 | E21: =D21/D$44*100 -> 0 | F21: ='INVEST TABEL'!J24 -> 0 | G21: =F21/F$44*100 -> 0 | I21: =D21-B21 -> 0 | J21: =F21-D21 -> 0
A22: Overige Materiële Vaste Activa | B22: ='INVEST TABEL'!C29-'INVEST TABEL'!E29 -> 0 | C22: =B22/B$44*100 -> 0 | D22: =B22-'INVEST TABEL'!F29 -> 0 | E22: =D22/D$44*100 -> 0 | F22: ='INVEST TABEL'!J29 -> 0 | G22: =F22/F$44*100 -> 0 | I22: =D22-B22 -> 0 | J22: =F22-D22 -> 0
A24: Financiële Vaste Activa | C24: =B24/B$44*100 -> 0 | E24: =D24/D$44*100 -> 0 | G24: =F24/F$44*100 -> 0 | I24: =D24-B24 -> 0 | J24: =F24-D24 -> 0
A26: VLOTTENDE ACTIVA | B26: =B28+B30+B39+B34+B42 -> 169829.71 | C26: =B26/B$44*100 -> 35.841929 | D26: =D28+D30+D39+D34+D42 -> 235429.99 | E26: =D26/D$44*100 -> 47.329272 | F26: =F28+F30+F39+F34+F42 -> 311796.31 | G26: =F26/F$44*100 -> 58.630777 | I26: =D26-B26 -> 65600.284 | J26: =F26-D26 -> 76366.314
A28: Vorderingen op + 1 Jaar | C28: =B28/B$44*100 -> 0 | E28: =D28/D$44*100 -> 0 | G28: =F28/F$44*100 -> 0 | I28: =D28-B28 -> 0 | J28: =F28-D28 -> 0
A30: Voorraden | B30: =B31+B32 -> 0 | C30: =B30/B$44*100 -> 0 | D30: =D31+D32 -> 0 | E30: =D30/D$44*100 -> 0 | F30: =F31+F32 -> 0 | G30: =F30/F$44*100 -> 0 | I30: =D30-B30 -> 0 | J30: =F30-D30 -> 0
A31: Voorraad Handelsgoederen | C31: =B31/B$44*100 -> 0 | D31: =B31 -> 0 | E31: =D31/D$44*100 -> 0 | F31: =D31 -> 0 | G31: =F31/F$44*100 -> 0 | I31: =D31-B31 -> 0 | J31: =F31-D31 -> 0
A32: Bestellingen in uitvoering | C32: =B32/B$44*100 -> 0 | E32: =D32/D$44*100 -> 0 | G32: =F32/F$44*100 -> 0 | I32: =D32-B32 -> 0 | J32: =F32-D32 -> 0
A34: Vorderingen op - 1 Jaar | B34: =B35+B37+B36 -> 62000 | C34: =B34/B$44*100 -> 13.08487 | D34: =D35+D37+D36 -> 65100 | E34: =D34/D$44*100 -> 13.087269 | F34: =F35+F37+F36 -> 68355 | G34: =F34/F$44*100 -> 12.853606 | I34: =D34-B34 -> 3100 | J34: =F34-D34 -> 3255
A35: Handelsvorderingen | B35: ='70-40-44-55'!C12 -> 62000 | C35: =B35/B$44*100 -> 13.08487 | D35: ='70-40-44-55'!C16 -> 65100 | E35: =D35/D$44*100 -> 13.087269 | F35: ='70-40-44-55'!C20 -> 68355 | G35: =F35/F$44*100 -> 12.853606 | I35: =D35-B35 -> 3100 | J35: =F35-D35 -> 3255
A36: Overige Vorderingen
A37: BTW | B37: =RESULTAAT!K46-RESULTAAT!L59 -> 0 | C37: =B37/B$44*100 -> 0 | D37: =RESULTAAT!M46-RESULTAAT!N59 -> 0 | E37: =D37/D$44*100 -> 0 | F37: =RESULTAAT!O46-RESULTAAT!P59 -> 0 | G37: =F37/F$44*100 -> 0 | I37: =D37-B37 -> 0 | J37: =F37-D37 -> 0
A39: Liquide Middelen | B39: =B40 -> 107829.71 | C39: =B39/B$44*100 -> 22.75706 | D39: =D40 -> 170329.99 | E39: =D39/D$44*100 -> 34.242003 | F39: =F40 -> 243441.31 | G39: =F39/F$44*100 -> 45.777171 | I39: =D39-B39 -> 62500.284 | J39: =F39-D39 -> 73111.314
A40: Bank | B40: ='FIN ANALYSE'!B94 -> 107829.71 | C40: =B40/B$44*100 -> 22.75706 | D40: ='FIN ANALYSE'!C94 -> 170329.99 | E40: =D40/D$44*100 -> 34.242003 | F40: ='FIN ANALYSE'!D94 -> 243441.31 | G40: =F40/F$44*100 -> 45.777171 | I40: =D40-B40 -> 62500.284 | J40: =F40-D40 -> 73111.314
A42: Overlopende rekeningen | C42: =B42/B$44*100 -> 0 | E42: =D42/D$44*100 -> 0 | G42: =F42/F$44*100 -> 0 | I42: =D42-B42 -> 0 | J42: =F42-D42 -> 0
A44: TOTAAL ACTIVA | B44: =B26+B8+B6 -> 473829.71 | C44: 100 | D44: =D26+D8+D6 -> 497429.99 | E44: 100 | F44: =F26+F8+F6 -> 531796.31 | G44: 100 | I44: =D44-B44 -> 23600.284 | J44: =F44-D44 -> 34366.314
B46: =B44-PASSIVA!B58 -> 0 | D46: =D44-PASSIVA!D58 -> 0 | F46: =F44-PASSIVA!F58 -> 0

Sheet ACTIVA analyse
A1: =ACTIVA!A1 -> VDO
A2: =ACTIVA!A2 -> BALANS NA WINSTVERDELING
C3: VERTIKALE ANALYSE | I3: HORIZONTALE ANALYSE
A4: ACTIVA | B4: Jaar 1 | C4: =ACTIVA!B4 -> Jaar 1 | D4: Jaar 2 | E4: =ACTIVA!D4 -> Jaar 2 | F4: Jaar 3 | G4: =ACTIVA!F4 -> Jaar 3 | I4: Mutaties in % | K4: Mutaties
C5: % | E5: % | G5: % | I5: jaar 1 -> 2 | J5: jaar 2 -> 3 | K5: jaar 1 -> 2 | L5: jaar 2 -> 3
A6: =ACTIVA!A6 -> Oprichtingskosten | B6: =ACTIVA!B6 -> 0 | C6: =B6/B$44*100 -> 0 | E6: =D6/D$44*100 -> 0 | G6: =F6/F$44*100 -> 0 | I6: =(D6-B6)/B6*100 -> #DIV/0! | J6: =(F6-D6)/D6*100 -> #DIV/0! | K6: =D6-B6 -> 0 | L6: =F6-D6 -> 0
A8: VASTE ACTIVA | B8: =B10+B15+B24 -> 304000 | C8: =B8/B$44*100 -> 64.158071 | D8: =D10+D15+D24 -> 262000 | E8: =D8/D$44*100 -> 52.670728 | F8: =F10+F15+F24 -> 220000 | G8: =F8/F$44*100 -> 41.369223 | I8: =(D8-B8)/B8*100 -> -13.815789 | J8: =(F8-D8)/D8*100 -> -16.030534 | K8: =D8-B8 -> -42000 | L8: =F8-D8 -> -42000
A10: Immateriële Vaste Activa | B10: =B12+B13 -> 0 | C10: =B10/B$44*100 -> 0 | D10: =D12+D13 -> 0 | E10: =D10/D$44*100 -> 0 | F10: =F12+F13 -> 0 | G10: =F10/F$44*100 -> 0 | I10: =(D10-B10)/B10*100 -> #DIV/0! | J10: =(F10-D10)/D10*100 -> #DIV/0! | K10: =D10-B10 -> 0 | L10: =F10-D10 -> 0
A12: =ACTIVA!A12 -> Octrooien, concessies, … | B12: =ACTIVA!B12 -> 0 | C12: =B12/B$44*100 -> 0 | D12: =ACTIVA!D12 -> 0 | E12: =D12/D$44*100 -> 0 | F12: =ACTIVA!F12 -> 0 | G12: =F12/F$44*100 -> 0 | I12: =(D12-B12)/B12*100 -> #DIV/0! | J12: =(F12-D12)/D12*100 -> #DIV/0! | K12: =D12-B12 -> 0 | L12: =F12-D12 -> 0
A13: =ACTIVA!A13 -> Goodwill | B13: =ACTIVA!B13 -> 0 | C13: =B13/B$44*100 -> 0 | D13: =ACTIVA!D13 -> 0 | E13: =D13/D$44*100 -> 0 | F13: =ACTIVA!F13 -> 0 | G13: =F13/F$44*100 -> 0 | I13: =(D13-B13)/B13*100 -> #DIV/0! | J13: =(F13-D13)/D13*100 -> #DIV/0! | K13: =D13-B13 -> 0 | L13: =F13-D13 -> 0
A15: Materiële Vaste Activa | B15: =SUM(B17:B22) -> 304000 | C15: =B15/B$44*100 -> 64.158071 | D15: =SUM(D17:D22) -> 262000 | E15: =D15/D$44*100 -> 52.670728 | F15: =SUM(F17:F22) -> 220000 | G15: =F15/F$44*100 -> 41.369223 | I15: =(D15-B15)/B15*100 -> -13.815789 | J15: =(F15-D15)/D15*100 -> -16.030534 | K15: =D15-B15 -> -42000 | L15: =F15-D15 -> -42000
A17: =ACTIVA!A17 -> Terrein en gebouwen | B17: =ACTIVA!B17 -> 0 | C17: =B17/B$44*100 -> 0 | D17: =ACTIVA!D17 -> 0 | E17: =D17/D$44*100 -> 0 | F17: =ACTIVA!F17 -> 0 | G17: =F17/F$44*100 -> 0 | I17: =(D17-B17)/B17*100 -> #DIV/0! | J17: =(F17-D17)/D17*100 -> #DIV/0! | K17: =D17-B17 -> 0 | L17: =F17-D17 -> 0
A18: =ACTIVA!A18 -> Machines, Installaties, Uitrusting | B18: =ACTIVA!B18 -> 270000 | C18: =B18/B$44*100 -> 56.982497 | D18: =ACTIVA!D18 -> 240000 | E18: =D18/D$44*100 -> 48.247995 | F18: =ACTIVA!F18 -> 210000 | G18: =F18/F$44*100 -> 39.488804 | I18: =(D18-B18)/B18*100 -> -11.111111 | J18: =(F18-D18)/D18*100 -> -12.5 | K18: =D18-B18 -> -30000 | L18: =F18-D18 -> -30000
A19: =ACTIVA!A19 -> Meubilair, Inrichting | B19: =ACTIVA!B19 -> 34000 | C19: =B19/B$44*100 -> 7.1755737 | D19: =ACTIVA!D19 -> 22000 | E19: =D19/D$44*100 -> 4.4227329 | F19: =ACTIVA!F19 -> 10000 | G19: =F19/F$44*100 -> 1.8804192 | I19: =(D19-B19)/B19*100 -> -35.294118 | J19: =(F19-D19)/D19*100 -> -54.545455 | K19: =D19-B19 -> -12000 | L19: =F19-D19 -> -12000
A20: =ACTIVA!A20 -> Rollend Materieel | B20: =ACTIVA!B20 -> 0 | C20: =B20/B$44*100 -> 0 | D20: =ACTIVA!D20 -> 0 | E20: =D20/D$44*100 -> 0 | F20: =ACTIVA!F20 -> 0 | G20: =F20/F$44*100 -> 0 | I20: =(D20-B20)/B20*100 -> #DIV/0! | J20: =(F20-D20)/D20*100 -> #DIV/0! | K20: =D20-B20 -> 0 | L20: =F20-D20 -> 0
A21: =ACTIVA!A21 -> Leasing en soortgelijke rechten | B21: =ACTIVA!B21 -> 0 | C21: =B21/B$44*100 -> 0 | D21: =ACTIVA!D21 -> 0 | E21: =D21/D$44*100 -> 0 | F21: =ACTIVA!F21 -> 0 | G21: =F21/F$44*100 -> 0 | I21: =(D21-B21)/B21*100 -> #DIV/0! | J21: =(F21-D21)/D21*100 -> #DIV/0! | K21: =D21-B21 -> 0 | L21: =F21-D21 -> 0
A22: =ACTIVA!A22 -> Overige Materiële Vaste Activa | B22: =ACTIVA!B22 -> 0 | C22: =B22/B$44*100 -> 0 | D22: =ACTIVA!D22 -> 0 | E22: =D22/D$44*100 -> 0 | F22: =ACTIVA!F22 -> 0 | G22: =F22/F$44*100 -> 0 | I22: =(D22-B22)/B22*100 -> #DIV/0! | J22: =(F22-D22)/D22*100 -> #DIV/0! | K22: =D22-B22 -> 0 | L22: =F22-D22 -> 0
A24: =ACTIVA!A24 -> Financiële Vaste Activa | B24: =ACTIVA!B24 -> 0 | C24: =B24/B$44*100 -> 0 | D24: =ACTIVA!D24 -> 0 | E24: =D24/D$44*100 -> 0 | F24: =ACTIVA!F24 -> 0 | G24: =F24/F$44*100 -> 0 | I24: =(D24-B24)/B24*100 -> #DIV/0! | J24: =(F24-D24)/D24*100 -> #DIV/0! | K24: =D24-B24 -> 0 | L24: =F24-D24 -> 0
A26: VLOTTENDE ACTIVA | B26: =B28+B30+B39+B34+B42 -> 169829.71 | C26: =B26/B$44*100 -> 35.841929 | D26: =D28+D30+D39+D34+D42 -> 235429.99 | E26: =D26/D$44*100 -> 47.329272 | F26: =F28+F30+F39+F34+F42 -> 311796.31 | G26: =F26/F$44*100 -> 58.630777 | I26: =(D26-B26)/B26*100 -> 38.627095 | J26: =(F26-D26)/D26*100 -> 32.436952 | K26: =D26-B26 -> 65600.284 | L26: =F26-D26 -> 76366.314
A28: =ACTIVA!A28 -> Vorderingen op + 1 Jaar | C28: =B28/B$44*100 -> 0 | E28: =D28/D$44*100 -> 0 | G28: =F28/F$44*100 -> 0 | I28: =(D28-B28)/B28*100 -> #DIV/0! | J28: =(F28-D28)/D28*100 -> #DIV/0! | K28: =D28-B28 -> 0 | L28: =F28-D28 -> 0
A30: =ACTIVA!A30 -> Voorraden | B30: =B31+B32 -> 0 | C30: =B30/B$44*100 -> 0 | D30: =D31+D32 -> 0 | E30: =D30/D$44*100 -> 0 | F30: =F31+F32 -> 0 | G30: =F30/F$44*100 -> 0 | I30: =(D30-B30)/B30*100 -> #DIV/0! | J30: =(F30-D30)/D30*100 -> #DIV/0! | K30: =D30-B30 -> 0 | L30: =F30-D30 -> 0
A31: =ACTIVA!A31 -> Voorraad Handelsgoederen | B31: =ACTIVA!B31 -> 0 | C31: =B31/B$44*100 -> 0 | D31: =ACTIVA!D31 -> 0 | E31: =D31/D$44*100 -> 0 | F31: =ACTIVA!F31 -> 0 | G31: =F31/F$44*100 -> 0 | I31: =(D31-B31)/B31*100 -> #DIV/0! | J31: =(F31-D31)/D31*100 -> #DIV/0! | K31: =D31-B31 -> 0 | L31: =F31-D31 -> 0
A32: =ACTIVA!A32 -> Bestellingen in uitvoering | B32: =ACTIVA!B32 -> 0 | C32: =B32/B$44*100 -> 0 | D32: =ACTIVA!D32 -> 0 | E32: =D32/D$44*100 -> 0 | F32: =ACTIVA!F32 -> 0 | G32: =F32/F$44*100 -> 0 | I32: =(D32-B32)/B32*100 -> #DIV/0! | J32: =(F32-D32)/D32*100 -> #DIV/0! | K32: =D32-B32 -> 0 | L32: =F32-D32 -> 0
A34: =ACTIVA!A34 -> Vorderingen op - 1 Jaar | B34: =B35+B37 -> 62000 | C34: =B34/B$44*100 -> 13.08487 | D34: =D35+D37 -> 65100 | E34: =D34/D$44*100 -> 13.087269 | F34: =F35+F37 -> 68355 | G34: =F34/F$44*100 -> 12.853606 | I34: =(D34-B34)/B34*100 -> 5 | J34: =(F34-D34)/D34*100 -> 5 | K34: =D34-B34 -> 3100 | L34: =F34-D34 -> 3255
A35: =ACTIVA!A35 -> Handelsvorderingen | B35: =ACTIVA!B35 -> 62000 | C35: =B35/B$44*100 -> 13.08487 | D35: =ACTIVA!D35 -> 65100 | E35: =D35/D$44*100 -> 13.087269 | F35: =ACTIVA!F35 -> 68355 | G35: =F35/F$44*100 -> 12.853606 | I35: =(D35-B35)/B35*100 -> 5 | J35: =(F35-D35)/D35*100 -> 5 | K35: =D35-B35 -> 3100 | L35: =F35-D35 -> 3255
A36: =ACTIVA!A36 -> Overige Vorderingen | C36: =B36/B$44*100 -> 0 | E36: =D36/D$44*100 -> 0 | G36: =F36/F$44*100 -> 0 | I36: =(D36-B36)/B36*100 -> #DIV/0! | J36: =(F36-D36)/D36*100 -> #DIV/0! | K36: =D36-B36 -> 0 | L36: =F36-D36 -> 0
A37: =ACTIVA!A37 -> BTW | B37: =ACTIVA!B37 -> 0 | C37: =B37/B$44*100 -> 0 | D37: =ACTIVA!D37 -> 0 | E37: =D37/D$44*100 -> 0 | F37: =ACTIVA!F37 -> 0 | G37: =F37/F$44*100 -> 0 | I37: =(D37-B37)/B37*100 -> #DIV/0! | J37: =(F37-D37)/D37*100 -> #DIV/0! | K37: =D37-B37 -> 0 | L37: =F37-D37 -> 0
A39: =ACTIVA!A39 -> Liquide Middelen | B39: =B40 -> 107829.71 | C39: =B39/B$44*100 -> 22.75706 | D39: =D40 -> 170329.99 | E39: =D39/D$44*100 -> 34.242003 | F39: =F40 -> 243441.31 | G39: =F39/F$44*100 -> 45.777171 | I39: =(D39-B39)/B39*100 -> 57.962025 | J39: =(F39-D39)/D39*100 -> 42.923335 | K39: =D39-B39 -> 62500.284 | L39: =F39-D39 -> 73111.314
A40: =ACTIVA!A40 -> Bank | B40: =ACTIVA!B40 -> 107829.71 | C40: =B40/B$44*100 -> 22.75706 | D40: =ACTIVA!D40 -> 170329.99 | E40: =D40/D$44*100 -> 34.242003 | F40: =ACTIVA!F40 -> 243441.31 | G40: =F40/F$44*100 -> 45.777171 | I40: =(D40-B40)/B40*100 -> 57.962025 | J40: =(F40-D40)/D40*100 -> 42.923335 | K40: =D40-B40 -> 62500.284 | L40: =F40-D40 -> 73111.314
A42: =ACTIVA!A42 -> Overlopende rekeningen | B42: =ACTIVA!B42 -> 0 | C42: =B42/B$44*100 -> 0 | E42: =D42/D$44*100 -> 0 | G42: =F42/F$44*100 -> 0 | I42: =(D42-B42)/B42*100 -> #DIV/0! | J42: =(F42-D42)/D42*100 -> #DIV/0! | K42: =D42-B42 -> 0 | L42: =F42-D42 -> 0
A44: TOTAAL ACTIVA | B44: =B26+B8+B6 -> 473829.71 | C44: 100 | D44: =D26+D8+D6 -> 497429.99 | E44: 100 | F44: =F26+F8+F6 -> 531796.31 | G44: 100 | I44: =(D44-B44)/B44*100 -> 4.9807522 | J44: =(F44-D44)/D44*100 -> 6.9087739 | K44: =D44-B44 -> 23600.284 | L44: =F44-D44 -> 34366.314

Sheet PASSIVA
A1: =ACTIVA!A1 -> VDO
A2: =ACTIVA!A2 -> BALANS NA WINSTVERDELING
A4: PASSIVA | B4: =ACTIVA!B4 -> Jaar 1 | D4: =ACTIVA!D4 -> Jaar 2 | F4: =ACTIVA!F4 -> Jaar 3 | I4: Mutaties in % | K4: Mutaties
C5: % | E5: % | G5: % | I5: jaar 1 -> 2 | J5: jaar 2 -> 3 | K5: jaar 1 -> 2 | L5: jaar 2 -> 3
A6: EIGEN VERMOGEN | B6: =B8+B14+B19+B12+B21 -> 136949.77 | C6: =B6/B58*100 -> 28.902741 | D6: =D8+D14+D19+D12+D21 -> 180601.35 | E6: =D6/D58*100 -> 36.306889 | F6: =F8+F14+F19+F12+F21 -> 232233.16 | G6: =F6/F58*100 -> 43.66957 | I6: =(D6-B6)/B6*100 -> 31.874153 | J6: =(F6-D6)/D6*100 -> 28.588825 | K6: =D6-B6 -> 43651.581 | L6: =F6-D6 -> 51631.805
A8: Inbreng | B8: =SUM(B9:B10) -> 90000 | C8: =B8/B$58*100 -> 18.994166 | D8: =SUM(D9:D10) -> 90000 | E8: =D8/D$58*100 -> 18.092998 | F8: =SUM(F9:F10) -> 90000 | G8: =F8/F$58*100 -> 16.923773 | I8: =(D8-B8)/B8*100 -> 0 | J8: =(F8-D8)/D8*100 -> 0 | K8: =D8-B8 -> 0 | L8: =F8-D8 -> 0
A9: Beschikbaar | B9: =OPGAVE!B3 -> 90000 | C9: =B9/B$58*100 -> 18.994166 | D9: =B9 -> 90000 | E9: =D9/D$58*100 -> 18.092998 | F9: =D9 -> 90000 | G9: =F9/F$58*100 -> 16.923773 | I9: =(D9-B9)/B9*100 -> 0 | J9: =(F9-D9)/D9*100 -> 0 | K9: =D9-B9 -> 0 | L9: =F9-D9 -> 0
A10: Onbeschikbaar | C10: =B10/B$58*100 -> 0 | D10: =B31+B10 -> 0 | E10: =D10/D$58*100 -> 0 | F10: =D10 -> 0 | G10: =F10/F$58*100 -> 0 | I10: =(D10-B10)/B10*100 -> #DIV/0! | J10: =(F10-D10)/D10*100 -> #DIV/0! | K10: =D10-B10 -> 0 | L10: =F10-D10 -> 0
A12: Herwaarderingsmeerwaarden | C12: =B12/B$58*100 -> 0 | E12: =D12/D$58*100 -> 0 | G12: =F12/F$58*100 -> 0 | I12: =(D12-B12)/B12*100 -> #DIV/0! | J12: =(F12-D12)/D12*100 -> #DIV/0! | K12: =D12-B12 -> 0 | L12: =F12-D12 -> 0
A14: Reserves | B14: =SUM(B15:B17) -> 0 | C14: =B14/B$58*100 -> 0 | D14: =SUM(D15:D17) -> 0 | E14: =D14/D$58*100 -> 0 | F14: =SUM(F15:F17) -> 0 | G14: =F14/F$58*100 -> 0 | I14: =(D14-B14)/B14*100 -> #DIV/0! | J14: =(F14-D14)/D14*100 -> #DIV/0! | K14: =D14-B14 -> 0 | L14: =F14-D14 -> 0
A15: Onbeschikbare Reserves | C15: =B15/B$58*100 -> 0 | E15: =D15/D$58*100 -> 0 | G15: =F15/F$58*100 -> 0 | I15: =(D15-B15)/B15*100 -> #DIV/0! | J15: =(F15-D15)/D15*100 -> #DIV/0! | K15: =D15-B15 -> 0 | L15: =F15-D15 -> 0
A16: Belastingvrije Reserves | C16: =B16/B$58*100 -> 0 | E16: =D16/D$58*100 -> 0 | F16: =RESULTAAT!D57 -> 0 | G16: =F16/F$58*100 -> 0 | I16: =(D16-B16)/B16*100 -> #DIV/0! | J16: =(F16-D16)/D16*100 -> #DIV/0! | K16: =D16-B16 -> 0 | L16: =F16-D16 -> 0
A17: Beschikbare Reserves | C17: =B17/B$58*100 -> 0 | E17: =D17/D$58*100 -> 0 | G17: =F17/F$58*100 -> 0 | I17: =(D17-B17)/B17*100 -> #DIV/0! | J17: =(F17-D17)/D17*100 -> #DIV/0! | K17: =D17-B17 -> 0 | L17: =F17-D17 -> 0
A19: Overgedragen Resultaat | B19: =RESULTAAT!B54 -> 46949.774 | C19: =B19/B$58*100 -> 9.9085754 | D19: =RESULTAAT!C75 -> 90601.355 | E19: =D19/D$58*100 -> 18.213891 | F19: =RESULTAAT!D75 -> 142233.16 | G19: =F19/F$58*100 -> 26.745797 | I19: =(D19-B19)/B19*100 -> 92.975061 | J19: =(F19-D19)/D19*100 -> 56.987896 | K19: =D19-B19 -> 43651.581 | L19: =F19-D19 -> 51631.805
A21: Kapitaalsubsidies | C21: =B21/B$58*100 -> 0 | E21: =D21/D$58*100 -> 0 | G21: =F21/F$58*100 -> 0 | I21: =(D21-B21)/B21*100 -> #DIV/0! | J21: =(F21-D21)/D21*100 -> #DIV/0! | K21: =D21-B21 -> 0 | L21: =F21-D21 -> 0
A23: VOORZIENINGEN EN UITGESTELDE BELASTING | B23: =SUM(B25:B26) -> 0 | C23: =B23/B$58*100 -> 0 | D23: =SUM(D25:D26) -> 0 | E23: =D23/D$58*100 -> 0 | F23: =SUM(F25:F26) -> 0 | G23: =F23/F$58*100 -> 0 | I23: =(D23-B23)/B23*100 -> #DIV/0! | J23: =(F23-D23)/D23*100 -> #DIV/0! | K23: =D23-B23 -> 0 | L23: =F23-D23 -> 0
A25: Voorzieningen | C25: =B25/B$58*100 -> 0 | E25: =D25/D$58*100 -> 0 | G25: =F25/F$58*100 -> 0 | I25: =(D25-B25)/B25*100 -> #DIV/0! | J25: =(F25-D25)/D25*100 -> #DIV/0! | K25: =D25-B25 -> 0 | L25: =F25-D25 -> 0
A26: Uitgestelde Belastingen | C26: =B26/B$58*100 -> 0 | E26: =D26/D$58*100 -> 0 | F26: =RESULTAAT!D51 -> 0 | G26: =F26/F$58*100 -> 0 | I26: =(D26-B26)/B26*100 -> #DIV/0! | J26: =(F26-D26)/D26*100 -> #DIV/0! | K26: =D26-B26 -> 0 | L26: =F26-D26 -> 0
A28: SCHULDEN OP + 1 JAAR | B28: =B30 -> 228120.77 | C28: =B28/B$58*100 -> 48.144041 | D28: =D30 -> 204628.06 | E28: =D28/D$58*100 -> 41.137056 | F28: =F30 -> 179933.41 | G28: =F28/F$58*100 -> 33.835025 | I28: =(D28-B28)/B28*100 -> -10.298367 | J28: =(F28-D28)/D28*100 -> -12.068064 | K28: =D28-B28 -> -23492.713 | L28: =F28-D28 -> -24694.645
A30: Financiële Schulden | B30: =SUM(B31:B33) -> 228120.77 | C30: =B30/B$58*100 -> 48.144041 | D30: =SUM(D31:D33) -> 204628.06 | E30: =D30/D$58*100 -> 41.137056 | F30: =SUM(F31:F33) -> 179933.41 | G30: =F30/F$58*100 -> 33.835025 | I30: =(D30-B30)/B30*100 -> -10.298367 | J30: =(F30-D30)/D30*100 -> -12.068064 | K30: =D30-B30 -> -23492.713 | L30: =F30-D30 -> -24694.645
A31: Achtergestelde Lening | C31: =B31/B$58*100 -> 0 | E31: =D31/D$58*100 -> 0 | G31: =F31/F$58*100 -> 0 | I31: =(D31-B31)/B31*100 -> #DIV/0! | J31: =(F31-D31)/D31*100 -> #DIV/0! | K31: =D31-B31 -> 0 | L31: =F31-D31 -> 0
A32: Lening Machines | B32: =Aflossingstabel!J25 -> 228120.77 | C32: =B32/B$58*100 -> 48.144041 | D32: =B32-D38 -> 204628.06 | E32: =D32/D$58*100 -> 41.137056 | F32: =D32-F38 -> 179933.41 | G32: =F32/F$58*100 -> 33.835025 | I32: =(D32-B32)/B32*100 -> -10.298367 | J32: =(F32-D32)/D32*100 -> -12.068064 | K32: =D32-B32 -> -23492.713 | L32: =F32-D32 -> -24694.645
A33: Overige | C33: =B33/B$58*100 -> 0 | E33: =D33/D$58*100 -> 0 | G33: =F33/F$58*100 -> 0 | I33: =(D33-B33)/B33*100 -> #DIV/0! | J33: =(F33-D33)/D33*100 -> #DIV/0! | K33: =D33-B33 -> 0 | L33: =F33-D33 -> 0
A35: SCHULDEN OP - 1 JAAR | B35: =B37+B45+B48+B53+B56+B41 -> 108759.17 | C35: =B35/B$58*100 -> 22.953218 | D35: =D37+D45+D48+D53+D56+D41 -> 112200.58 | E35: =D35/D$58*100 -> 22.556055 | F35: =F37+F45+F48+F53+F56+F41 -> 119629.73 | G35: =F35/F$58*100 -> 22.495405 | I35: =(D35-B35)/B35*100 -> 3.1642537 | J35: =(F35-D35)/D35*100 -> 6.6213141 | K35: =D35-B35 -> 3441.4159 | L35: =F35-D35 -> 7429.1529
A37: Schulden + 1 jaar die binnen het jaar vervallen | B37: =SUM(B38:B39) -> 22349.281 | C37: =B37/B$58*100 -> 4.7167328 | D37: =SUM(D38:D39) -> 23492.713 | E37: =D37/D$58*100 -> 4.722818 | F37: =SUM(F38:F39) -> 24694.645 | G37: =F37/F$58*100 -> 4.6436285 | I37: =(D37-B37)/B37*100 -> 5.1161898 | J37: =(F37-D37)/D37*100 -> 5.1161898 | K37: =D37-B37 -> 1143.4317 | L37: =F37-D37 -> 1201.9318
A38: =A32 -> Lening Machines | B38: =Aflossingstabel!K25 -> 22349.281 | C38: =B38/B$58*100 -> 4.7167328 | D38: =Aflossingstabel!K26 -> 23492.713 | E38: =D38/D$58*100 -> 4.722818 | F38: =Aflossingstabel!K27 -> 24694.645 | G38: =F38/F$58*100 -> 4.6436285 | I38: =(D38-B38)/B38*100 -> 5.1161898 | J38: =(F38-D38)/D38*100 -> 5.1161898 | K38: =D38-B38 -> 1143.4317 | L38: =F38-D38 -> 1201.9318
A39: =A33 -> Overige | C39: =B39/B$58*100 -> 0 | E39: =D39/D$58*100 -> 0 | G39: =F39/F$58*100 -> 0 | I39: =(D39-B39)/B39*100 -> #DIV/0! | J39: =(F39-D39)/D39*100 -> #DIV/0! | K39: =D39-B39 -> 0 | L39: =F39-D39 -> 0
A41: =A30 -> Financiële Schulden | B41: =B42+B43 -> 0 | C41: =B41/B$58*100 -> 0 | D41: =D42+D43 -> 0 | E41: =D41/D$58*100 -> 0 | F41: =F42+F43 -> 0 | G41: =F41/F$58*100 -> 0 | I41: =(D41-B41)/B41*100 -> #DIV/0! | J41: =(F41-D41)/D41*100 -> #DIV/0! | K41: =D41-B41 -> 0 | L41: =F41-D41 -> 0
A42: Kredietinstellingen R/C | C42: =B42/B$58*100 -> 0 | E42: =D42/D$58*100 -> 0 | G42: =F42/F$58*100 -> 0 | I42: =(D42-B42)/B42*100 -> #DIV/0! | J42: =(F42-D42)/D42*100 -> #DIV/0! | K42: =D42-B42 -> 0 | L42: =F42-D42 -> 0
A43: Overige | C43: =B43/B$58*100 -> 0 | E43: =D43/D$58*100 -> 0 | G43: =F43/F$58*100 -> 0 | I43: =(D43-B43)/B43*100 -> #DIV/0! | J43: =(F43-D43)/D43*100 -> #DIV/0! | K43: =D43-B43 -> 0 | L43: =F43-D43 -> 0
A45: Handelsschulden | B45: =B46 -> 69750 | C45: =B45/B$58*100 -> 14.720478 | D45: =D46 -> 73237.5 | E45: =D45/D$58*100 -> 14.723177 | F45: =F46 -> 76899.375 | G45: =F45/F$58*100 -> 14.460306 | I45: =(D45-B45)/B45*100 -> 5 | J45: =(F45-D45)/D45*100 -> 5 | K45: =D45-B45 -> 3487.5 | L45: =F45-D45 -> 3661.875
A46: Leveranciers | B46: ='70-40-44-55'!D28 -> 69750 | C46: =B46/B$58*100 -> 14.720478 | D46: ='70-40-44-55'!D32 -> 73237.5 | E46: =D46/D$58*100 -> 14.723177 | F46: ='70-40-44-55'!D36 -> 76899.375 | G46: =F46/F$58*100 -> 14.460306 | I46: =(D46-B46)/B46*100 -> 5 | J46: =(F46-D46)/D46*100 -> 5 | K46: =D46-B46 -> 3487.5 | L46: =F46-D46 -> 3661.875
A48: Belastingen en Sociale Schulden | B48: =SUM(B49:B51) -> 15649.925 | C48: =B48/B$58*100 -> 3.3028585 | D48: =SUM(D49:D51) -> 14550.527 | E48: =D48/D$58*100 -> 2.9251407 | F48: =SUM(F49:F51) -> 17210.602 | G48: =F48/F$58*100 -> 3.2363147 | I48: =(D48-B48)/B48*100 -> -7.024939 | J48: =(F48-D48)/D48*100 -> 18.281639 | K48: =D48-B48 -> -1099.3977 | L48: =F48-D48 -> 2660.0748
A49: Belastingen | B49: =RESULTAAT!B52 -> 15649.925 | C49: =B49/B$58*100 -> 3.3028585 | D49: =RESULTAAT!C52 -> 14550.527 | E49: =D49/D$58*100 -> 2.9251407 | F49: =RESULTAAT!D52 -> 17210.602 | G49: =F49/F$58*100 -> 3.2363147 | I49: =(D49-B49)/B49*100 -> -7.024939 | J49: =(F49-D49)/D49*100 -> 18.281639 | K49: =D49-B49 -> -1099.3977 | L49: =F49-D49 -> 2660.0748
A50: BTW
A51: Bezoldigingen en Sociale lasten | C51: =B51/B$58*100 -> 0 | E51: =D51/D$58*100 -> 0 | G51: =F51/F$58*100 -> 0 | I51: =(D51-B51)/B51*100 -> #DIV/0! | J51: =(F51-D51)/D51*100 -> #DIV/0! | K51: =D51-B51 -> 0 | L51: =F51-D51 -> 0
A53: Overige | B53: =B54 -> 0 | C53: =B53/B$58*100 -> 0 | D53: =D54 -> 0 | E53: =D53/D$58*100 -> 0 | F53: =F54 -> 0 | G53: =F53/F$58*100 -> 0 | I53: =(D53-B53)/B53*100 -> #DIV/0! | J53: =(F53-D53)/D53*100 -> #DIV/0! | K53: =D53-B53 -> 0 | L53: =F53-D53 -> 0
A54: Overige schulden | C54: =B54/B$58*100 -> 0 | D54: =B54 -> 0 | E54: =D54/D$58*100 -> 0 | F54: =D54 -> 0 | G54: =F54/F$58*100 -> 0 | I54: =(D54-B54)/B54*100 -> #DIV/0! | J54: =(F54-D54)/D54*100 -> #DIV/0! | K54: =D54-B54 -> 0 | L54: =F54-D54 -> 0
A56: Overlopende Rekeningen | B56: =Aflossingstabel!J44 -> 1009.9599 | C56: =B56/B$58*100 -> 0.21314828 | D56: =Aflossingstabel!J45 -> 919.84181 | E56: =D56/D$58*100 -> 0.18491885 | F56: =Aflossingstabel!J46 -> 825.11313 | G56: =F56/F$58*100 -> 0.15515586 | I56: =(D56-B56)/B56*100 -> -8.9229356 | J56: =(F56-D56)/D56*100 -> -10.298367 | K56: =D56-B56 -> -90.11807 | L56: =F56-D56 -> -94.728682
A58: TOTAAL PASSIVA | B58: =B35+B28+B6 -> 473829.71 | C58: 100 | D58: =D35+D28+D6 -> 497429.99 | E58: 100 | F58: =F35+F28+F6+F23 -> 531796.31 | G58: 100 | I58: =(D58-B58)/B58*100 -> 4.9807522 | J58: =(F58-D58)/D58*100 -> 6.9087739 | K58: =D58-B58 -> 23600.284 | L58: =F58-D58 -> 34366.314

Sheet PASSIVA analyse
A1: =ACTIVA!A1 -> VDO
A2: =ACTIVA!A2 -> BALANS NA WINSTVERDELING
C4: VERTIKALE ANALYSE | I4: HORIZONTALE ANALYSE
A5: PASSIVA | B5: =ACTIVA!B4 -> Jaar 1 | C5: ='ACTIVA analyse'!C4 -> Jaar 1 | D5: ='ACTIVA analyse'!D4 -> Jaar 2 | E5: ='ACTIVA analyse'!E4 -> Jaar 2 | F5: ='ACTIVA analyse'!F4 -> Jaar 3 | G5: ='ACTIVA analyse'!G4 -> Jaar 3 | I5: Mutaties in % | K5: Mutaties
C6: % | E6: % | G6: % | I6: jaar 1 -> 2 | J6: jaar 2 -> 3 | K6: jaar 1 -> 2 | L6: jaar 2 -> 3
A7: EIGEN VERMOGEN | B7: =B9+B15+B20+B13+B22 -> 136949.77 | C7: =B7/B59*100 -> 28.902741 | D7: =D9+D15+D20+D13+D22 -> 180601.35 | E7: =D7/D59*100 -> 36.306889 | F7: =F9+F15+F20+F13+F22 -> 232233.16 | G7: =F7/F59*100 -> 43.66957 | I7: =(D7-B7)/B7*100 -> 31.874153 | J7: =(F7-D7)/D7*100 -> 28.588825 | K7: =D7-B7 -> 43651.581 | L7: =F7-D7 -> 51631.805
A9: =PASSIVA!A8 -> Inbreng | B9: =SUM(B10:B11) -> 90000 | C9: =B9/B$59*100 -> 18.994166 | D9: =SUM(D10:D11) -> 90000 | E9: =D9/D$59*100 -> 18.092998 | F9: =SUM(F10:F11) -> 90000 | G9: =F9/F$59*100 -> 16.923773 | I9: =(D9-B9)/B9*100 -> 0 | J9: =(F9-D9)/D9*100 -> 0 | K9: =D9-B9 -> 0 | L9: =F9-D9 -> 0
A10: =PASSIVA!A9 -> Beschikbaar | B10: =PASSIVA!B9 -> 90000 | C10: =B10/B$59*100 -> 18.994166 | D10: =PASSIVA!D9 -> 90000 | E10: =D10/D$59*100 -> 18.092998 | F10: =PASSIVA!F9 -> 90000 | G10: =F10/F$59*100 -> 16.923773 | I10: =(D10-B10)/B10*100 -> 0 | J10: =(F10-D10)/D10*100 -> 0 | K10: =D10-B10 -> 0 | L10: =F10-D10 -> 0
A11: =PASSIVA!A10 -> Onbeschikbaar | B11: =PASSIVA!B10 -> 0 | C11: =B11/B$59*100 -> 0 | D11: =PASSIVA!D10 -> 0 | E11: =D11/D$59*100 -> 0 | F11: =PASSIVA!F10 -> 0 | G11: =F11/F$59*100 -> 0 | I11: =(D11-B11)/B11*100 -> #DIV/0! | J11: =(F11-D11)/D11*100 -> #DIV/0! | K11: =D11-B11 -> 0 | L11: =F11-D11 -> 0
A13: =PASSIVA!A12 -> Herwaarderingsmeerwaarden | B13: =PASSIVA!B12 -> 0 | C13: =B13/B$59*100 -> 0 | D13: =PASSIVA!D12 -> 0 | E13: =D13/D$59*100 -> 0 | F13: =PASSIVA!F12 -> 0 | G13: =F13/F$59*100 -> 0 | I13: =(D13-B13)/B13*100 -> #DIV/0! | J13: =(F13-D13)/D13*100 -> #DIV/0! | K13: =D13-B13 -> 0 | L13: =F13-D13 -> 0
A15: =PASSIVA!A14 -> Reserves | B15: =SUM(B16:B18) -> 0 | C15: =B15/B$59*100 -> 0 | D15: =SUM(D16:D18) -> 0 | E15: =D15/D$59*100 -> 0 | F15: =SUM(F16:F18) -> 0 | G15: =F15/F$59*100 -> 0 | I15: =(D15-B15)/B15*100 -> #DIV/0! | J15: =(F15-D15)/D15*100 -> #DIV/0! | K15: =D15-B15 -> 0 | L15: =F15-D15 -> 0
A16: =PASSIVA!A15 -> Onbeschikbare Reserves | B16: =PASSIVA!B15 -> 0 | C16: =B16/B$59*100 -> 0 | D16: =PASSIVA!D15 -> 0 | E16: =D16/D$59*100 -> 0 | F16: =PASSIVA!F15 -> 0 | G16: =F16/F$59*100 -> 0 | I16: =(D16-B16)/B16*100 -> #DIV/0! | J16: =(F16-D16)/D16*100 -> #DIV/0! | K16: =D16-B16 -> 0 | L16: =F16-D16 -> 0
A17: =PASSIVA!A16 -> Belastingvrije Reserves | B17: =PASSIVA!B16 -> 0 | C17: =B17/B$59*100 -> 0 | D17: =PASSIVA!D16 -> 0 | E17: =D17/D$59*100 -> 0 | F17: =PASSIVA!F16 -> 0 | G17: =F17/F$59*100 -> 0 | I17: =(D17-B17)/B17*100 -> #DIV/0! | J17: =(F17-D17)/D17*100 -> #DIV/0! | K17: =D17-B17 -> 0 | L17: =F17-D17 -> 0
A18: =PASSIVA!A17 -> Beschikbare Reserves | B18: =PASSIVA!B17 -> 0 | C18: =B18/B$59*100 -> 0 | D18: =PASSIVA!D17 -> 0 | E18: =D18/D$59*100 -> 0 | F18: =PASSIVA!F17 -> 0 | G18: =F18/F$59*100 -> 0 | I18: =(D18-B18)/B18*100 -> #DIV/0! | J18: =(F18-D18)/D18*100 -> #DIV/0! | K18: =D18-B18 -> 0 | L18: =F18-D18 -> 0
A20: =PASSIVA!A19 -> Overgedragen Resultaat | B20: =PASSIVA!B19 -> 46949.774 | C20: =B20/B$59*100 -> 9.9085754 | D20: =PASSIVA!D19 -> 90601.355 | E20: =D20/D$59*100 -> 18.213891 | F20: =PASSIVA!F19 -> 142233.16 | G20: =F20/F$59*100 -> 26.745797 | I20: =(D20-B20)/B20*100 -> 92.975061 | J20: =(F20-D20)/D20*100 -> 56.987896 | K20: =D20-B20 -> 43651.581 | L20: =F20-D20 -> 51631.805
A22: =PASSIVA!A21 -> Kapitaalsubsidies | B22: =PASSIVA!B21 -> 0 | C22: =B22/B$59*100 -> 0 | D22: =PASSIVA!D21 -> 0 | E22: =D22/D$59*100 -> 0 | F22: =PASSIVA!F21 -> 0 | G22: =F22/F$59*100 -> 0 | I22: =(D22-B22)/B22*100 -> #DIV/0! | J22: =(F22-D22)/D22*100 -> #DIV/0! | K22: =D22-B22 -> 0 | L22: =F22-D22 -> 0
A24: VOORZIENINGEN EN UITGESTELDE BELASTING | B24: =SUM(B26:B27) -> 0 | C24: =B24/B$59*100 -> 0 | D24: =SUM(D26:D27) -> 0 | E24: =D24/D$59*100 -> 0 | F24: =SUM(F26:F27) -> 0 | G24: =F24/F$59*100 -> 0 | I24: =(D24-B24)/B24*100 -> #DIV/0! | J24: =(F24-D24)/D24*100 -> #DIV/0! | K24: =D24-B24 -> 0 | L24: =F24-D24 -> 0
A26: =PASSIVA!A25 -> Voorzieningen | B26: =PASSIVA!B25 -> 0 | C26: =B26/B$59*100 -> 0 | D26: =PASSIVA!D25 -> 0 | E26: =D26/D$59*100 -> 0 | F26: =PASSIVA!F25 -> 0 | G26: =F26/F$59*100 -> 0 | I26: =(D26-B26)/B26*100 -> #DIV/0! | J26: =(F26-D26)/D26*100 -> #DIV/0! | K26: =D26-B26 -> 0 | L26: =F26-D26 -> 0
A27: =PASSIVA!A26 -> Uitgestelde Belastingen | B27: =PASSIVA!B26 -> 0 | C27: =B27/B$59*100 -> 0 | D27: =PASSIVA!D26 -> 0 | E27: =D27/D$59*100 -> 0 | F27: =PASSIVA!F26 -> 0 | G27: =F27/F$59*100 -> 0 | I27: =(D27-B27)/B27*100 -> #DIV/0! | J27: =(F27-D27)/D27*100 -> #DIV/0! | K27: =D27-B27 -> 0 | L27: =F27-D27 -> 0
A29: SCHULDEN OP + 1 JAAR | B29: =B31 -> 228120.77 | C29: =B29/B$59*100 -> 48.144041 | D29: =D31 -> 204628.06 | E29: =D29/D$59*100 -> 41.137056 | F29: =F31 -> 179933.41 | G29: =F29/F$59*100 -> 33.835025 | I29: =(D29-B29)/B29*100 -> -10.298367 | J29: =(F29-D29)/D29*100 -> -12.068064 | K29: =D29-B29 -> -23492.713 | L29: =F29-D29 -> -24694.645
A31: =PASSIVA!A30 -> Financiële Schulden | B31: =SUM(B32:B34) -> 228120.77 | C31: =B31/B$59*100 -> 48.144041 | D31: =SUM(D32:D34) -> 204628.06 | E31: =D31/D$59*100 -> 41.137056 | F31: =SUM(F32:F34) -> 179933.41 | G31: =F31/F$59*100 -> 33.835025 | I31: =(D31-B31)/B31*100 -> -10.298367 | J31: =(F31-D31)/D31*100 -> -12.068064 | K31: =D31-B31 -> -23492.713 | L31: =F31-D31 -> -24694.645
A32: =PASSIVA!A31 -> Achtergestelde Lening | B32: =PASSIVA!B31 -> 0 | C32: =B32/B$59*100 -> 0 | D32: =PASSIVA!D31 -> 0 | E32: =D32/D$59*100 -> 0 | F32: =PASSIVA!F31 -> 0 | G32: =F32/F$59*100 -> 0 | I32: =(D32-B32)/B32*100 -> #DIV/0! | J32: =(F32-D32)/D32*100 -> #DIV/0! | K32: =D32-B32 -> 0 | L32: =F32-D32 -> 0
A33: =PASSIVA!A32 -> Lening Machines | B33: =PASSIVA!B32 -> 228120.77 | C33: =B33/B$59*100 -> 48.144041 | D33: =PASSIVA!D32 -> 204628.06 | E33: =D33/D$59*100 -> 41.137056 | F33: =PASSIVA!F32 -> 179933.41 | G33: =F33/F$59*100 -> 33.835025 | I33: =(D33-B33)/B33*100 -> -10.298367 | J33: =(F33-D33)/D33*100 -> -12.068064 | K33: =D33-B33 -> -23492.713 | L33: =F33-D33 -> -24694.645
A34: =PASSIVA!A33 -> Overige | B34: =PASSIVA!B33 -> 0 | C34: =B34/B$59*100 -> 0 | D34: =PASSIVA!D33 -> 0 | E34: =D34/D$59*100 -> 0 | F34: =PASSIVA!F33 -> 0 | G34: =F34/F$59*100 -> 0 | I34: =(D34-B34)/B34*100 -> #DIV/0! | J34: =(F34-D34)/D34*100 -> #DIV/0! | K34: =D34-B34 -> 0 | L34: =F34-D34 -> 0
A36: SCHULDEN OP - 1 JAAR | B36: =B38+B46+B49+B54+B57+B42 -> 108759.17 | C36: =B36/B$59*100 -> 22.953218 | D36: =D38+D46+D49+D54+D57+D42 -> 112200.58 | E36: =D36/D$59*100 -> 22.556055 | F36: =F38+F46+F49+F54+F57+F42 -> 119629.73 | G36: =F36/F$59*100 -> 22.495405 | I36: =(D36-B36)/B36*100 -> 3.1642537 | J36: =(F36-D36)/D36*100 -> 6.6213141 | K36: =D36-B36 -> 3441.4159 | L36: =F36-D36 -> 7429.1529
A38: =PASSIVA!A37 -> Schulden + 1 jaar die binnen het jaar vervallen | B38: =SUM(B39:B43) -> 22349.281 | C38: =B38/B$59*100 -> 4.7167328 | D38: =SUM(D39:D43) -> 23492.713 | E38: =D38/D$59*100 -> 4.722818 | F38: =SUM(F39:F43) -> 24694.645 | G38: =F38/F$59*100 -> 4.6436285 | I38: =(D38-B38)/B38*100 -> 5.1161898 | J38: =(F38-D38)/D38*100 -> 5.1161898 | K38: =D38-B38 -> 1143.4317 | L38: =F38-D38 -> 1201.9318
A39: =PASSIVA!A38 -> Lening Machines | B39: =PASSIVA!B38 -> 22349.281 | C39: =B39/B$59*100 -> 4.7167328 | D39: =PASSIVA!D38 -> 23492.713 | E39: =D39/D$59*100 -> 4.722818 | F39: =PASSIVA!F38 -> 24694.645 | G39: =F39/F$59*100 -> 4.6436285 | I39: =(D39-B39)/B39*100 -> 5.1161898 | J39: =(F39-D39)/D39*100 -> 5.1161898 | K39: =D39-B39 -> 1143.4317 | L39: =F39-D39 -> 1201.9318
A40: =PASSIVA!A39 -> Overige | B40: =PASSIVA!B39 -> 0 | C40: =B40/B$59*100 -> 0 | D40: =PASSIVA!D39 -> 0 | E40: =D40/D$59*100 -> 0 | F40: =PASSIVA!F39 -> 0 | G40: =F40/F$59*100 -> 0 | I40: =(D40-B40)/B40*100 -> #DIV/0! | J40: =(F40-D40)/D40*100 -> #DIV/0! | K40: =D40-B40 -> 0 | L40: =F40-D40 -> 0
A42: =PASSIVA!A41 -> Financiële Schulden | B42: =B43+B44 -> 0 | C42: =B42/B$59*100 -> 0 | D42: =D43+D44 -> 0 | E42: =D42/D$59*100 -> 0 | F42: =F43+F44 -> 0 | G42: =F42/F$59*100 -> 0 | I42: =(D42-B42)/B42*100 -> #DIV/0! | J42: =(F42-D42)/D42*100 -> #DIV/0! | K42: =D42-B42 -> 0 | L42: =F42-D42 -> 0
A43: =PASSIVA!A42 -> Kredietinstellingen R/C | B43: =PASSIVA!B42 -> 0 | C43: =B43/B$59*100 -> 0 | D43: =PASSIVA!D42 -> 0 | E43: =D43/D$59*100 -> 0 | F43: =PASSIVA!F42 -> 0 | G43: =F43/F$59*100 -> 0 | I43: =(D43-B43)/B43*100 -> #DIV/0! | J43: =(F43-D43)/D43*100 -> #DIV/0! | K43: =D43-B43 -> 0 | L43: =F43-D43 -> 0
A44: =PASSIVA!A43 -> Overige | B44: =PASSIVA!B43 -> 0 | C44: =B44/B$59*100 -> 0 | D44: =PASSIVA!D43 -> 0 | E44: =D44/D$59*100 -> 0 | F44: =PASSIVA!F43 -> 0 | G44: =F44/F$59*100 -> 0 | I44: =(D44-B44)/B44*100 -> #DIV/0! | J44: =(F44-D44)/D44*100 -> #DIV/0! | K44: =D44-B44 -> 0 | L44: =F44-D44 -> 0
A46: =PASSIVA!A45 -> Handelsschulden | B46: =B47 -> 69750 | C46: =B46/B$59*100 -> 14.720478 | D46: =D47 -> 73237.5 | E46: =D46/D$59*100 -> 14.723177 | F46: =F47 -> 76899.375 | G46: =F46/F$59*100 -> 14.460306 | I46: =(D46-B46)/B46*100 -> 5 | J46: =(F46-D46)/D46*100 -> 5 | K46: =D46-B46 -> 3487.5 | L46: =F46-D46 -> 3661.875
A47: =PASSIVA!A46 -> Leveranciers | B47: =PASSIVA!B46 -> 69750 | C47: =B47/B$59*100 -> 14.720478 | D47: =PASSIVA!D46 -> 73237.5 | E47: =D47/D$59*100 -> 14.723177 | F47: =PASSIVA!F46 -> 76899.375 | G47: =F47/F$59*100 -> 14.460306 | I47: =(D47-B47)/B47*100 -> 5 | J47: =(F47-D47)/D47*100 -> 5 | K47: =D47-B47 -> 3487.5 | L47: =F47-D47 -> 3661.875
A49: =PASSIVA!A48 -> Belastingen en Sociale Schulden | B49: =SUM(B50:B52) -> 15649.925 | C49: =B49/B$59*100 -> 3.3028585 | D49: =SUM(D50:D52) -> 14550.527 | E49: =D49/D$59*100 -> 2.9251407 | F49: =SUM(F50:F52) -> 17210.602 | G49: =F49/F$59*100 -> 3.2363147 | I49: =(D49-B49)/B49*100 -> -7.024939 | J49: =(F49-D49)/D49*100 -> 18.281639 | K49: =D49-B49 -> -1099.3977 | L49: =F49-D49 -> 2660.0748
A50: =PASSIVA!A49 -> Belastingen | B50: =PASSIVA!B49 -> 15649.925 | C50: =B50/B$59*100 -> 3.3028585 | D50: =PASSIVA!D49 -> 14550.527 | E50: =D50/D$59*100 -> 2.9251407 | F50: =PASSIVA!F49 -> 17210.602 | G50: =F50/F$59*100 -> 3.2363147 | I50: =(D50-B50)/B50*100 -> -7.024939 | J50: =(F50-D50)/D50*100 -> 18.281639 | K50: =D50-B50 -> -1099.3977 | L50: =F50-D50 -> 2660.0748
A51: =PASSIVA!A50 -> BTW | B51: =PASSIVA!B50 -> 0 | C51: =B51/B$59*100 -> 0 | D51: =PASSIVA!D50 -> 0 | E51: =D51/D$59*100 -> 0 | F51: =PASSIVA!F50 -> 0 | G51: =F51/F$59*100 -> 0 | I51: =(D51-B51)/B51*100 -> #DIV/0! | J51: =(F51-D51)/D51*100 -> #DIV/0! | K51: =D51-B51 -> 0 | L51: =F51-D51 -> 0
A52: =PASSIVA!A51 -> Bezoldigingen en Sociale lasten | B52: =PASSIVA!B51 -> 0 | C52: =B52/B$59*100 -> 0 | D52: =PASSIVA!D51 -> 0 | E52: =D52/D$59*100 -> 0 | F52: =PASSIVA!F51 -> 0 | G52: =F52/F$59*100 -> 0 | I52: =(D52-B52)/B52*100 -> #DIV/0! | J52: =(F52-D52)/D52*100 -> #DIV/0! | K52: =D52-B52 -> 0 | L52: =F52-D52 -> 0
A54: =PASSIVA!A53 -> Overige | B54: =B55 -> 0 | C54: =B54/B$59*100 -> 0 | D54: =D55 -> 0 | E54: =D54/D$59*100 -> 0 | F54: =F55 -> 0 | G54: =F54/F$59*100 -> 0 | I54: =(D54-B54)/B54*100 -> #DIV/0! | J54: =(F54-D54)/D54*100 -> #DIV/0! | K54: =D54-B54 -> 0 | L54: =F54-D54 -> 0
A55: =PASSIVA!A54 -> Overige schulden | B55: =PASSIVA!B54 -> 0 | C55: =B55/B$59*100 -> 0 | D55: =PASSIVA!D54 -> 0 | E55: =D55/D$59*100 -> 0 | F55: =PASSIVA!F54 -> 0 | G55: =F55/F$59*100 -> 0 | I55: =(D55-B55)/B55*100 -> #DIV/0! | J55: =(F55-D55)/D55*100 -> #DIV/0! | K55: =D55-B55 -> 0 | L55: =F55-D55 -> 0
A57: =PASSIVA!A56 -> Overlopende Rekeningen | B57: =PASSIVA!B56 -> 1009.9599 | C57: =B57/B$59*100 -> 0.21314828 | D57: =PASSIVA!D56 -> 919.84181 | E57: =D57/D$59*100 -> 0.18491885 | F57: =PASSIVA!F56 -> 825.11313 | G57: =F57/F$59*100 -> 0.15515586 | I57: =(D57-B57)/B57*100 -> -8.9229356 | J57: =(F57-D57)/D57*100 -> -10.298367 | K57: =D57-B57 -> -90.11807 | L57: =F57-D57 -> -94.728682
A59: TOTAAL PASSIVA | B59: =B36+B29+B7 -> 473829.71 | C59: 100 | D59: =D36+D29+D7 -> 497429.99 | E59: 100 | F59: =F36+F29+F7+F24 -> 531796.31 | G59: 100 | I59: =(D59-B59)/B59*100 -> 4.9807522 | J59: =(F59-D59)/D59*100 -> 6.9087739 | K59: =D59-B59 -> 23600.284 | L59: =F59-D59 -> 34366.314
F61: =F59-PASSIVA!F58 -> 0

Sheet RESULTAAT
A1: =PASSIVA!A1 -> VDO | L1: op balans terug te vinden
A2: RESULTATENREKENING | L2: bedrag of breuk ingeven
A4: BEDRIJFSOPBRENGSTEN | B4: =PASSIVA!B4 -> Jaar 1 | C4: =ACTIVA!D4 -> Jaar 2 | D4: =ACTIVA!F4 -> Jaar 3 | G4: Mutaties in % | K4: jaar 1 | M4: jaar 2 | O4: jaar 3
B5: =B8+B12+B15 -> 945000 | C5: =C8+C12+C15 -> 976500 | D5: =D8+D12+D15 -> 1025325 | G5: =(C5-B5)/B5*100 -> 3.3333333 | H5: =(D5-C5)/C5*100 -> 5 | K5: 411 | L5: 451 | M5: 411 | N5: 451 | O5: 411 | P5: 451
A7: Recurrente Bedrijfsopbrengsten | B7: =B8+B12 -> 945000 | C7: =C8+C12 -> 976500 | D7: =D8+D12 -> 1025325 | E7: 100 | G7: =(C7-B7)/B7*100 -> 3.3333333 | H7: =(D7-C7)/C7*100 -> 5 | J7: totaal | K7: =(B20+B21+B24)*21% -> 154669.87 | L7: =B8*21% -> 195300 | M7: =(C20+C21+C24)*21% -> 162038.42 | N7: =C8*21% -> 205065 | O7: =(D20+D21+D24)*21% -> 169898.53 | P7: =D8*21% -> 215318.25
A8: Omzet | B8: =SUM(B9:B10) -> 930000 | C8: =SUM(C9:C10) -> 976500 | D8: =SUM(D9:D10) -> 1025325 | G8: =(C8-B8)/B8*100 -> 5 | H8: =(D8-C8)/C8*100 -> 5 | J8: saldo | L8: =L7-K7 -> 40630.128 | N8: =N7-M7 -> 43026.581 | P8: =P7-O7 -> 45419.715
A9: Omzet | B9: ='70-40-44-55'!C2 -> 930000 | C9: ='70-40-44-55'!C3 -> 976500 | D9: ='70-40-44-55'!C4 -> 1025325 | G9: =(C9-B9)/B9*100 -> 5 | H9: =(D9-C9)/C9*100 -> 5 | J9: rek 451 | L9: =L8/4 -> 10157.532 | N9: =N8/4 -> 10756.645 | P9: =P8/4 -> 11354.929
A10: Omzet | G10: =(C10-B10)/B10*100 -> #DIV/0! | H10: =(D10-C10)/C10*100 -> #DIV/0! | J10: betaald | L10: =L8-L9 -> 30472.596 | N10: =N8-N9 -> 32269.936 | P10: =P8-P9 -> 34064.786
A12: Overige Bedrijfsopbrengsten | B12: =B13 -> 15000 | C12: =C13 -> 0 | D12: =D13 -> 0 | G12: =(C12-B12)/B12*100 -> -100 | H12: =(D12-C12)/C12*100 -> #DIV/0!
A13: Subsidies | B13: =OPGAVE!B23 -> 15000 | G13: =(C13-B13)/B13*100 -> -100 | H13: =(D13-C13)/C13*100 -> #DIV/0! | J13: VERKOOP | K13: =B8 -> 930000 | M13: =C8 -> 976500 | O13: =D8 -> 1025325
A14: Meerwaarde realisatie vaste activa
A15: Niet recurrente opbrengsten | G15: =(C15-B15)/B15*100 -> #DIV/0! | H15: =(D15-C15)/C15*100 -> #DIV/0! | J15: BTW | K15: =L7 -> 195300 | M15: =N7 -> 205065 | O15: =P7 -> 215318.25
A17: BEDRIJFSKOSTEN | B17: =B19+B24+B26+B28+B33+B37 -> 869418.83 | C17: =C19+C24+C26+C28+C33+C37 -> 906372.06 | D17: =D19+D24+D26+D28+D33+D37 -> 945704.81 | E17: =D17/D7*100 -> 92.234639 | G17: =(C17-B17)/B17*100 -> 4.2503373 | H17: =(D17-C17)/C17*100 -> 4.3395802 | K17: =SUM(K13:K15) -> 1125300 | M17: =SUM(M13:M15) -> 1181565 | O17: =SUM(O13:O15) -> 1240643.2
A19: Aankopen | B19: =SUM(B20:B22) -> 558000 | C19: =SUM(C20:C22) -> 585900 | D19: =SUM(D20:D22) -> 615195 | E19: =D19/D$7*100 -> 60 | G19: =(C19-B19)/B19*100 -> 5 | H19: =(D19-C19)/C19*100 -> 5 | J19: Krediet/m | K19: 0.91666667 | M19: 0.91666667 | O19: 0.91666667
A20: Aankoop Grondstoffen | E20: =D20/D$7*100 -> 0 | G20: =(C20-B20)/B20*100 -> #DIV/0! | H20: =(D20-C20)/C20*100 -> #DIV/0! | J20: betaald | K20: =K17*K19 -> 1031525 | M20: =M17*M19 -> 1083101.2 | O20: =O17*O19 -> 1137256.3
A21: aankoop Handelsgoederen | B21: ='70-40-44-55'!L25 -> 558000 | C21: ='70-40-44-55'!L26 -> 585900 | D21: ='70-40-44-55'!L27 -> 615195 | E21: =D21/D$7*100 -> 60 | G21: =(C21-B21)/B21*100 -> 5 | H21: =(D21-C21)/C21*100 -> 5 | J21: klanten | K21: =K17-K20 -> 93775 | M21: =M17-M20 -> 98463.75 | O21: =O17-O20 -> 103386.94
A22: Voorraadwijziging | E22: =D22/D$7*100 -> 0 | G22: =(C22-B22)/B22*100 -> #DIV/0! | H22: =(D22-C22)/C22*100 -> #DIV/0!
A24: Diensten en Div. Goederen | B24: =DETAILS!B54 -> 178523.2 | C24: =DETAILS!C54 -> 185711.52 | D24: =DETAILS!D54 -> 193845.64 | E24: =D24/D$7*100 -> 18.905775 | G24: =(C24-B24)/B24*100 -> 4.0265467 | H24: =(D24-C24)/C24*100 -> 4.3799771 | J24: 700 | L24: 1200000 | N24: =L24*1.05 -> 1260000 | P24: =N24*1.05 -> 1323000
A26: Personeelskosten | B26: =DETAILS!B74 -> 86195.632 | C26: =DETAILS!C74 -> 87919.545 | D26: =DETAILS!D74 -> 89677.936 | E26: =D26/D$7*100 -> 8.7462937 | G26: =(C26-B26)/B26*100 -> 2 | H26: =(D26-C26)/C26*100 -> 2 | J26: 451 | L26: =K15 -> 195300 | N26: =M15 -> 205065 | P26: =O15 -> 215318.25
A28: Afschrijvingen en waardeverminderingen | B28: =B29+B30+B31 -> 42000 | C28: =C29+C30+C31 -> 42000 | D28: =D29+D30+D31 -> 42000 | E28: =D28/D$7*100 -> 4.0962622 | G28: =(C28-B28)/B28*100 -> 0 | H28: =(D28-C28)/C28*100 -> 0 | J28: 400 | K28: =K21 -> 93775 | M28: =M21 -> 98463.75 | O28: =O21 -> 103386.94
A29: Afschrijvingen | B29: ='INVEST TABEL'!E33 -> 42000 | C29: ='INVEST TABEL'!F33 -> 42000 | D29: ='INVEST TABEL'!G33 -> 42000 | E29: =D29/D$7*100 -> 4.0962622 | G29: =(C29-B29)/B29*100 -> 0 | H29: =(D29-C29)/C29*100 -> 0 | J29: 550 | K29: =K20 -> 1031525 | M29: =M20 -> 1083101.2 | O29: =O20 -> 1137256.3
A30: Waardeverminderingen | E30: =D30/D$7*100 -> 0 | G30: =(C30-B30)/B30*100 -> #DIV/0! | H30: =(D30-C30)/C30*100 -> #DIV/0!
A31: Voorzieningen | E31: =D31/D$7*100 -> 0 | G31: =(C31-B31)/B31*100 -> #DIV/0! | H31: =(D31-C31)/C31*100 -> #DIV/0! | K31: =SUM(K24:K30) -> 1125300 | L31: =SUM(L24:L30) -> 1395300 | M31: =SUM(M24:M30) -> 1181565 | N31: =SUM(N24:N30) -> 1465065 | O31: =SUM(O24:O30) -> 1240643.2 | P31: =SUM(P24:P30) -> 1538318.2
A33: Overige Bedrijfskosten | B33: =B34+B35 -> 4700 | C33: =C34+C35 -> 4841 | D33: =D34+D35 -> 4986.23 | E33: =D33/D$7*100 -> 0.48630727 | G33: =(C33-B33)/B33*100 -> 3 | H33: =(D33-C33)/C33*100 -> 3
A34: Bedrijfsbelastingen | B34: =DETAILS!B91 -> 4700 | C34: =DETAILS!B92 -> 4841 | D34: =DETAILS!B93 -> 4986.23 | E34: =D34/D$7*100 -> 0.48630727 | G34: =(C34-B34)/B34*100 -> 3 | H34: =(D34-C34)/C34*100 -> 3 | J34: AANKOOP | K34: =B20+B21+B24 -> 736523.2 | M34: =C20+C21+C24 -> 771611.52 | O34: =D20+D21+D24 -> 809040.64
A35: Minderwaarde verkoop mva | E35: =D35/D$7*100 -> 0 | G35: =(C35-B35)/B35*100 -> #DIV/0! | H35: =(D35-C35)/C35*100 -> #DIV/0! | J35: BTW | K35: =K7 -> 154669.87 | M35: =M7 -> 162038.42 | O35: =O7 -> 169898.53
A37: Niet recurrente bedrijfskosten | E37: =D37/D$7*100 -> 0 | G37: =(C37-B37)/B37*100 -> #DIV/0! | H37: =(D37-C37)/C37*100 -> #DIV/0! | K37: =SUM(K34:K36) -> 891193.07 | M37: =SUM(M34:M36) -> 933649.94 | O37: =SUM(O34:O36) -> 978939.18
A39: BRUTO TOEGEVOEGDE WAARDE | B39: =B7-B19-B24 -> 208476.8 | C39: =C7-C19-C24 -> 204888.48 | D39: =D7-D19-D24 -> 216284.36 | E39: =D39/D$7*100 -> 21.094225 | G39: =(C39-B39)/B39*100 -> -1.7212083 | H39: =(D39-C39)/C39*100 -> 5.5619906 | J39: krediet/m | K39: 0.91666667 | M39: 0.91666667 | O39: 0.91666667
A40: EBIT | B40: =B5-B17 -> 75581.168 | C40: =C5-C17 -> 70127.935 | D40: =D5-D17 -> 79620.192 | E40: =D40/D$7*100 -> 7.7653615 | G40: =(C40-B40)/B40*100 -> -7.215068 | H40: =(D40-C40)/C40*100 -> 13.535629 | J40: betaald | K40: =K37*K39 -> 816926.98 | M40: =M37*M39 -> 855845.78 | O40: =O37*O39 -> 897360.91
A41: EBITDA | B41: =B40+B29+B30 -> 117581.17 | C41: =C40+C29+C30 -> 112127.94 | D41: =D40+D29+D30 -> 121620.19 | E41: =D41/D$7*100 -> 11.861624 | G41: =(C41-B41)/B41*100 -> -4.6378453 | H41: =(D41-C41)/C41*100 -> 8.4655595 | J41: leverancier | K41: =K37-K40 -> 74266.089 | M41: =M37-M40 -> 77804.162 | O41: =O37-O40 -> 81578.265
A42: BEDRIJFSRESULTAAT | B42: =B5-B17 -> 75581.168 | C42: =C5-C17 -> 70127.935 | D42: =D5-D17 -> 79620.192 | E42: =D42/D$7*100 -> 7.7653615 | G42: =(C42-B42)/B42*100 -> -7.215068 | H42: =(D42-C42)/C42*100 -> 13.535629
A44: Financiële Opbrengsten | E44: =D44/D$7*100 -> 0 | G44: =(C44-B44)/B44*100 -> #DIV/0! | H44: =(D44-C44)/C44*100 -> #DIV/0! | J44: 600 | K44: =B20+B21 -> 558000 | M44: =C20+C21 -> 585900 | O44: =D20+D21 -> 615195
A45: Financiële Kosten | B45: =Aflossingstabel!K13 -> 12981.469 | C45: =Aflossingstabel!K14 -> 11925.827 | D45: =Aflossingstabel!K15 -> 10777.785 | E45: =D45/D$7*100 -> 1.0511579 | G45: =(C45-B45)/B45*100 -> -8.1319143 | H45: =(D45-C45)/C45*100 -> -9.6265209 | J45: 61 | K45: =B24 -> 178523.2 | M45: =C24 -> 185711.52 | O45: =D24 -> 193845.64
A46: Niet recurrent Financieel (+/-) | E46: =D46/D$7*100 -> 0 | G46: =(C46-B46)/B46*100 -> #DIV/0! | H46: =(D46-C46)/C46*100 -> #DIV/0! | J46: 411 | K46: =K35 -> 154669.87 | M46: =M35 -> 162038.42 | O46: =O35 -> 169898.53
A48: RESULTAAT VOOR BELASTING | B48: =B42+B44-B45 -> 62599.699 | C48: =C42+C44-C45 -> 58202.108 | D48: =D42+D44-D45 -> 68842.407 | E48: =D48/D7*100 -> 6.7142035 | G48: =(C48-B48)/B48*100 -> -7.024939 | H48: =(D48-C48)/C48*100 -> 18.281639 | J48: 440 | L48: =K41 -> 74266.089 | N48: =M41 -> 77804.162 | P48: =O41 -> 81578.265
A50: Onttrekking aan de uitgestelde belasting | G50: =(C50-B50)/B50*100 -> #DIV/0! | H50: =(D50-C50)/C50*100 -> #DIV/0! | J50: 550 | L50: =K40 -> 816926.98 | N50: =M40 -> 855845.78 | P50: =O40 -> 897360.91
A51: Overboeking naar de uitgestelde belasting | G51: =(C51-B51)/B51*100 -> #DIV/0! | H51: =(D51-C51)/C51*100 -> #DIV/0!
A52: Belastingen op het resultaat | B52: =B48*25% -> 15649.925 | C52: =C48*25% -> 14550.527 | D52: =D48*25% -> 17210.602 | E52: =D52/D7*100 -> 1.6785509 | G52: =(C52-B52)/B52*100 -> -7.024939 | H52: =(D52-C52)/C52*100 -> 18.281639 | K52: =SUM(K44:K51) -> 891193.07 | L52: =SUM(L44:L50) -> 891193.07 | M52: =SUM(M44:M51) -> 933649.94 | N52: =SUM(N44:N50) -> 933649.94 | O52: =SUM(O44:O51) -> 978939.18 | P52: =SUM(P44:P50) -> 978939.18
A54: NETTO RESULTAAT | B54: =B48+B50-B51-B52 -> 46949.774 | C54: =C48+C50-C51-C52 -> 43651.581 | D54: =D48+D50-D51-D52 -> 51631.805 | E54: =D54/D7*100 -> 5.0356526 | G54: =(C54-B54)/B54*100 -> -7.024939 | H54: =(D54-C54)/C54*100 -> 18.281639 | J54: BTW | K54: 411 | L54: 451 | M54: 411 | N54: 451 | O54: 411 | P54: 451
A56: Onttrekking aan de Belastingvrije Reserves | G56: =(C56-B56)/B56*100 -> #DIV/0! | H56: =(D56-C56)/C56*100 -> #DIV/0! | K56: =K46 -> 154669.87 | L56: =L26 -> 195300 | M56: =M46 -> 162038.42 | N56: =N26 -> 205065 | O56: =O46 -> 169898.53 | P56: =P26 -> 215318.25
A57: Overboeking naar de Belastingvrije Reserves | D57: =D13-D51 -> 0 | G57: =(C57-B57)/B57*100 -> #DIV/0! | H57: =(D57-C57)/C57*100 -> #DIV/0!
A59: TE BESTEMMEN RESULTAAT | B59: =B54+B56-B57 -> 46949.774 | C59: =C54+C56-C57 -> 43651.581 | D59: =D54+D56-D57 -> 51631.805 | E59: =D59/D7*100 -> 5.0356526 | G59: =(C59-B59)/B59*100 -> -7.024939 | H59: =(D59-C59)/C59*100 -> 18.281639 | J59: 411 | L59: =K56 -> 154669.87 | N59: =M56 -> 162038.42 | P59: =O56 -> 169898.53
J60: 451 | K60: =L59 -> 154669.87 | M60: =N59 -> 162038.42 | O60: =P59 -> 169898.53
J61: 550 | L61: =L10 -> 30472.596 | N61: =N10 -> 32269.936 | P61: =P10 -> 34064.786
A62: =A1 -> VDO | J62: 451 | K62: =L61 -> 30472.596 | M62: =N61 -> 32269.936 | O62: =P61 -> 34064.786
A63: RESULTAATVERWERKING | K63: =SUM(K59:K62) -> 185142.47 | L63: =SUM(L59:L62) -> 185142.47 | M63: =SUM(M59:M62) -> 194308.35 | N63: =SUM(N59:N62) -> 194308.35 | O63: =SUM(O59:O62) -> 203963.32 | P63: =SUM(P59:P62) -> 203963.32
B65: =B4 -> Jaar 1 | C65: =C4 -> Jaar 2 | D65: =D4 -> Jaar 3
A66: Te Bestemmen Resultaat | B66: =B59 -> 46949.774 | C66: =C59 -> 43651.581 | D66: =D59 -> 51631.805
A67: Overgedragen resultaat | C67: =B71 -> 46949.774 | D67: =C71 -> 90601.355
A68: Te Bestemmen | B68: =B66+B67 -> 46949.774 | C68: =C66+C67 -> 90601.355 | D68: =D66+D67 -> 142233.16
A69: Toevoeging aan het Kapitaal
A70: Toevoeging Reserves
A71: Over te dragen resultaat | B71: =B68-B70 -> 46949.774 | C71: =C68-C70 -> 90601.355 | D71: =D68-D70 -> 142233.16
A72: Vergoeding aan het Kapitaal
A73: Vergoeding aan Bestuurders
A74: Vergoeding Personeel
A75: Totaal Bestemd | B75: =SUM(B69:B74) -> 46949.774 | C75: =SUM(C69:C74) -> 90601.355 | D75: =SUM(D69:D74) -> 142233.16

Sheet RESULTAAT analyse
A1: =PASSIVA!A1 -> VDO
A2: RESULTATENREKENING
C3: HORIZONTALE ANALYSE | I3: VERTIKALE ANALYSE
B4: =PASSIVA!B4 -> Jaar 1 | D4: =PASSIVA!D4 -> Jaar 2 | F4: =PASSIVA!F4 -> Jaar 3 | I4: Mutaties in % | K4: Mutaties
A5: =RESULTAAT!A4 -> BEDRIJFSOPBRENGSTEN | B5: =B8+B12+B15 -> 945000 | D5: =D8+D12+D15 -> 976500 | F5: =F8+F12+F15 -> 1025325 | I5: =(D5-B5)/B5*100 -> 3.3333333 | J5: =(F5-D5)/D5*100 -> 5 | K5: jaar 1 -> 2 | L5: jaar 2 -> 3
A7: =RESULTAAT!A7 -> Recurrente Bedrijfsopbrengsten | B7: =B8+B12 -> 945000 | C7: 100 | D7: =D8+D12 -> 976500 | E7: 100 | F7: =F8+F12 -> 1025325 | G7: 100 | I7: =(D7-B7)/B7*100 -> 3.3333333 | J7: =(F7-D7)/D7*100 -> 5 | K7: =RESULTAAT!C7-RESULTAAT!B7 -> 31500 | L7: =RESULTAAT!D7-RESULTAAT!C7 -> 48825
A8: =RESULTAAT!A8 -> Omzet | B8: =SUM(B9:B10) -> 930000 | D8: =SUM(D9:D10) -> 976500 | F8: =SUM(F9:F10) -> 1025325 | I8: =(D8-B8)/B8*100 -> 5 | J8: =(F8-D8)/D8*100 -> 5 | K8: =RESULTAAT!C8-RESULTAAT!B8 -> 46500 | L8: =RESULTAAT!D8-RESULTAAT!C8 -> 48825
A9: =RESULTAAT!A9 -> Omzet | B9: =RESULTAAT!B9 -> 930000 | D9: =RESULTAAT!C9 -> 976500 | F9: =RESULTAAT!D9 -> 1025325 | I9: =(D9-B9)/B9*100 -> 5 | J9: =(F9-D9)/D9*100 -> 5 | K9: =RESULTAAT!C9-RESULTAAT!B9 -> 46500 | L9: =RESULTAAT!D9-RESULTAAT!C9 -> 48825
A10: =RESULTAAT!A10 -> Omzet | B10: =RESULTAAT!B10 -> 0 | D10: =RESULTAAT!C10 -> 0 | F10: =RESULTAAT!D10 -> 0 | I10: =(D10-B10)/B10*100 -> #DIV/0! | J10: =(F10-D10)/D10*100 -> #DIV/0! | K10: =RESULTAAT!C10-RESULTAAT!B10 -> 0 | L10: =RESULTAAT!D10-RESULTAAT!C10 -> 0
A12: =RESULTAAT!A12 -> Overige Bedrijfsopbrengsten | B12: =B13 -> 15000 | D12: =D13 -> 0 | F12: =F13 -> 0 | I12: =(D12-B12)/B12*100 -> -100 | J12: =(F12-D12)/D12*100 -> #DIV/0! | K12: =RESULTAAT!C12-RESULTAAT!B12 -> -15000 | L12: =RESULTAAT!D12-RESULTAAT!C12 -> 0
A13: =RESULTAAT!A14 -> Meerwaarde realisatie vaste activa | B13: =RESULTAAT!B13 -> 15000 | D13: =RESULTAAT!C13 -> 0 | F13: =RESULTAAT!D13 -> 0 | I13: =(D13-B13)/B13*100 -> -100 | J13: =(F13-D13)/D13*100 -> #DIV/0! | K13: =RESULTAAT!C13-RESULTAAT!B13 -> -15000 | L13: =RESULTAAT!D13-RESULTAAT!C13 -> 0
A15: =RESULTAAT!A15 -> Niet recurrente opbrengsten | B15: =RESULTAAT!B15 -> 0 | D15: =RESULTAAT!C15 -> 0 | F15: =RESULTAAT!D15 -> 0 | I15: =(D15-B15)/B15*100 -> #DIV/0! | J15: =(F15-D15)/D15*100 -> #DIV/0! | K15: =RESULTAAT!C15-RESULTAAT!B15 -> 0 | L15: =RESULTAAT!D15-RESULTAAT!C15 -> 0
A17: =RESULTAAT!A17 -> BEDRIJFSKOSTEN | B17: =B19+B24+B26+B28+B33+B37 -> 869418.83 | C17: =RESULTAAT!B17/RESULTAAT!B$7*100 -> 92.001993 | D17: =D19+D24+D26+D28+D33+D37 -> 906372.06 | E17: =D17/D7*100 -> 92.81844 | F17: =F19+F24+F26+F28+F33+F37 -> 945704.81 | G17: =F17/F7*100 -> 92.234639 | I17: =(D17-B17)/B17*100 -> 4.2503373 | J17: =(F17-D17)/D17*100 -> 4.3395802 | K17: =RESULTAAT!C17-RESULTAAT!B17 -> 36953.233 | L17: =RESULTAAT!D17-RESULTAAT!C17 -> 39332.743
A19: =RESULTAAT!A19 -> Aankopen | B19: =SUM(B20:B22) -> 558000 | C19: =RESULTAAT!B19/RESULTAAT!B$7*100 -> 59.047619 | D19: =SUM(D20:D22) -> 585900 | E19: =D19/D$7*100 -> 60 | F19: =SUM(F20:F22) -> 615195 | G19: =F19/F$7*100 -> 60 | I19: =(D19-B19)/B19*100 -> 5 | J19: =(F19-D19)/D19*100 -> 5 | K19: =RESULTAAT!C19-RESULTAAT!B19 -> 27900 | L19: =RESULTAAT!D19-RESULTAAT!C19 -> 29295
A20: =RESULTAAT!A20 -> Aankoop Grondstoffen | B20: =RESULTAAT!B20 -> 0 | C20: =RESULTAAT!B20/RESULTAAT!B$7*100 -> 0 | D20: =RESULTAAT!C20 -> 0 | E20: =D20/D$7*100 -> 0 | F20: =RESULTAAT!D20 -> 0 | G20: =F20/F$7*100 -> 0 | I20: =(D20-B20)/B20*100 -> #DIV/0! | J20: =(F20-D20)/D20*100 -> #DIV/0! | K20: =RESULTAAT!C20-RESULTAAT!B20 -> 0 | L20: =RESULTAAT!D20-RESULTAAT!C20 -> 0
A21: =RESULTAAT!A21 -> aankoop Handelsgoederen | B21: =RESULTAAT!B21 -> 558000 | C21: =RESULTAAT!B21/RESULTAAT!B$7*100 -> 59.047619 | D21: =RESULTAAT!C21 -> 585900 | E21: =D21/D$7*100 -> 60 | F21: =RESULTAAT!D21 -> 615195 | G21: =F21/F$7*100 -> 60 | I21: =(D21-B21)/B21*100 -> 5 | J21: =(F21-D21)/D21*100 -> 5 | K21: =RESULTAAT!C21-RESULTAAT!B21 -> 27900 | L21: =RESULTAAT!D21-RESULTAAT!C21 -> 29295
A22: =RESULTAAT!A22 -> Voorraadwijziging | B22: =RESULTAAT!B22 -> 0 | C22: =RESULTAAT!B22/RESULTAAT!B$7*100 -> 0 | D22: =RESULTAAT!C22 -> 0 | E22: =D22/D$7*100 -> 0 | F22: =RESULTAAT!D22 -> 0 | G22: =F22/F$7*100 -> 0 | I22: =(D22-B22)/B22*100 -> #DIV/0! | J22: =(F22-D22)/D22*100 -> #DIV/0! | K22: =RESULTAAT!C22-RESULTAAT!B22 -> 0 | L22: =RESULTAAT!D22-RESULTAAT!C22 -> 0
A24: =RESULTAAT!A24 -> Diensten en Div. Goederen | B24: =RESULTAAT!B24 -> 178523.2 | C24: =RESULTAAT!B24/RESULTAAT!B$7*100 -> 18.891344 | D24: =RESULTAAT!C24 -> 185711.52 | E24: =D24/D$7*100 -> 19.018077 | F24: =RESULTAAT!D24 -> 193845.64 | G24: =F24/F$7*100 -> 18.905775 | I24: =(D24-B24)/B24*100 -> 4.0265467 | J24: =(F24-D24)/D24*100 -> 4.3799771 | K24: =RESULTAAT!C24-RESULTAAT!B24 -> 7188.32 | L24: =RESULTAAT!D24-RESULTAAT!C24 -> 8134.122
A26: =RESULTAAT!A26 -> Personeelskosten | B26: =RESULTAAT!B26 -> 86195.632 | C26: =RESULTAAT!B26/RESULTAAT!B$7*100 -> 9.1212309 | D26: =RESULTAAT!C26 -> 87919.545 | E26: =D26/D$7*100 -> 9.0035376 | F26: =RESULTAAT!D26 -> 89677.936 | G26: =F26/F$7*100 -> 8.7462937 | I26: =(D26-B26)/B26*100 -> 2 | J26: =(F26-D26)/D26*100 -> 2 | K26: =RESULTAAT!C26-RESULTAAT!B26 -> 1723.9126 | L26: =RESULTAAT!D26-RESULTAAT!C26 -> 1758.3909
A28: =RESULTAAT!A28 -> Afschrijvingen en waardeverminderingen | B28: =B29+B30+B31 -> 42000 | C28: =RESULTAAT!B28/RESULTAAT!B$7*100 -> 4.4444444 | D28: =D29+D30+D31 -> 42000 | E28: =D28/D$7*100 -> 4.3010753 | F28: =F29+F30+F31 -> 42000 | G28: =F28/F$7*100 -> 4.0962622 | I28: =(D28-B28)/B28*100 -> 0 | J28: =(F28-D28)/D28*100 -> 0 | K28: =RESULTAAT!C28-RESULTAAT!B28 -> 0 | L28: =RESULTAAT!D28-RESULTAAT!C28 -> 0
A29: =RESULTAAT!A29 -> Afschrijvingen | B29: =RESULTAAT!B29 -> 42000 | C29: =RESULTAAT!B29/RESULTAAT!B$7*100 -> 4.4444444 | D29: =RESULTAAT!C29 -> 42000 | E29: =D29/D$7*100 -> 4.3010753 | F29: =RESULTAAT!D29 -> 42000 | G29: =F29/F$7*100 -> 4.0962622 | I29: =(D29-B29)/B29*100 -> 0 | J29: =(F29-D29)/D29*100 -> 0 | K29: =RESULTAAT!C29-RESULTAAT!B29 -> 0 | L29: =RESULTAAT!D29-RESULTAAT!C29 -> 0
A30: =RESULTAAT!A30 -> Waardeverminderingen | B30: =RESULTAAT!B30 -> 0 | C30: =RESULTAAT!B30/RESULTAAT!B$7*100 -> 0 | D30: =RESULTAAT!C30 -> 0 | E30: =D30/D$7*100 -> 0 | F30: =RESULTAAT!D30 -> 0 | G30: =F30/F$7*100 -> 0 | I30: =(D30-B30)/B30*100 -> #DIV/0! | J30: =(F30-D30)/D30*100 -> #DIV/0! | K30: =RESULTAAT!C30-RESULTAAT!B30 -> 0 | L30: =RESULTAAT!D30-RESULTAAT!C30 -> 0
A31: =RESULTAAT!A31 -> Voorzieningen | B31: =RESULTAAT!B31 -> 0 | C31: =RESULTAAT!B31/RESULTAAT!B$7*100 -> 0 | D31: =RESULTAAT!C31 -> 0 | E31: =D31/D$7*100 -> 0 | F31: =RESULTAAT!D31 -> 0 | G31: =F31/F$7*100 -> 0 | I31: =(D31-B31)/B31*100 -> #DIV/0! | J31: =(F31-D31)/D31*100 -> #DIV/0! | K31: =RESULTAAT!C31-RESULTAAT!B31 -> 0 | L31: =RESULTAAT!D31-RESULTAAT!C31 -> 0
A33: =RESULTAAT!A33 -> Overige Bedrijfskosten | B33: =B34+B35 -> 4700 | C33: =RESULTAAT!B33/RESULTAAT!B$7*100 -> 0.4973545 | D33: =D34+D35 -> 4841 | E33: =D33/D$7*100 -> 0.49575013 | F33: =F34+F35 -> 4986.23 | G33: =F33/F$7*100 -> 0.48630727 | I33: =(D33-B33)/B33*100 -> 3 | J33: =(F33-D33)/D33*100 -> 3 | K33: =RESULTAAT!C33-RESULTAAT!B33 -> 141 | L33: =RESULTAAT!D33-RESULTAAT!C33 -> 145.23
A34: =RESULTAAT!A34 -> Bedrijfsbelastingen | B34: =RESULTAAT!B34 -> 4700 | C34: =RESULTAAT!B34/RESULTAAT!B$7*100 -> 0.4973545 | D34: =RESULTAAT!C34 -> 4841 | E34: =D34/D$7*100 -> 0.49575013 | F34: =RESULTAAT!D34 -> 4986.23 | G34: =F34/F$7*100 -> 0.48630727 | I34: =(D34-B34)/B34*100 -> 3 | J34: =(F34-D34)/D34*100 -> 3 | K34: =RESULTAAT!C34-RESULTAAT!B34 -> 141 | L34: =RESULTAAT!D34-RESULTAAT!C34 -> 145.23
A35: =RESULTAAT!A35 -> Minderwaarde verkoop mva | B35: =RESULTAAT!B35 -> 0 | C35: =RESULTAAT!B35/RESULTAAT!B$7*100 -> 0 | D35: =RESULTAAT!C35 -> 0 | E35: =D35/D$7*100 -> 0 | F35: =RESULTAAT!D35 -> 0 | G35: =F35/F$7*100 -> 0 | I35: =(D35-B35)/B35*100 -> #DIV/0! | J35: =(F35-D35)/D35*100 -> #DIV/0! | K35: =RESULTAAT!C35-RESULTAAT!B35 -> 0 | L35: =RESULTAAT!D35-RESULTAAT!C35 -> 0
A37: =RESULTAAT!A37 -> Niet recurrente bedrijfskosten | B37: =RESULTAAT!B37 -> 0 | C37: =RESULTAAT!B37/RESULTAAT!B$7*100 -> 0 | D37: =RESULTAAT!C37 -> 0 | E37: =D37/D$7*100 -> 0 | F37: =RESULTAAT!D37 -> 0 | G37: =F37/F$7*100 -> 0 | I37: =(D37-B37)/B37*100 -> #DIV/0! | J37: =(F37-D37)/D37*100 -> #DIV/0! | K37: =RESULTAAT!C37-RESULTAAT!B37 -> 0 | L37: =RESULTAAT!D37-RESULTAAT!C37 -> 0
A39: =RESULTAAT!A39 -> BRUTO TOEGEVOEGDE WAARDE | B39: =B7-B19-B24 -> 208476.8 | C39: =B39/B$7*100 -> 22.061037 | D39: =D7-D19-D24 -> 204888.48 | E39: =D39/D$7*100 -> 20.981923 | F39: =F7-F19-F24 -> 216284.36 | G39: =F39/F$7*100 -> 21.094225 | I39: =(D39-B39)/B39*100 -> -1.7212083 | J39: =(F39-D39)/D39*100 -> 5.5619906 | K39: =RESULTAAT!C39-RESULTAAT!B39 -> -3588.32 | L39: =RESULTAAT!D39-RESULTAAT!C39 -> 11395.878
A40: =RESULTAAT!A40 -> EBIT | B40: =B5-B17 -> 75581.168 | C40: =B40/B$7*100 -> 7.9980072 | D40: =D5-D17 -> 70127.935 | E40: =D40/D$7*100 -> 7.1815602 | F40: =F5-F17 -> 79620.192 | G40: =F40/F$7*100 -> 7.7653615 | I40: =(D40-B40)/B40*100 -> -7.215068 | J40: =(F40-D40)/D40*100 -> 13.535629 | K40: =RESULTAAT!C40-RESULTAAT!B40 -> -5453.2326 | L40: =RESULTAAT!D40-RESULTAAT!C40 -> 9492.2571
A41: =RESULTAAT!A41 -> EBITDA | B41: =B40+B29+B30 -> 117581.17 | C41: =B41/B$7*100 -> 12.442452 | D41: =D40+D29+D30 -> 112127.94 | E41: =D41/D$7*100 -> 11.482635 | F41: =F40+F29+F30 -> 121620.19 | G41: =F41/F$7*100 -> 11.861624 | I41: =(D41-B41)/B41*100 -> -4.6378453 | J41: =(F41-D41)/D41*100 -> 8.4655595 | K41: =RESULTAAT!C41-RESULTAAT!B41 -> -5453.2326 | L41: =RESULTAAT!D41-RESULTAAT!C41 -> 9492.2571
A42: =RESULTAAT!A42 -> BEDRIJFSRESULTAAT | B42: =B5-B17 -> 75581.168 | C42: =B42/B$7*100 -> 7.9980072 | D42: =D5-D17 -> 70127.935 | E42: =D42/D$7*100 -> 7.1815602 | F42: =F5-F17 -> 79620.192 | G42: =F42/F$7*100 -> 7.7653615 | I42: =(D42-B42)/B42*100 -> -7.215068 | J42: =(F42-D42)/D42*100 -> 13.535629 | K42: =RESULTAAT!C42-RESULTAAT!B42 -> -5453.2326 | L42: =RESULTAAT!D42-RESULTAAT!C42 -> 9492.2571
A44: =RESULTAAT!A44 -> Financiële Opbrengsten | B44: =RESULTAAT!B44 -> 0 | C44: =B44/B$7*100 -> 0 | D44: =RESULTAAT!C44 -> 0 | E44: =D44/D$7*100 -> 0 | F44: =RESULTAAT!D44 -> 0 | G44: =F44/F$7*100 -> 0 | I44: =(D44-B44)/B44*100 -> #DIV/0! | J44: =(F44-D44)/D44*100 -> #DIV/0! | K44: =RESULTAAT!C44-RESULTAAT!B44 -> 0 | L44: =RESULTAAT!D44-RESULTAAT!C44 -> 0
A45: =RESULTAAT!A45 -> Financiële Kosten | B45: =RESULTAAT!B45 -> 12981.469 | C45: =B45/B$7*100 -> 1.3737005 | D45: =RESULTAAT!C45 -> 11925.827 | E45: =D45/D$7*100 -> 1.2212829 | F45: =RESULTAAT!D45 -> 10777.785 | G45: =F45/F$7*100 -> 1.0511579 | I45: =(D45-B45)/B45*100 -> -8.1319143 | J45: =(F45-D45)/D45*100 -> -9.6265209 | K45: =RESULTAAT!C45-RESULTAAT!B45 -> -1055.642 | L45: =RESULTAAT!D45-RESULTAAT!C45 -> -1148.0423
A46: =RESULTAAT!A46 -> Niet recurrent Financieel (+/-) | B46: =RESULTAAT!B46 -> 0 | C46: =B46/B$7*100 -> 0 | D46: =RESULTAAT!C46 -> 0 | E46: =D46/D$7*100 -> 0 | F46: =RESULTAAT!D46 -> 0 | G46: =F46/F$7*100 -> 0 | I46: =(D46-B46)/B46*100 -> #DIV/0! | J46: =(F46-D46)/D46*100 -> #DIV/0! | K46: =RESULTAAT!C46-RESULTAAT!B46 -> 0 | L46: =RESULTAAT!D46-RESULTAAT!C46 -> 0
A48: =RESULTAAT!A48 -> RESULTAAT VOOR BELASTING | B48: =B42+B44-B45 -> 62599.699 | C48: =B48/B$7*100 -> 6.6243067 | D48: =D42+D44-D45 -> 58202.108 | E48: =D48/D7*100 -> 5.9602773 | F48: =F42+F44-F45 -> 68842.407 | G48: =F48/F7*100 -> 6.7142035 | I48: =(D48-B48)/B48*100 -> -7.024939 | J48: =(F48-D48)/D48*100 -> 18.281639 | K48: =RESULTAAT!C48-RESULTAAT!B48 -> -4397.5907 | L48: =RESULTAAT!D48-RESULTAAT!C48 -> 10640.299
A50: =RESULTAAT!A50 -> Onttrekking aan de uitgestelde belasting | B50: =RESULTAAT!B50 -> 0 | D50: =RESULTAAT!C50 -> 0 | F50: =RESULTAAT!D50 -> 0 | I50: =(D50-B50)/B50*100 -> #DIV/0! | J50: =(F50-D50)/D50*100 -> #DIV/0! | K50: =RESULTAAT!C50-RESULTAAT!B50 -> 0 | L50: =RESULTAAT!D50-RESULTAAT!C50 -> 0
A51: =RESULTAAT!A51 -> Overboeking naar de uitgestelde belasting | B51: =RESULTAAT!B51 -> 0 | D51: =RESULTAAT!C51 -> 0 | F51: =RESULTAAT!D51 -> 0 | I51: =(D51-B51)/B51*100 -> #DIV/0! | J51: =(F51-D51)/D51*100 -> #DIV/0! | K51: =RESULTAAT!C51-RESULTAAT!B51 -> 0 | L51: =RESULTAAT!D51-RESULTAAT!C51 -> 0
A52: =RESULTAAT!A52 -> Belastingen op het resultaat | B52: =RESULTAAT!B52 -> 15649.925 | C52: =B52/B$7*100 -> 1.6560767 | D52: =RESULTAAT!C52 -> 14550.527 | E52: =D52/D7*100 -> 1.4900693 | F52: =RESULTAAT!D52 -> 17210.602 | G52: =F52/F7*100 -> 1.6785509 | I52: =(D52-B52)/B52*100 -> -7.024939 | J52: =(F52-D52)/D52*100 -> 18.281639 | K52: =RESULTAAT!C52-RESULTAAT!B52 -> -1099.3977 | L52: =RESULTAAT!D52-RESULTAAT!C52 -> 2660.0748
A54: =RESULTAAT!A54 -> NETTO RESULTAAT | B54: =B48+B50-B51-B52 -> 46949.774 | C54: =B54/B$7*100 -> 4.96823 | D54: =D48+D50-D51-D52 -> 43651.581 | E54: =D54/D7*100 -> 4.470208 | F54: =F48+F50-F51-F52 -> 51631.805 | G54: =F54/F7*100 -> 5.0356526 | I54: =(D54-B54)/B54*100 -> -7.024939 | J54: =(F54-D54)/D54*100 -> 18.281639 | K54: =RESULTAAT!C54-RESULTAAT!B54 -> -3298.193 | L54: =RESULTAAT!D54-RESULTAAT!C54 -> 7980.2245
A56: =RESULTAAT!A56 -> Onttrekking aan de Belastingvrije Reserves | B56: =RESULTAAT!B56 -> 0 | D56: =RESULTAAT!C56 -> 0 | F56: =RESULTAAT!D56 -> 0 | I56: =(D56-B56)/B56*100 -> #DIV/0! | J56: =(F56-D56)/D56*100 -> #DIV/0! | K56: =RESULTAAT!C56-RESULTAAT!B56 -> 0 | L56: =RESULTAAT!D56-RESULTAAT!C56 -> 0
A57: =RESULTAAT!A57 -> Overboeking naar de Belastingvrije Reserves | B57: =RESULTAAT!B57 -> 0 | D57: =RESULTAAT!C57 -> 0 | F57: =RESULTAAT!D57 -> 0 | I57: =(D57-B57)/B57*100 -> #DIV/0! | J57: =(F57-D57)/D57*100 -> #DIV/0! | K57: =RESULTAAT!C57-RESULTAAT!B57 -> 0 | L57: =RESULTAAT!D57-RESULTAAT!C57 -> 0
A59: =RESULTAAT!A59 -> TE BESTEMMEN RESULTAAT | B59: =B54+B56-B57 -> 46949.774 | C59: =B59/B$7*100 -> 4.96823 | D59: =D54+D56-D57 -> 43651.581 | E59: =D59/D7*100 -> 4.470208 | F59: =F54+F56-F57 -> 51631.805 | G59: =F59/F7*100 -> 5.0356526 | I59: =(D59-B59)/B59*100 -> -7.024939 | J59: =(F59-D59)/D59*100 -> 18.281639 | K59: =RESULTAAT!C59-RESULTAAT!B59 -> -3298.193 | L59: =RESULTAAT!D59-RESULTAAT!C59 -> 7980.2245

Sheet INVEST TABEL
A1: =ACTIVA!A1 -> VDO
A2: INVESTERINGEN | C2: MATERIELE VASTE ACTIVA
A4: Jaar | B4: Omschrijving | C4: Aanschaf | D4: % | E4: Afschrijvingen | J4: Boekwaarde
E5: Jaar 1 | F5: Jaar 2 | G5: Jaar 3 | H5: desinvestering | I5: Totaal
A7: Terreinen en Gebouwen | C7: =C8+C9 -> 0 | E7: =E8+E9 -> 0 | F7: =F8+F9 -> 0 | G7: =G8+G9 -> 0 | H7: =H8+H9 -> 0 | I7: =E7+F7+G7+H7 -> 0 | J7: =C7-I7 -> 0
E8: =C8*D8% -> 0 | F8: =E8 -> 0 | G8: =F8 -> 0 | I8: =E8+F8+G8+H8 -> 0 | J8: =C8-I8 -> 0
E9: =C9*D9% -> 0 | F9: =E9 -> 0 | G9: =F9 -> 0 | I9: =E9+F9+G9+H9 -> 0 | J9: =C9-I9 -> 0
A11: Machines, Installaties | C11: =C12+C13 -> 300000 | E11: =E12+E13 -> 30000 | F11: =F12+F13 -> 30000 | G11: =G12+G13 -> 30000 | H11: =H12+H13 -> 0 | I11: =E11+F11+G11+H11 -> 90000 | J11: =C11-I11 -> 210000
A12: =E5 -> Jaar 1 | B12: Machines | C12: =OPGAVE!B15 -> 300000 | D12: 10 | E12: =C12*D12% -> 30000 | F12: =E12 -> 30000 | G12: =(C12+C13)*D12% -> 30000 | I12: =E12+F12+G12+H12 -> 90000 | J12: =C12-I12 -> 210000
A13: Jaar 3 | B13: Verkoop machine | H13: =(C13*D12%)*2 -> 0 | I13: =E13+F13+G13+H13 -> 0 | J13: =C13-I13 -> 0 | L13: 50000
I14: =E14+F14+G14+H14 -> 0 | L14: =-E12-F12 -> -60000
L15: =SUM(L13:L14) -> -10000
A16: Meubilair, Inrichting | C16: =C17+C18 -> 46000 | E16: =E17+E18 -> 12000 | F16: =F17+F18 -> 12000 | G16: =G17+G18 -> 12000 | H16: =H17+H18 -> 0 | I16: =E16+F16+G16+H16 -> 36000 | J16: =C16-I16 -> 10000
A17: Jaar 1 | B17: Inrichting kantoren | C17: =OPGAVE!B20 -> 25000 | D17: 20 | E17: 5000 | F17: =C17*D17% -> 5000 | G17: 5000 | I17: =E17+F17+G17+H17 -> 15000 | J17: =C17-I17 -> 10000 | L17: 70000
A18: Jaar 1 | B18: Informatica materiaal | C18: =OPGAVE!B21 -> 21000 | D18: 33.33 | E18: 7000 | F18: =E18 -> 7000 | G18: 7000 | I18: =E18+F18+G18+H18 -> 21000 | J18: =C18-I18 -> 0 | L18: =L17-L15 -> 80000 | M18: meerwaarde
A20: Rollend Materieel | C20: =C21+C22 -> 0 | E20: =E21+E22 -> 0 | F20: =F21+F22 -> 0 | G20: =G21+G22 -> 0 | H20: =H21+H22 -> 0 | I20: =E20+F20+G20+H20 -> 0 | J20: =J21+J22 -> 0
E21: =C21*D21% -> 0 | F21: =E21 -> 0 | G21: =F21 -> 0 | I21: =E21+F21+G21+H21 -> 0 | J21: =C21-I21 -> 0
E22: =C22*D22% -> 0 | F22: =E22 -> 0 | G22: =F22 -> 0 | I22: =E22+F22+G22+H22 -> 0 | J22: =C22-I22 -> 0
A24: Leasing en soortgelijke | C24: =SUM(C25:C27) -> 0 | E24: =SUM(E25:E27) -> 0 | F24: =SUM(F25:F27) -> 0 | G24: =SUM(G25:G27) -> 0 | H24: =SUM(H25:H27) -> 0 | I24: =SUM(I25:I27) -> 0 | J24: =SUM(J25:J27) -> 0
A25: =A12 -> Jaar 1 | E25: =C25*D25% -> 0 | F25: =E25 -> 0 | G25: =F25 -> 0 | I25: =E25+F25+G25+H25 -> 0 | J25: =C25-I25 -> 0
E26: =C26*D26% -> 0 | F26: =E26 -> 0 | G26: =F26 -> 0 | I26: =E26+F26+G26+H26 -> 0 | J26: =C26-I26 -> 0
E27: =C27*D27% -> 0 | F27: =E27 -> 0 | G27: =F27 -> 0 | I27: =E27+F27+G27+H27 -> 0 | J27: =C27-I27 -> 0
A29: Overige MVA | C29: =C30+C31 -> 0 | E29: =E30+E31 -> 0 | F29: =F30+F31 -> 0 | G29: =G30+G31 -> 0 | H29: =H30+H31 -> 0 | I29: =E29+F29+G29+H29 -> 0 | J29: =J30+J31 -> 0
E30: =C30*D30% -> 0 | F30: =E30 -> 0 | G30: =F30 -> 0 | I30: =E30+F30+G30+H30 -> 0 | J30: =C30-I30 -> 0
E31: =C31*D31% -> 0 | F31: =E31 -> 0 | G31: =F31 -> 0 | I31: =E31+F31+G31+H31 -> 0 | J31: =C31-I31 -> 0
A33: TOTAAL | C33: =C7+C11+C16+C20+C24+C29 -> 346000 | E33: =E7+E11+E16+E20+E24+E29 -> 42000 | F33: =F7+F11+F16+F20+F24+F29 -> 42000 | G33: =G7+G11+G16+G20+G24+G29 -> 42000 | H33: =H7+H11+H16+H20+H24+H29 -> 0 | I33: =I7+I11+I16+I20+I24+I29 -> 126000 | J33: =J7+J11+J16+J20+J24+J29 -> 220000

Sheet FIN ANALYSE
A1: =PASSIVA!A1 -> VDO
A2: SAMENVATTENDE TABEL FINANCIELE ANALYSE
B4: Jaar 1 | C4: Jaar 2 | D4: Jaar 3
A5: Cashflow
A6: operationele cashflow | C6: =$B$118 -> 96775.393 | D6: =$C$118 -> 107381.81
A7: vrije cashflow | C7: =B$126 -> 96775.393 | D7: =C$126 -> 107381.81
A8: totale cashflow | C8: =B$138 -> 62500.284 | D8: =C$138 -> 73111.314
A9: vermogensstroom : toename + afname - | C9: =B$213 -> 96775.393 | D9: =C$213 -> 107381.81
A11: Liquiditeit
A12: nettobedrijfskapitaal (NBK) | B12: =B$150 -> 61070.544 | C12: =C$150 -> 123229.41 | D12: =D$150 -> 192166.57
A13: behoefte aan NBK (overschot -) | B13: =B$160 -> -24409.885 | C13: =C$160 -> -23607.869 | D13: =D$160 -> -26580.09
A14: nettokas | B14: =B$166 -> 85480.429 | C14: =C$166 -> 146837.28 | D14: =D$166 -> 218746.66
A15: current ratio | B15: =B$156 -> 1.5615209 | C15: =C$156 -> 2.0982957 | D15: =D$156 -> 2.6063445
A16: voorraadrotatie | B16: =B$299 -> 0 | C16: =C$299 -> 0 | D16: =D$299 -> 0
A17: aantal dagen voorraad | B17: =B$300 -> 0 | C17: =C$300 -> 0 | D17: =D$300 -> 0
A18: klantenkrediet | B18: =B$307 -> 23.94709 | C18: =C$307 -> 24.333333 | D18: =D$307 -> 24.333333
A19: leverancierskrediet | B19: =B$314 -> 28.567042 | C19: =C$314 -> 28.631381 | D19: =D$314 -> 28.672131
A20: aantal dagen exploitatiecyclus | B20: =B18-B19 -> -4.6199521 | C20: =C18-C19 -> -4.2980481 | D20: =D18-D19 -> -4.3387972
A22: Solvabiliteit
A23: algemene schuldgraad
A24: VV/EV | B24: =B$228 -> 2.4598795 | C24: =C$228 -> 1.7542982 | D24: =D$228 -> 1.2899241
A25: VV/TV | B25: =B$231 -> 0.71097259 | C25: =C$231 -> 0.63693111 | D25: =D$231 -> 0.5633043
A26: schuldgraad | B26: =B$253 -> 1.0415522 | C26: =C$253 -> 0.31999082 | D26: =D$253 -> -0.16713053
A27: lange termijnschuldgraad | B27: =B234 -> 1.6657258 | C27: =C234 -> 1.1330372 | D27: =D234 -> 0.5151277
A28: solvabiliteitsgraad
A29: EV/VV | B29: =B$238 -> 0.40652398 | C29: =C$238 -> 0.5700285 | D29: =D$238 -> 0.77523942
A30: EV/TV | B30: =B$239 -> 0.28902741 | C30: =C$239 -> 0.36306889 | D30: =D$239 -> 0.4366957
A31: lange termijn solvabiliteitsgraad | B31: =B241 -> 0.60033891 | C31: =C241 -> 0.88258354 | D31: =D241 -> 1.9412662
A32: nettoschuld | B32: =B$248 -> 142640.34 | C32: =C$248 -> 57790.776 | D32: =D$248 -> -38813.25
A33: netto financiële schuldgraad | B33: =B253 -> 1.0415522 | C33: =C253 -> 0.31999082 | D33: =D253 -> -0.16713053
A34: netto financiële schuld ratio | B34: =B257 -> 1.2131223 | C34: =C257 -> 0.51540034 | D34: =D257 -> -0.31913492
A35: zelffinancieringsgraad | B35: =B$265 -> 0.099085754 | C35: =C$265 -> 0.18213891 | D35: =D$265 -> 0.26745797
A36: intrestdekking | B36: =B$271 -> 5.8222352 | C36: =C$271 -> 5.8803413 | D36: =D$271 -> 7.3874355
A37: dekking VV door CF | C37: =B278 -> 0.2703404 | D37: =C278 -> 0.31256116
A38: schuldaflossingscapaciteit | B38: =B$284 -> 1.2131223 | C38: =C$284 -> 0.51540034 | D38: =D$284 -> -0.31913492
A40: Rendabiliteit
A41: omzet | B41: =RESULTAAT!B8 -> 930000 | C41: =RESULTAAT!C8 -> 976500 | D41: =RESULTAAT!D8 -> 1025325
A42: break even omzet | B42: ='OMZET en BREAK EVEN'!C34 -> #REF!
A43: bruto toegevoegde waarde | B43: =B$325 -> 208476.8 | C43: =C$325 -> 204888.48 | D43: =D$325 -> 216284.36
A44: bruto toegevoegde waarde marge | B44: =B$326 -> 0.22061037 | C44: =C$326 -> 0.20981923 | D44: =D$326 -> 0.21094225
A45: aandeel in toegevoegde waarde
A46: bezoldigingen | B46: =B$331 -> 0.41345431 | C46: =C$331 -> 0.42910926 | D46: =D$331 -> 0.41462978
A47: afschrijving en waardevermindering | B47: =B$333 -> 0.20146127 | C47: =C$333 -> 0.20498956 | D47: =D$333 -> 0.1941888
A48: financiële kosten | B48: =B$335 -> 0.062268173 | C48: =C$335 -> 0.058206432 | D48: =D$335 -> 0.049831552
A49: belastingen | B49: =B$337 -> 0.075067944 | C49: =C$337 -> 0.071016814 | D49: =D$337 -> 0.079573955
A50: materiële vaste activa | B50: =B$341 -> 1.439009 | C50: =C$341 -> 0.1220176 | D50: =D$341 -> 0
A51: netto rendabiliteit EV | B51: =B$350 -> 0.34282476 | C51: =C$350 -> 0.24170129 | D51: =D$350 -> 0.22232745
A52: netto rendabiliteit TV | B52: =B$351 -> 0.15951125 | C52: =C$351 -> 0.14098051 | D52: =D$351 -> 0.14971934
A53: bruto rendabiliteit EV | C53: =C355 -> 0.47425769 | D53: =D355 -> 0.40318017
A54: financiële hefboom multiplicator | B54: =B$361 -> 2.8656267 | C54: =C$361 -> 2.2859074 | D54: =D$361 -> 1.9799486
A55: graad financiële hefboom | B55: =B365 -> 1.2073727 | C55: =C365 -> 1.2049037 | D55: =D365 -> 1.1565574
A56: bruto verkoopmarge | B56: =B$371 -> 0.12643136 | C56: =C$371 -> 0.11482635 | D56: =D$371 -> 0.11861624
A57: netto verkoopmarge | B57: =B$372 -> 0.081270073 | C57: =C$372 -> 0.071815602 | D57: =D$372 -> 0.077653615
A58: graad van operationele hefboom | B58: =B$377 -> #REF! | C58: =C$377 -> 15.745523 | D58: =D$377 -> 14.012295
A59: brutorendement bedrijfsactiva | B59: =B$385 -> 1.8964705 | C59: =C$385 -> 1.7223953 | D59: =D$385 -> 1.7792435
A60: rotatie bedrijfsactiva | B60: =B$386 -> 15 | C60: =C$386 -> 15 | D60: =D$386 -> 15
A61: bruto rendabiliteit activa | B61: =B393 -> 0.24815069 | C61: =C393 -> 0.2254145 | D61: =D393 -> 0.22869695
A62: netto rendabiliteit activa | B62: =B394 -> 0.15951125 | C62: =C394 -> 0.14098051 | D62: =D394 -> 0.14971934
A66: =A1 -> VDO
A67: CASHFLOW - DIRECTE METHODE
B69: =ACTIVA!B4 -> Jaar 1 | C69: =ACTIVA!D4 -> Jaar 2 | D69: =ACTIVA!F4 -> Jaar 3
B70: IN
A72: Inbreng | B72: =PASSIVA!B8 -> 90000
A73: Achtergestelde lening | B73: =PASSIVA!B31 -> 0
A74: Handelsvorderingen bewerkingen | B74: ='70-40-44-55'!G13 -> 868000 | C74: ='70-40-44-55'!G17-'70-40-44-55'!G13 -> 973400 | D74: ='70-40-44-55'!G21-'70-40-44-55'!G17 -> 1022070
A75: Handelsvorderingen verkoop MVA
A76: Subsidies | B76: =OPGAVE!B23 -> 15000
A77: Financiële opbrengsten
A79: Inkomende kasstromen | B79: =SUM(B71:B77) -> 973000 | C79: =SUM(C72:C77) -> 973400 | D79: =SUM(D72:D77) -> 1022070
B81: UIT
A82: Lease machines aflossingen | B82: =SUM(Aflossingstabel!F14:F24) -> 19529.949 | C82: =SUM(Aflossingstabel!F25:F36) -> 22349.281 | D82: =SUM(Aflossingstabel!F37:F48) -> 23492.713
A83: Betaling 10 % voorschot | B83: =-DETAILS!B83 -> 30000
A84: Investeringen | B84: =OPGAVE!B20+OPGAVE!B21 -> 46000
A85: Leveranciers goederen | B85: ='70-40-44-55'!H28 -> 488250 | C85: ='70-40-44-55'!H31-'70-40-44-55'!H28 -> 582412.5 | D85: ='70-40-44-55'!H34-'70-40-44-55'!H31 -> 611533.12
A86: Leveranciers diensten | B86: =DETAILS!B54 -> 178523.2 | C86: =DETAILS!C54 -> 185711.52 | D86: =DETAILS!D54 -> 193845.64
A87: Bezoldigingen en Sociale lasten | B87: =DETAILS!B74 -> 86195.632 | C87: =DETAILS!C74 -> 87919.545 | D87: =DETAILS!D74 -> 89677.936
A88: Overige bedrijfskosten | B88: =DETAILS!B91 -> 4700 | C88: =DETAILS!B92 -> 4841 | D88: =DETAILS!B93 -> 4986.23
A89: Intresten | B89: =SUM(Aflossingstabel!E14:E24) -> 11971.51 | C89: =SUM(Aflossingstabel!E25:E36) -> 12015.946 | D89: =SUM(Aflossingstabel!E37:E48) -> 10872.514
A90: Belastingen | C90: =RESULTAAT!B52 -> 15649.925 | D90: =RESULTAAT!C52 -> 14550.527
A92: Uitgaande kasstromen | B92: =SUM(B82:B90) -> 865170.29 | C92: =SUM(C82:C90) -> 910899.72 | D92: =SUM(D82:D90) -> 948958.69
A93: Verschil In/Uit | B93: =B79-B92 -> 107829.71 | C93: =C79-C92 -> 62500.284 | D93: =D79-D92 -> 73111.314
A94: SALDO Liquide Middelen | B94: =B93 -> 107829.71 | C94: =B94+C93 -> 170329.99 | D94: =C94+D93 -> 243441.31
A95: Controle T | B95: ='70-40-44-55'!C54 -> 107829.71 | C95: ='70-40-44-55'!C65 -> 170329.99 | D95: ='70-40-44-55'!C74 -> 243441.31
A97: CASH FLOW - INDIRECTE METHODE
B99: Jaar 2 | C99: Jaar 3
A100: Resultaat voor belasting | B100: =RESULTAAT!C48 -> 58202.108 | C100: =RESULTAAT!D48 -> 68842.407
A101: niet-kaskosten (+) | B101: =RESULTAAT!C28 -> 42000 | C101: =RESULTAAT!D28+RESULTAAT!D35 -> 42000
A102: niet-kasopbrengsten (-)
A103: intresten uit vreemd vermogen (+) | B103: =RESULTAAT!C45 -> 11925.827 | C103: =RESULTAAT!D45 -> 10777.785
A105: pot. operat. CF voor belastingen | B105: =B100+B101+B103-B102 -> 112127.94 | C105: =C100+C101+C103-C102 -> 121620.19
A107: operationele belastingen (-) | B107: =RESULTAAT!C52 -> 14550.527 | C107: =RESULTAAT!D52 -> 17210.602
A109: cashflow van het eigen vermogen | B109: =B111-B103 -> 85651.581 | C109: =C111-C103 -> 93631.805
A111: potentiële operationele cashflow | B111: =B105-B107 -> 97577.408 | C111: =C105-C107 -> 104409.59
A113: mutaties
A114: operationele activa op korte termijn | B114: =(ACTIVA!I30+ACTIVA!I34+ACTIVA!I42)*-1 -> -3100 | C114: =(ACTIVA!J30+ACTIVA!J34+ACTIVA!J42)*-1 -> -3255 | F114: opgelet : stijging A is in -, daling A is in + (dus mogelijk de inhoud cel * -1)
A115: operationele passiva korte termijn | B115: =PASSIVA!K45+PASSIVA!K48+PASSIVA!K53+PASSIVA!K56 -> 2297.9843 | C115: =PASSIVA!L45+PASSIVA!L48+PASSIVA!L53+PASSIVA!L56 -> 6227.2212
A116: cashflow uit operationele activiteiten | B116: =SUM(B114:B115) -> -802.01574 | C116: =SUM(C114:C115) -> 2972.2212
A118: operationele cash flow | B118: =B111+B116 -> 96775.393 | C118: =C111+C116 -> 107381.81
A120: mutaties
A121: investeringen | B121: =-ACTIVA!I8 -> 42000 | C121: =-ACTIVA!J8 -> 42000 | F121: opgelet : stijging VA is in -, desinvesteringen (daling VA) is in +
...

Sheet CASH FLOW MAAND
A1: =PASSIVA!A1 -> VDO
A2: VERMOGENSSTROOM TABEL DIRECTE METHODE
A4: JAAR 1 | B4: jan | C4: feb | D4: mrt | E4: apr | F4: mei | G4: jun | H4: jul | I4: aug | J4: sep | K4: okt | L4: nov | M4: dec | N4: TOTAAL
A5: INKOMEND
A7: ='FIN ANALYSE'!A72 -> Inbreng | B7: ='FIN ANALYSE'!B72 -> 90000 | N7: =SUM(B7:M7) -> 90000
A8: ='FIN ANALYSE'!A73 -> Achtergestelde lening | B8: ='FIN ANALYSE'!B73 -> 0 | N8: =SUM(B8:M8) -> 0
A9: ='FIN ANALYSE'!A74 -> Handelsvorderingen bewerkingen | C9: ='FIN ANALYSE'!B74/11 -> 78909.091 | D9: =C9 -> 78909.091 | E9: =D9 -> 78909.091 | F9: =E9 -> 78909.091 | G9: =F9 -> 78909.091 | H9: =G9 -> 78909.091 | I9: =H9 -> 78909.091 | J9: =I9 -> 78909.091 | K9: =J9 -> 78909.091 | ... M9: =L9 -> 78909.091 | N9: =SUM(B9:M9) -> 868000
A10: ='FIN ANALYSE'!A75 -> Handelsvorderingen verkoop MVA | C10: ='FIN ANALYSE'!B75 -> 0 | N10: =SUM(B10:M10) -> 0
A11: ='FIN ANALYSE'!A76 -> Subsidies
A12: ='FIN ANALYSE'!A77 -> Financiële opbrengsten | B12: ='FIN ANALYSE'!B76 -> 15000 | N12: =SUM(B12:M12) -> 15000
A14: TOTAAL IN | B14: =SUM(B7:B12) -> 105000 | C14: =SUM(C7:C12) -> 78909.091 | D14: =SUM(D7:D12) -> 78909.091 | E14: =SUM(E7:E12) -> 78909.091 | F14: =SUM(F7:F12) -> 78909.091 | G14: =SUM(G7:G12) -> 78909.091 | H14: =SUM(H7:H12) -> 78909.091 | I14: =SUM(I7:I12) -> 78909.091 | ... N14: =SUM(N7:N12) -> 973000
A16: UITGAAND
A17: ='FIN ANALYSE'!A82 -> Lease machines aflossingen | B17: ='FIN ANALYSE'!B82/12 -> 1627.4957 | C17: =B17 -> 1627.4957 | D17: =C17 -> 1627.4957 | E17: =D17 -> 1627.4957 | F17: =E17 -> 1627.4957 | G17: =F17 -> 1627.4957 | H17: =G17 -> 1627.4957 | I17: =H17 -> 1627.4957 | J17: =I17 -> 1627.4957 | ... M17: =L17 -> 1627.4957 | N17: =SUM(B17:M17) -> 19529.949
A18: ='FIN ANALYSE'!A83 -> Betaling 10 % voorschot | B18: =B8 -> 0 | N18: =SUM(B18:M18) -> 0
A19: ='FIN ANALYSE'!A84 -> Investeringen | N19: =SUM(B19:M19) -> 0
A20: ='FIN ANALYSE'!A85 -> Leveranciers goederen | B20: ='FIN ANALYSE'!B85/12 -> 40687.5 | C20: =B20 -> 40687.5 | D20: =C20 -> 40687.5 | E20: =D20 -> 40687.5 | F20: =E20 -> 40687.5 | G20: =F20 -> 40687.5 | H20: =G20 -> 40687.5 | I20: =H20 -> 40687.5 | J20: =I20 -> 40687.5 | ... M20: =L20 -> 40687.5 | N20: =SUM(B20:M20) -> 488250
A21: ='FIN ANALYSE'!#REF! -> #REF! | C21: ='FIN ANALYSE'!B86/11 -> 16229.382 | D21: =C21 -> 16229.382 | E21: =D21 -> 16229.382 | F21: =E21 -> 16229.382 | G21: =F21 -> 16229.382 | H21: =G21 -> 16229.382 | I21: =H21 -> 16229.382 | J21: =I21 -> 16229.382 | K21: =J21 -> 16229.382 | ... M21: =L21 -> 16229.382 | N21: =SUM(B21:M21) -> 178523.2
A22: Leveranciers kosten | N22: =SUM(B22:M22) -> 0
A23: ='FIN ANALYSE'!#REF! -> #REF! | E23: ='FIN ANALYSE'!#REF!/3 -> #REF! | H23: =E23 -> #REF! | K23: =H23 -> #REF! | N23: =SUM(B23:M23) -> #REF!
A24: ='FIN ANALYSE'!A87 -> Bezoldigingen en Sociale lasten | B24: ='FIN ANALYSE'!B87/12 -> 7182.9693 | C24: =B24 -> 7182.9693 | D24: =C24 -> 7182.9693 | E24: =D24 -> 7182.9693 | F24: =E24 -> 7182.9693 | G24: =F24 -> 7182.9693 | H24: =G24 -> 7182.9693 | I24: =H24 -> 7182.9693 | J24: =I24 -> 7182.9693 | ... M24: =L24 -> 7182.9693 | N24: =SUM(B24:M24) -> 86195.632
A25: ='FIN ANALYSE'!A88 -> Overige bedrijfskosten | B25: ='FIN ANALYSE'!B88/12 -> 391.66667 | C25: =B25 -> 391.66667 | D25: =C25 -> 391.66667 | E25: =D25 -> 391.66667 | F25: =E25 -> 391.66667 | G25: =F25 -> 391.66667 | H25: =G25 -> 391.66667 | I25: =H25 -> 391.66667 | J25: =I25 -> 391.66667 | ... M25: =L25 -> 391.66667 | N25: =SUM(B25:M25) -> 4700
A26: ='FIN ANALYSE'!A89 -> Intresten | B26: ='FIN ANALYSE'!B89/12 -> 997.62579 | C26: =B26 -> 997.62579 | D26: =C26 -> 997.62579 | E26: =D26 -> 997.62579 | F26: =E26 -> 997.62579 | G26: =F26 -> 997.62579 | H26: =G26 -> 997.62579 | I26: =H26 -> 997.62579 | J26: =I26 -> 997.62579 | ... M26: =L26 -> 997.62579 | N26: =SUM(B26:M26) -> 11971.51
A27: ='FIN ANALYSE'!A90 -> Belastingen | N27: =SUM(B27:M27) -> 0
A29: TOTAAL UIT | B29: =SUM(B17:B28) -> 50887.258 | C29: =SUM(C17:C28) -> 67116.639 | D29: =SUM(D17:D28) -> 67116.639 | E29: =SUM(E17:E28) -> #REF! | F29: =SUM(F17:F28) -> 67116.639 | G29: =SUM(G17:G28) -> 67116.639 | H29: =SUM(H17:H28) -> #REF! | I29: =SUM(I17:I28) -> 67116.639 | ... N29: =SUM(N17:N28) -> #REF!
A30: SALDO PERIODE | B30: =B14-B29 -> 54112.742 | C30: =C14-C29 -> 11792.452 | D30: =D14-D29 -> 11792.452 | E30: =E14-E29 -> #REF! | F30: =F14-F29 -> 11792.452 | G30: =G14-G29 -> 11792.452 | H30: =H14-H29 -> #REF! | I30: =I14-I29 -> 11792.452 | ... N30: =N14-N29 -> #REF!
A31: SALDO BANK JAAR 1 | B31: =B30 -> 54112.742 | C31: =B31+C30 -> 65905.194 | D31: =C31+D30 -> 77697.646 | E31: =D31+E30 -> #REF! | F31: =E31+F30 -> #REF! | G31: =F31+G30 -> #REF! | H31: =G31+H30 -> #REF! | I31: =H31+I30 -> #REF! | J31: =I31+J30 -> #REF! | ... M31: =L31+M30 -> #REF!
A34: JAAR 2 | B34: jan | C34: feb | D34: mrt | E34: apr | F34: mei | G34: jun | H34: jul | I34: aug | J34: sep | K34: okt | L34: nov | M34: dec | N34: TOTAAL
A35: INKOMEND
A37: =A7 -> Inbreng | N37: =SUM(B37:M37) -> 0
A38: =A8 -> Achtergestelde lening | N38: =SUM(B38:M38) -> 0
A39: =A9 -> Handelsvorderingen bewerkingen | B39: =M9 -> 78909.091 | C39: =('FIN ANALYSE'!C74-'CASH FLOW MAAND'!B39)/11 -> 81317.355 | D39: =C39 -> 81317.355 | E39: =D39 -> 81317.355 | F39: =E39 -> 81317.355 | G39: =F39 -> 81317.355 | H39: =G39 -> 81317.355 | I39: =H39 -> 81317.355 | J39: =I39 -> 81317.355 | K39: =J39 -> 81317.355 | ... M39: =L39 -> 81317.355 | N39: =SUM(B39:M39) -> 973400
A40: =A10 -> Handelsvorderingen verkoop MVA | N40: =SUM(B40:M40) -> 0
A41: =A11 -> Subsidies | N41: =SUM(B41:M41) -> 0
A42: =A12 -> Financiële opbrengsten | N42: =SUM(B42:M42) -> 0
A44: TOTAAL IN | B44: =SUM(B37:B42) -> 78909.091 | C44: =SUM(C37:C42) -> 81317.355 | D44: =SUM(D37:D42) -> 81317.355 | E44: =SUM(E37:E42) -> 81317.355 | F44: =SUM(F37:F42) -> 81317.355 | G44: =SUM(G37:G42) -> 81317.355 | H44: =SUM(H37:H42) -> 81317.355 | I44: =SUM(I37:I42) -> 81317.355 | ... N44: =SUM(N37:N42) -> 973400
A46: UITGAAND
A48: =A17 -> Lease machines aflossingen | B48: ='FIN ANALYSE'!C82/12 -> 1862.4401 | C48: =B48 -> 1862.4401 | D48: =C48 -> 1862.4401 | E48: =D48 -> 1862.4401 | F48: =E48 -> 1862.4401 | G48: =F48 -> 1862.4401 | H48: =G48 -> 1862.4401 | I48: =H48 -> 1862.4401 | J48: =I48 -> 1862.4401 | ... M48: =L48 -> 1862.4401 | N48: =SUM(B48:M48) -> 22349.281
A49: =A18 -> Betaling 10 % voorschot | N49: =SUM(B49:M49) -> 0
A50: =A19 -> Investeringen | B50: ='FIN ANALYSE'!C84 -> 0 | N50: =SUM(B50:M50) -> 0
A51: =A20 -> Leveranciers goederen | B51: ='FIN ANALYSE'!C85/12 -> 48534.375 | C51: =B51 -> 48534.375 | D51: =C51 -> 48534.375 | E51: =D51 -> 48534.375 | F51: =E51 -> 48534.375 | G51: =F51 -> 48534.375 | H51: =G51 -> 48534.375 | I51: =H51 -> 48534.375 | J51: =I51 -> 48534.375 | ... M51: =L51 -> 48534.375 | N51: =SUM(B51:M51) -> 582412.5
A52: =A21 -> #REF! | B52: =M21 -> 16229.382 | C52: =('FIN ANALYSE'!C86-'CASH FLOW MAAND'!B52)/11 -> 15407.467 | D52: =C52 -> 15407.467 | E52: =D52 -> 15407.467 | F52: =E52 -> 15407.467 | G52: =F52 -> 15407.467 | H52: =G52 -> 15407.467 | I52: =H52 -> 15407.467 | J52: =I52 -> 15407.467 | K52: =J52 -> 15407.467 | ... M52: =L52 -> 15407.467 | N52: =SUM(B52:M52) -> 185711.52
A53: =A22 -> Leveranciers kosten | N53: =SUM(B53:M53) -> 0
A54: =A23 -> #REF! | E54: ='FIN ANALYSE'!#REF!/3 -> #REF! | H54: =E54 -> #REF! | K54: =H54 -> #REF! | N54: =SUM(B54:M54) -> #REF!
A55: =A24 -> Bezoldigingen en Sociale lasten | B55: ='FIN ANALYSE'!C87/12 -> 7326.6287 | C55: =B55 -> 7326.6287 | D55: =C55 -> 7326.6287 | E55: =D55 -> 7326.6287 | F55: =E55 -> 7326.6287 | G55: =F55 -> 7326.6287 | H55: =G55 -> 7326.6287 | I55: =H55 -> 7326.6287 | J55: =I55 -> 7326.6287 | ... M55: =L55 -> 7326.6287 | N55: =SUM(B55:M55) -> 87919.545
A56: =A25 -> Overige bedrijfskosten | B56: ='FIN ANALYSE'!C88/12 -> 403.41667 | C56: =B56 -> 403.41667 | D56: =C56 -> 403.41667 | E56: =D56 -> 403.41667 | F56: =E56 -> 403.41667 | G56: =F56 -> 403.41667 | H56: =G56 -> 403.41667 | I56: =H56 -> 403.41667 | J56: =I56 -> 403.41667 | ... M56: =L56 -> 403.41667 | N56: =SUM(B56:M56) -> 4841
A57: =A26 -> Intresten | B57: ='FIN ANALYSE'!C89/12 -> 1001.3288 | C57: =B57 -> 1001.3288 | D57: =C57 -> 1001.3288 | E57: =D57 -> 1001.3288 | F57: =E57 -> 1001.3288 | G57: =F57 -> 1001.3288 | H57: =G57 -> 1001.3288 | I57: =H57 -> 1001.3288 | J57: =I57 -> 1001.3288 | ... M57: =L57 -> 1001.3288 | N57: =SUM(B57:M57) -> 12015.946
A58: =A27 -> Belastingen | N58: =SUM(B58:M58) -> 0
A60: TOTAAL UIT | B60: =SUM(B48:B59) -> 75357.571 | C60: =SUM(C48:C59) -> 74535.656 | D60: =SUM(D48:D59) -> 74535.656 | E60: =SUM(E48:E59) -> #REF! | F60: =SUM(F48:F59) -> 74535.656 | G60: =SUM(G48:G59) -> 74535.656 | H60: =SUM(H48:H59) -> #REF! | I60: =SUM(I48:I59) -> 74535.656 | ... N60: =SUM(N48:N59) -> #REF!
A61: SALDO PERIODE | B61: =B44-B60 -> 3551.5198 | C61: =C44-C60 -> 6781.699 | D61: =D44-D60 -> 6781.699 | E61: =E44-E60 -> #REF! | F61: =F44-F60 -> 6781.699 | G61: =G44-G60 -> 6781.699 | H61: =H44-H60 -> #REF! | I61: =I44-I60 -> 6781.699 | ... N61: =N44-N60 -> #REF!
A62: SALDO BANK JAAR 2 | B62: =M31+B61 -> #REF! | C62: =B62+C61 -> #REF! | D62: =C62+D61 -> #REF! | E62: =D62+E61 -> #REF! | F62: =E62+F61 -> #REF! | G62: =F62+G61 -> #REF! | H62: =G62+H61 -> #REF! | I62: =H62+I61 -> #REF! | J62: =I62+J61 -> #REF! | ... M62: =L62+M61 -> #REF!

Sheet DETAILS
A1: =ACTIVA!A1 -> VDO
A3: DETAIL ALGEMENE KOSTEN
B4: ='FIN ANALYSE'!B69 -> Jaar 1 | C4: =RESULTAAT!C4 -> Jaar 2 | D4: Jaar 3 | E4: jaarlijkse stijging | F4: % Vast
A6: Huisvesting | B6: =SUM(B8:B14) -> 58100 | C6: =SUM(C8:C14) -> 59011 | D6: =SUM(D8:D14) -> 62222.87
A8: Huur gebouw | B8: =1200*12 -> 14400 | C8: =B8*(1+$E$8) -> 14688 | D8: =C8*(1+$E$8) -> 14981.76 | E8: 0.02 | F8: 1
A9: Onderhoud gebouw | B9: =700*12 -> 8400 | C9: =B9*(1+$E$9) -> 8568 | D9: =C9*(1+$E$9) -> 8739.36 | E9: 0.02 | F9: 0.5
A10: Onderhoud installaties, machines | B10: 15000 | C10: =B10*(1+$E$10) -> 16500 | D10: =C10*(1+$E$10) -> 18150 | E10: 0.1 | F10: 0
A11: Aankoop materiaal, inrichting | B11: 5000 | C11: 2500 | D11: 2000 | E11: 0.02 | F11: 0.3
A12: Energie | B12: =1050*12 -> 12600 | C12: =B12*(1+$E$12) -> 13860 | D12: =C12*(1+$E$12) -> 15246 | E12: 0.1 | F12: 0.3
A13: Verzekeringen | B13: 1500 | C13: =B13*(1+$E$13) -> 1575 | D13: =C13*(1+$E$13) -> 1653.75 | E13: 0.05 | F13: 1
A14: Overige | B14: 1200 | C14: =B14*(1+$E$14) -> 1320 | D14: =C14*(1+$E$14) -> 1452 | E14: 0.1 | F14: 0.5
A16: Administratie | B16: =SUM(B18:B25) -> 27300 | C16: =SUM(C18:C25) -> 27960 | D16: =SUM(D18:D25) -> 30556
A18: Kantoorbenodigdheden | B18: 7000 | C18: =B18*(1+$E$18) -> 7700 | D18: =C18*(1+$E$18) -> 8470 | E18: 0.1 | F18: 0.75
A19: Website, software | B19: 3000 | C19: =B19*(1+$E$19) -> 3300 | D19: =C19*(1+$E$19) -> 3630 | E19: 0.1 | F19: 0.75
A20: Telefoon, mobiel | B20: 4300 | C20: =B20*(1+$E$20) -> 4730 | D20: =C20*(1+$E$20) -> 5203 | E20: 0.1 | F20: 0.45
A21: administratie, drukwerk, materiaal | B21: 1900 | C21: =B21*(1+$E$21) -> 2090 | D21: =C21*(1+$E$21) -> 2299 | E21: 0.1 | F21: 0.45
A22: Accounting | B22: 5500 | C22: =B22*(1+$E$22) -> 6050 | D22: =C22*(1+$E$22) -> 6655 | E22: 0.1 | F22: 0.95
A23: Erelonen | B23: 3700 | C23: 2000 | D23: 2000 | F23: 1
A24: Beheersbijdragen | B24: 700 | C24: =B24*(1+$E$24) -> 770 | D24: =C24*(1+$E$24) -> 847 | E24: 0.1 | F24: 0.55
A25: andere bijdragen, lidgelden | B25: 1200 | C25: =B25*(1+$E$25) -> 1320 | D25: =C25*(1+$E$25) -> 1452 | E25: 0.1 | F25: 0.75
A27: Verkoop | B27: =SUM(B29:B33) -> 15750 | C27: =SUM(C29:C33) -> 15780 | D27: =SUM(D29:D33) -> 16100
A29: Representatie | B29: 6000 | C29: =B29 -> 6000 | D29: =C29 -> 6000 | F29: 0.15
A30: Reizen en verplaatsingen | B30: 6550 | C30: 6680 | D30: 7000 | F30: 0.15
A31: Publiciteit, marketing, … | B31: 1700 | C31: 1800 | D31: 1850 | F31: 0.15
A32: Incentives
A33: Overige | B33: 1500 | C33: 1300 | D33: 1250 | F33: 0.15
A35: Rollend Materieel | B35: =SUM(B37:B41) -> 26700 | C35: =SUM(C37:C41) -> 27220 | D35: =SUM(D37:D41) -> 27730
A37: Verzekeringen | B37: 2400 | C37: 2550 | D37: 2700 | F37: 1
A38: Huurlast off balance | B38: =1350*12 -> 16200 | C38: =1350*12 -> 16200 | D38: =1350*12 -> 16200 | F38: 1
A39: Brandstof | B39: =550*12 -> 6600 | C39: 6900 | D39: 7200 | F39: 0.25
A40: Onderhoud | B40: 1500 | C40: 1570 | D40: 1630 | F40: 0.25
A41: Overige
A43: Consulting | B43: =SUM(B45:B46) -> 0 | C43: =SUM(C45:C46) -> 0 | D43: =SUM(D45:D46) -> 0
A45: Aankoop consulting
A46: Financiële en management
A48: Vergoeding Bedrijfsleiding | B48: =SUM(B50:B52) -> 50673.2 | C48: =SUM(C50:C52) -> 55740.52 | D48: =SUM(D50:D52) -> 57236.772
A50: Vergoeding Bedrijfsleider | B50: =3800*12 -> 45600 | C50: =B50*1.1 -> 50160 | D50: =C50*1.02 -> 51163.2 | F50: 0.5
A51: Verzekeringen | B51: 1500 | C51: 1650 | D51: 1750 | F51: 0.5
A52: Sociale Zekerheid bijdragen | B52: =893.3*4 -> 3573.2 | C52: =B52*1.1 -> 3930.52 | D52: =C52*1.1 -> 4323.572 | F52: 1
A54: TOTAAL | B54: =B48+B43+B35+B6+B16+B27 -> 178523.2 | C54: =C48+C43+C35+C6+C16+C27 -> 185711.52 | D54: =D48+D43+D35+D6+D16+D27 -> 193845.64
A58: PERSONEELSKOSTEN
B59: =B4 -> Jaar 1 | C59: =C4 -> Jaar 2 | D59: Jaar 3
A60: Aantal arbeiders | B60: 1 | C60: 1 | D60: 1
A61: Bruto loon per uur | B61: 18 | C61: =B61*1.02 -> 18.36 | D61: =C61*1.02 -> 18.7272 | E61: 0.02
A62: Prestatie per week | B62: 38 | C62: 38 | D62: 38
A63: Bruto maandlast | B63: =B61*B62*4 -> 2736 | C63: =C61*C62*4 -> 2790.72 | D63: =D61*D62*4 -> 2846.5344
A64: Totale incl RSZ patronaal | B64: =B63*1.3385 -> 3662.136 | C64: =C63*1.3385 -> 3735.3787 | D64: =D63*1.3385 -> 3810.0863
A65: Jaarbasis arbeider | B65: =B64*12 -> 43945.632 | C65: =C64*12 -> 44824.545 | D65: =D64*12 -> 45721.036
A68: Aantal bedienden | B68: 1 | C68: 1 | D68: 1
A69: Bruto maandlast | B69: 2600 | C69: =B69*(1+$E$69) -> 2652 | D69: =C69*(1+$E$69) -> 2705.04 | E69: 0.02
A70: Totale incl RSZ patronaal | B70: =B69*1.25 -> 3250 | C70: =C69*1.25 -> 3315 | D70: =D69*1.25 -> 3381.3
A71: Jaarbasis bedienden | B71: =B70*13 -> 42250 | C71: =C70*13 -> 43095 | D71: =D70*13 -> 43956.9
A74: Jaarbasis | B74: =B65+B71 -> 86195.632 | C74: =C65+C71 -> 87919.545 | D74: =D65+D71 -> 89677.936
A78: FINANCIERINGSWIJZE INVESTERINGEN
A79: MACHINES
A80: Aanschaffingswaarde | B80: ='INVEST TABEL'!C12 -> 300000
A81: Restwaarde | B81: =-B80*C81 -> 0 | C81: 0
A82: Saldo | B82: =B80+B81 -> 300000
A83: Voorschot 10 % | B83: =-B80*C83 -> -30000 | C83: 0.1
A84: Af te lossen kapitaal | B84: =SUM(B82:B83) -> 270000
A85: Duurtijd jaar | B85: 10
A86: Jaarlijkse Intrest | B86: 0.05
A87: Maandelijkse aflossing | B87: =Aflossingstabel!D14 -> 2863.7689
A90: Overige kosten | C90: Jaarlijkse stijging
A91: 31/12/N1 | B91: =OPGAVE!B12 -> 4700 | C91: 0.03
A92: 31/12/N2 | B92: =B91*(1+$C$91) -> 4841
A93: 31/12/N3 | B93: =B92*(1+$C$91) -> 4986.23

Sheet OPGAVE
A1: TOEPASSING BUDGETTERING
A3: Inbreng | B3: 90000 | C3: 30% van de lening
A4: Omzet | B4: 930000 | C4: jaarlijkse stijging 5 %
A5: Klanten | B5: 80% betaalbaar 30 dagen
A6: Aankopen goederen | B6: 65 % van de verkopen
A7: Leveranciers goederen | B7: betaalbaar 45 dagen
A8: Algemene onkosten | B8: zie "Details"
A9: Leveranciers Algemenen onkosten | B9: betaalbaar contant
A10: Personeel | B10: zie "Details"
A11: Personeelsschuld | B11: betaalbaar onmiddellijk
A12: Overige kosten | B12: 4700 | C12: jaarlijkse stijging 3 %
A13: Belastingen | B13: Tarief 25 %
A15: Machine | B15: 300000
A16: Afschrijving en duurtijd lening | B16: 10 jaar
A17: Lening | B17: 270000
A18: intrest | B18: tarief 5 %
A20: Inrichting kantoren | B20: 25000 | C20: eigen middelen
A21: Informatica materiaal | B21: 21000 | C21: eigen middelen
A23: Subsidies | B23: 15000 | C23: wordt ontvangen per 1 december

Sheet 70-40-44-55
C1: Omzet
B2: N1 | C2: 930000 | D2: jaarlijkse stijging 5 % | E2: 0.05
B3: N2 | C3: =C2*(1+$E$2) -> 976500
B4: N3 | C4: =C3*(1+$E$2) -> 1025325
B5: Klanten product A | C5: 0.8 | D5: 80 % van de omzet | E5: vervaldatum 30 dagen
B6: Klanten product B | C6: 0.2 | D6: 20 % van de omzet | E6: contante verkopen
C9: Klanten | G9: Bank (door KL) | K9: Omzet
C10: D | D10: C | G10: D | H10: C | K10: D | L10: C
C11: =C2*C5/12 -> 62000 | F11: Contant | G11: =C2*C6 -> 186000 | J11: 31/12/N1 | L11: =G13+C12 -> 930000
B12: 31/12/N1 | C12: =C11 -> 62000 | F12: KL | G12: =C2*C5*11/12 -> 682000 | J12: 31/12/N2 | L12: =C16+G15+G16 -> 976500
D13: =C12 -> 62000 | F13: 31/12/N1 | G13: =SUM(G11:G12) -> 868000 | J13: 31/12/N3 | L13: =C18+G20+G19 -> 1025325
C14: =C3*C5/12 -> 65100 | F14: KL eind Bkj | G14: =C12 -> 62000 | L14: =SUM(L11:L13) -> 2931825 | M14: Totaal
C15: =SUM(C12:C14) -> 127100 | D15: =SUM(D12:D14) -> 62000 | F15: Cash | G15: =C3*C6 -> 195300 | L15: =G21+C20 -> 2931825 | M15: Control
B16: 31/12/N2 | C16: =C15-D15 -> 65100 | F16: KL | G16: =C3*C5*11/12 -> 716100
D17: =C16 -> 65100 | F17: 31/12/N2 | G17: =SUM(G13:G16) -> 1841400
C18: =C4*C5/12 -> 68355 | F18: KL eind Bkj | G18: =D17 -> 65100
C19: =SUM(C16:C18) -> 133455 | D19: =SUM(D16:D18) -> 65100 | F19: Cash | G19: =C4*C6 -> 205065
B20: 31/12/N3 | C20: =C19-D19 -> 68355 | F20: KL | G20: =C4*C5*11/12 -> 751905
F21: 31/12/N3 | G21: =SUM(G17:G20) -> 2863470
B24: Leveranciers | C24: 0.6 | D24: Omzet | L24: Aankopen | M24: Control
C25: Leveranciers | G25: Bank (door L) | K25: 31/12/N1 | L25: =C2*$C$24 -> 558000 | M25: =D28+H28 -> 558000
C26: D | D26: C | G26: D | H26: C | K26: 31/12/N2 | L26: =C3*$C$24 -> 585900 | M26: =H30+D32 -> 585900
D27: =C2*C24*(1.5/12) -> 69750 | H27: =C2*C24*10.5/12 -> 488250 | K27: 31/12/N3 | L27: =C4*$C$24 -> 615195 | M27: =H33+D34 -> 615195
B28: 31/12/N1 | D28: =SUM(D27) -> 69750 | F28: 31/12/N1 | H28: =SUM(H27) -> 488250 | L28: =SUM(L25:L27) -> 1759095 | M28: =H34+D36 -> 1759095
C29: =D28 -> 69750 | F29: L eind Bkj | H29: =C29 -> 69750
D30: =C3*C24*1.5/12 -> 73237.5 | F30: L | H30: =C3*C24*10.5/12 -> 512662.5
C31: =SUM(C28:C30) -> 69750 | D31: =SUM(D28:D30) -> 142987.5 | F31: 31/12/N2 | H31: =SUM(H28:H30) -> 1070662.5
B32: 31/12/N2 | D32: =D31-C31 -> 73237.5 | F32: L eind Bkj | H32: =D32 -> 73237.5
C33: =D32 -> 73237.5 | F33: L | H33: =C4*C24*10.5/12 -> 538295.62
D34: =C4*C24*1.5/12 -> 76899.375 | F34: 31/12/N3 | H34: =SUM(H31:H33) -> 1682195.6
C35: =SUM(C32:C34) -> 73237.5 | D35: =SUM(D32:D34) -> 150136.88
B36: 31/12/N3 | D36: =D35-C35 -> 76899.375
D40: 55
C41: Bank
C42: D | D42: C
B43: Inbreng | C43: =OPGAVE!B3 -> 90000
B44: KL | C44: =G13 -> 868000
B45: Subsidies | C45: 15000
B46: VA voorschot | D46: =OPGAVE!B15*DETAILS!C83 -> 30000
B47: VA direct betaald | D47: =OPGAVE!B20+OPGAVE!B21 -> 46000
B48: L | D48: =H28 -> 488250
B49: Algemene kosten | D49: =DETAILS!B54 -> 178523.2
B50: Personeelkosten | D50: =DETAILS!B74 -> 86195.632
B51: Overige kosten | D51: =DETAILS!B91 -> 4700
B52: Lening | D52: =Aflossingstabel!J13 -> 31501.458
C53: =SUM(C43:C52) -> 973000 | D53: =SUM(D43:D52) -> 865170.29
B54: 31/12/N1 | C54: =C53-D53 -> 107829.71
B57: KL | C57: =SUM(G14:G16) -> 973400
B58: L | D58: =SUM(H29:H30) -> 582412.5
B59: Algemene kosten | D59: =DETAILS!C54 -> 185711.52
B60: Personeelkosten | D60: =DETAILS!C74 -> 87919.545
B61: Overige kosten | D61: =DETAILS!B92 -> 4841
B62: Lening | D62: =Aflossingstabel!J14 -> 34365.227
B63: Venn. Belasting | D63: =RESULTAAT!B52 -> 15649.925
C64: =SUM(C54:C63) -> 1081229.7 | D64: =SUM(D54:D63) -> 910899.72
B65: 31/12/N2 | C65: =C64-D64 -> 170329.99
B66: KL | C66: =SUM(G18:G20) -> 1022070
B67: L | D67: =SUM(H32:H33) -> 611533.12
B68: Algemene kosten | D68: =DETAILS!D54 -> 193845.64
B69: Personeelkosten | D69: =DETAILS!D74 -> 89677.936
B70: Overige kosten | D70: =DETAILS!B93 -> 4986.23
B71: Lening | D71: =Aflossingstabel!J15 -> 34365.227
B72: Venn. Belasting | D72: =RESULTAAT!C52 -> 14550.527
B73: 31/12/N3 | C73: =SUM(C65:C71) -> 1192400 | D73: =SUM(D65:D72) -> 948958.69
C74: =C73-D73 -> 243441.31

Sheet Aflossingstabel
A1: Parameters
I2: Totalen (over looptijd)
A3: Leenbedrag | B3: 270000 | I3: Totale betalingen | J3: =SUM($D$14:$D$133) -> 343652.27
A4: Jaarlijkse rente | B4: 0.05 | D4: Aflossingberekening | E4: Berekening | F4: =PMT(0.05/12, 120,- 270000) -> 2863.7689 | I4: Totale interest | J4: =SUM($E$14:$E$133) -> 73652.269
A5: Looptijd (jaren) | B5: 5 | E5: Excel | I5: Totale kapitaalaflossing | J5: =SUM($F$14:$F$133) -> 270000
A6: Startdatum lening | B6: 45658
A7: Eerste betaaldatum | B7: 45689
A8: Aantal maanden | B8: =B5*12 -> 60
A9: Maandrente | B9: =B4/12 -> 0.0041666667
A10: Maandelijkse betaling (annuïteit) | B10: =-PMT(B9,B8,B3) -> 5095.2331
A12: Periode | B12: Datum | C12: Begin saldo | D12: Betaling | E12: Intrest | F12: Kapitaal | G12: Eind saldo | I12: Jaarlijkse aflossing | J12: Betaling | K12: Intrest | L12: Kapitaal
A13: =IF(ROW()-13>$B$8,"",ROW()-13) -> 0 | B13: =IF($A13="","",EDATE($B$7,$A13-1)) -> 45658 | C13: 270000 | I13: Jaar 1 | J13: =SUM(D14:D24) -> 31501.458 | K13: =SUM(E14:E24)+E25*(30/31) -> 12981.469 | L13: =SUM(F14:F24) -> 19529.949
A14: =IF(ROW()-13>$B$8,"",ROW()-13) -> 1 | B14: =IF($A14="","",EDATE($B$7,$A14-1)) -> 45689 | C14: =IF($A13="","",$B$3) -> 270000 | D14: =PMT(0.05/12, 120,- 270000) -> 2863.7689 | E14: =C14*$B$9 -> 1125 | F14: =IF($A13="","",$D14-$E14) -> 1738.7689 | G14: =IF($A13="","",MAX(0,$C14-$F14)) -> 268261.23 | I14: Jaar 2 | J14: =SUM(D25:D36) -> 34365.227 | K14: =(E25/31)+SUM(E26:E36)+(E37*30/31) -> 11925.827 | L14: =SUM(F25:F36) -> 22349.281
A15: =IF(ROW()-13>$B$8,"",ROW()-13) -> 2 | B15: =IF($A15="","",EDATE($B$7,$A15-1)) -> 45717 | C15: =IF($A14="","",$G14) -> 268261.23 | D15: =PMT(0.05/12, 120,- 270000) -> 2863.7689 | E15: =IF($A14="","",$C15*$B$9) -> 1117.7551 | F15: =IF($A14="","",$D15-$E15) -> 1746.0138 | G15: =IF($A14="","",MAX(0,$C15-$F15)) -> 266515.22 | I15: Jaar 3 | J15: =SUM(D37:D48) -> 34365.227 | K15: =E37/31+SUM(E38:E48)+E49*(30/31) -> 10777.785 | L15: =SUM(F37:F48) -> 23492.713
A16: =IF(ROW()-13>$B$8,"",ROW()-13) -> 3 | B16: =IF($A16="","",EDATE($B$7,$A16-1)) -> 45748 | C16: =IF($A15="","",$G15) -> 266515.22 | D16: =PMT(0.05/12, 120,- 270000) -> 2863.7689 | E16: =IF($A15="","",$C16*$B$9) -> 1110.4801 | F16: =IF($A15="","",$D16-$E16) -> 1753.2888 | G16: =IF($A15="","",MAX(0,$C16-$F16)) -> 264761.93 | I16: Jaar 4 | J16: =SUM(D49:D60) -> 34365.227 | K16: =E49/31 +SUM(E50:E60)+E61*(30/31) -> 9571.0069 | L16: =SUM(F49:F60) -> 24694.645
A17: =IF(ROW()-13>$B$8,"",ROW()-13) -> 4 | B17: =IF($A17="","",EDATE($B$7,$A17-1)) -> 45778 | C17: =IF($A16="","",$G16) -> 264761.93 | D17: =PMT(0.05/12, 120,- 270000) -> 2863.7689 | E17: =IF($A16="","",$C17*$B$9) -> 1103.1747 | F17: =IF($A16="","",$D17-$E17) -> 1760.5942 | G17: =IF($A16="","",MAX(0,$C17-$F17)) -> 263001.33 | I17: Jaar 5 | J17: =SUM(D61:D72) -> 34365.227 | K17: =E61/31+SUM(E62:E72)+E73*(30/31) -> 8302.4875 | L17: =SUM(F61:F72) -> 25958.07
A18: =IF(ROW()-13>$B$8,"",ROW()-13) -> 5 | B18: =IF($A18="","",EDATE($B$7,$A18-1)) -> 45809 | C18: =IF($A17="","",$G17) -> 263001.33 | D18: =PMT(0.05/12, 120,- 270000) -> 2863.7689 | E18: =IF($A17="","",$C18*$B$9) -> 1095.8389 | F18: =IF($A17="","",$D18-$E18) -> 1767.93 | G18: =IF($A17="","",MAX(0,$C18-$F18)) -> 261233.4 | I18: Jaar 6 | J18: =D73 -> 2863.7689 | K18: =E73/31 -> 20.695611 | L18: =F73 -> 2222.205
A19: =IF(ROW()-13>$B$8,"",ROW()-13) -> 6 | B19: =IF($A19="","",EDATE($B$7,$A19-1)) -> 45839 | C19: =IF($A18="","",$G18) -> 261233.4 | D19: =PMT(0.05/12, 120,- 270000) -> 2863.7689 | E19: =IF($A18="","",$C19*$B$9) -> 1088.4725 | F19: =IF($A18="","",$D19-$E19) -> 1775.2964 | G19: =IF($A18="","",MAX(0,$C19-$F19)) -> 259458.11 | J19: =SUM(J13:J18) -> 171826.13 | K19: =SUM(K13:K18) -> 53579.272 | L19: =SUM(L13:L18) -> 118246.86
A20: =IF(ROW()-13>$B$8,"",ROW()-13) -> 7 | B20: =IF($A20="","",EDATE($B$7,$A20-1)) -> 45870 | C20: =IF($A19="","",$G19) -> 259458.11 | D20: =PMT(0.05/12, 120,- 270000) -> 2863.7689 | E20: =IF($A19="","",$C20*$B$9) -> 1081.0754 | F20: =IF($A19="","",$D20-$E20) -> 1782.6935 | G20: =IF($A19="","",MAX(0,$C20-$F20)) -> 257675.41 | I20: Lening | J20: =J19-K19 -> 118246.86
A21: =IF(ROW()-13>$B$8,"",ROW()-13) -> 8 | B21: =IF($A21="","",EDATE($B$7,$A21-1)) -> 45901 | C21: =IF($A20="","",$G20) -> 257675.41 | D21: =PMT(0.05/12, 120,- 270000) -> 2863.7689 | E21: =IF($A20="","",$C21*$B$9) -> 1073.6476 | F21: =IF($A20="","",$D21-$E21) -> 1790.1214 | G21: =IF($A20="","",MAX(0,$C21-$F21)) -> 255885.29
A22: =IF(ROW()-13>$B$8,"",ROW()-13) -> 9 | B22: =IF($A22="","",EDATE($B$7,$A22-1)) -> 45931 | C22: =IF($A21="","",$G21) -> 255885.29 | D22: =PMT(0.05/12, 120,- 270000) -> 2863.7689 | E22: =IF($A21="","",$C22*$B$9) -> 1066.1887 | F22: =IF($A21="","",$D22-$E22) -> 1797.5802 | G22: =IF($A21="","",MAX(0,$C22-$F22)) -> 254087.71
A23: =IF(ROW()-13>$B$8,"",ROW()-13) -> 10 | B23: =IF($A23="","",EDATE($B$7,$A23-1)) -> 45962 | C23: =IF($A22="","",$G22) -> 254087.71 | D23: =PMT(0.05/12, 120,- 270000) -> 2863.7689 | E23: =IF($A22="","",$C23*$B$9) -> 1058.6988 | F23: =IF($A22="","",$D23-$E23) -> 1805.0701 | G23: =IF($A22="","",MAX(0,$C23-$F23)) -> 252282.64 | J23: 173000 | K23: 423000
A24: =IF(ROW()-13>$B$8,"",ROW()-13) -> 11 | B24: =IF($A24="","",EDATE($B$7,$A24-1)) -> 45992 | C24: =IF($A23="","",$G23) -> 252282.64 | D24: =PMT(0.05/12, 120,- 270000) -> 2863.7689 | E24: =IF($A23="","",$C24*$B$9) -> 1051.1777 | F24: =IF($A23="","",$D24-$E24) -> 1812.5912 | G24: =IF($A23="","",MAX(0,$C24-$F24)) -> 250470.05 | J24: 270000
A25: =IF(ROW()-13>$B$8,"",ROW()-13) -> 12 | B25: =IF($A25="","",EDATE($B$7,$A25-1)) -> 46023 | C25: =IF($A24="","",$G24) -> 250470.05 | D25: =PMT(0.05/12, 120,- 270000) -> 2863.7689 | E25: =IF($A24="","",$C25*$B$9) -> 1043.6252 | F25: =IF($A24="","",$D25-$E25) -> 1820.1437 | G25: =IF($A24="","",MAX(0,$C25-$F25)) -> 248649.91 | I25: Jaar 1 | J25: =J24-L13-L14 -> 228120.77 | K25: =L14 -> 22349.281
A26: =IF(ROW()-13>$B$8,"",ROW()-13) -> 13 | B26: =IF($A26="","",EDATE($B$7,$A26-1)) -> 46054 | C26: =IF($A25="","",$G25) -> 248649.91 | D26: =PMT(0.05/12, 120,- 270000) -> 2863.7689 | E26: =IF($A25="","",$C26*$B$9) -> 1036.0413 | F26: =IF($A25="","",$D26-$E26) -> 1827.7276 | G26: =IF($A25="","",MAX(0,$C26-$F26)) -> 246822.18 | I26: Jaar 2 | J26: =J25-K26 -> 204628.06 | K26: =L15 -> 23492.713
A27: =IF(ROW()-13>$B$8,"",ROW()-13) -> 14 | B27: =IF($A27="","",EDATE($B$7,$A27-1)) -> 46082 | C27: =IF($A26="","",$G26) -> 246822.18 | D27: =PMT(0.05/12, 120,- 270000) -> 2863.7689 | E27: =IF($A26="","",$C27*$B$9) -> 1028.4258 | F27: =IF($A26="","",$D27-$E27) -> 1835.3432 | G27: =IF($A26="","",MAX(0,$C27-$F27)) -> 244986.84 | I27: Jaar 3 | J27: =J26-K27 -> 179933.41 | K27: =L16 -> 24694.645
A28: =IF(ROW()-13>$B$8,"",ROW()-13) -> 15 | B28: =IF($A28="","",EDATE($B$7,$A28-1)) -> 46113 | C28: =IF($A27="","",$G27) -> 244986.84 | D28: =PMT(0.05/12, 120,- 270000) -> 2863.7689 | E28: =IF($A27="","",$C28*$B$9) -> 1020.7785 | F28: =IF($A27="","",$D28-$E28) -> 1842.9904 | G28: =IF($A27="","",MAX(0,$C28-$F28)) -> 243143.85 | I28: Jaar 4 | J28: =J27-K28 -> 153975.34 | K28: =L17 -> 25958.07
A29: =IF(ROW()-13>$B$8,"",ROW()-13) -> 16 | B29: =IF($A29="","",EDATE($B$7,$A29-1)) -> 46143 | C29: =IF($A28="","",$G28) -> 243143.85 | D29: =PMT(0.05/12, 120,- 270000) -> 2863.7689 | E29: =IF($A28="","",$C29*$B$9) -> 1013.0994 | F29: =IF($A28="","",$D29-$E29) -> 1850.6696 | G29: =IF($A28="","",MAX(0,$C29-$F29)) -> 241293.18 | I29: Jaar 5 | K29: =L18 -> 2222.205
A30: =IF(ROW()-13>$B$8,"",ROW()-13) -> 17 | B30: =IF($A30="","",EDATE($B$7,$A30-1)) -> 46174 | C30: =IF($A29="","",$G29) -> 241293.18 | D30: =PMT(0.05/12, 120,- 270000) -> 2863.7689 | E30: =IF($A29="","",$C30*$B$9) -> 1005.3882 | F30: =IF($A29="","",$D30-$E30) -> 1858.3807 | G30: =IF($A29="","",MAX(0,$C30-$F30)) -> 239434.8
A31: =IF(ROW()-13>$B$8,"",ROW()-13) -> 18 | B31: =IF($A31="","",EDATE($B$7,$A31-1)) -> 46204 | C31: =IF($A30="","",$G30) -> 239434.8 | D31: =PMT(0.05/12, 120,- 270000) -> 2863.7689 | E31: =IF($A30="","",$C31*$B$9) -> 997.64498 | F31: =IF($A30="","",$D31-$E31) -> 1866.1239 | G31: =IF($A30="","",MAX(0,$C31-$F31)) -> 237568.67
A32: =IF(ROW()-13>$B$8,"",ROW()-13) -> 19 | B32: =IF($A32="","",EDATE($B$7,$A32-1)) -> 46235 | C32: =IF($A31="","",$G31) -> 237568.67 | D32: =PMT(0.05/12, 120,- 270000) -> 2863.7689 | E32: =IF($A31="","",$C32*$B$9) -> 989.86947 | F32: =IF($A31="","",$D32-$E32) -> 1873.8994 | G32: =IF($A31="","",MAX(0,$C32-$F32)) -> 235694.77
A33: =IF(ROW()-13>$B$8,"",ROW()-13) -> 20 | B33: =IF($A33="","",EDATE($B$7,$A33-1)) -> 46266 | C33: =IF($A32="","",$G32) -> 235694.77 | D33: =PMT(0.05/12, 120,- 270000) -> 2863.7689 | E33: =IF($A32="","",$C33*$B$9) -> 982.06155 | F33: =IF($A32="","",$D33-$E33) -> 1881.7074 | G33: =IF($A32="","",MAX(0,$C33-$F33)) -> 233813.07
A34: =IF(ROW()-13>$B$8,"",ROW()-13) -> 21 | B34: =IF($A34="","",EDATE($B$7,$A34-1)) -> 46296 | C34: =IF($A33="","",$G33) -> 233813.07 | D34: =PMT(0.05/12, 120,- 270000) -> 2863.7689 | E34: =IF($A33="","",$C34*$B$9) -> 974.22111 | F34: =IF($A33="","",$D34-$E34) -> 1889.5478 | G34: =IF($A33="","",MAX(0,$C34-$F34)) -> 231923.52
A35: =IF(ROW()-13>$B$8,"",ROW()-13) -> 22 | B35: =IF($A35="","",EDATE($B$7,$A35-1)) -> 46327 | C35: =IF($A34="","",$G34) -> 231923.52 | D35: =PMT(0.05/12, 120,- 270000) -> 2863.7689 | E35: =IF($A34="","",$C35*$B$9) -> 966.34799 | F35: =IF($A34="","",$D35-$E35) -> 1897.4209 | G35: =IF($A34="","",MAX(0,$C35-$F35)) -> 230026.1
A36: =IF(ROW()-13>$B$8,"",ROW()-13) -> 23 | B36: =IF($A36="","",EDATE($B$7,$A36-1)) -> 46357 | C36: =IF($A35="","",$G35) -> 230026.1 | D36: =PMT(0.05/12, 120,- 270000) -> 2863.7689 | E36: =IF($A35="","",$C36*$B$9) -> 958.44207 | F36: =IF($A35="","",$D36-$E36) -> 1905.3268 | G36: =IF($A35="","",MAX(0,$C36-$F36)) -> 228120.77
A37: =IF(ROW()-13>$B$8,"",ROW()-13) -> 24 | B37: =IF($A37="","",EDATE($B$7,$A37-1)) -> 46388 | C37: =IF($A36="","",$G36) -> 228120.77 | D37: =PMT(0.05/12, 120,- 270000) -> 2863.7689 | E37: =IF($A36="","",$C37*$B$9) -> 950.50321 | F37: =IF($A36="","",$D37-$E37) -> 1913.2657 | G37: =IF($A36="","",MAX(0,$C37-$F37)) -> 226207.5
A38: =IF(ROW()-13>$B$8,"",ROW()-13) -> 25 | B38: =IF($A38="","",EDATE($B$7,$A38-1)) -> 46419 | C38: =IF($A37="","",$G37) -> 226207.5 | D38: =PMT(0.05/12, 120,- 270000) -> 2863.7689 | E38: =IF($A37="","",$C38*$B$9) -> 942.53127 | F38: =IF($A37="","",$D38-$E38) -> 1921.2376 | G38: =IF($A37="","",MAX(0,$C38-$F38)) -> 224286.27
A39: =IF(ROW()-13>$B$8,"",ROW()-13) -> 26 | B39: =IF($A39="","",EDATE($B$7,$A39-1)) -> 46447 | C39: =IF($A38="","",$G38) -> 224286.27 | D39: =PMT(0.05/12, 120,- 270000) -> 2863.7689 | E39: =IF($A38="","",$C39*$B$9) -> 934.52611 | F39: =IF($A38="","",$D39-$E39) -> 1929.2428 | G39: =IF($A38="","",MAX(0,$C39-$F39)) -> 222357.02
A40: =IF(ROW()-13>$B$8,"",ROW()-13) -> 27 | B40: =IF($A40="","",EDATE($B$7,$A40-1)) -> 46478 | C40: =IF($A39="","",$G39) -> 222357.02 | D40: =PMT(0.05/12, 120,- 270000) -> 2863.7689 | E40: =IF($A39="","",$C40*$B$9) -> 926.4876 | F40: =IF($A39="","",$D40-$E40) -> 1937.2813 | G40: =IF($A39="","",MAX(0,$C40-$F40)) -> 220419.74
A41: =IF(ROW()-13>$B$8,"",ROW()-13) -> 28 | B41: =IF($A41="","",EDATE($B$7,$A41-1)) -> 46508 | C41: =IF($A40="","",$G40) -> 220419.74 | D41: =PMT(0.05/12, 120,- 270000) -> 2863.7689 | E41: =IF($A40="","",$C41*$B$9) -> 918.41559 | F41: =IF($A40="","",$D41-$E41) -> 1945.3533 | G41: =IF($A40="","",MAX(0,$C41-$F41)) -> 218474.39
A42: =IF(ROW()-13>$B$8,"",ROW()-13) -> 29 | B42: =IF($A42="","",EDATE($B$7,$A42-1)) -> 46539 | C42: =IF($A41="","",$G41) -> 218474.39 | D42: =PMT(0.05/12, 120,- 270000) -> 2863.7689 | E42: =IF($A41="","",$C42*$B$9) -> 910.30996 | F42: =IF($A41="","",$D42-$E42) -> 1953.459 | G42: =IF($A41="","",MAX(0,$C42-$F42)) -> 216520.93
A43: =IF(ROW()-13>$B$8,"",ROW()-13) -> 30 | B43: =IF($A43="","",EDATE($B$7,$A43-1)) -> 46569 | C43: =IF($A42="","",$G42) -> 216520.93 | D43: =PMT(0.05/12, 120,- 270000) -> 2863.7689 | E43: =IF($A42="","",$C43*$B$9) -> 902.17054 | F43: =IF($A42="","",$D43-$E43) -> 1961.5984 | G43: =IF($A42="","",MAX(0,$C43-$F43)) -> 214559.33 | J43: 492
A44: =IF(ROW()-13>$B$8,"",ROW()-13) -> 31 | B44: =IF($A44="","",EDATE($B$7,$A44-1)) -> 46600 | C44: =IF($A43="","",$G43) -> 214559.33 | D44: =PMT(0.05/12, 120,- 270000) -> 2863.7689 | E44: =IF($A43="","",$C44*$B$9) -> 893.99722 | F44: =IF($A43="","",$D44-$E44) -> 1969.7717 | G44: =IF($A43="","",MAX(0,$C44-$F44)) -> 212589.56 | I44: Jaar 1 | J44: =E25*30/31 -> 1009.9599
A45: =IF(ROW()-13>$B$8,"",ROW()-13) -> 32 | B45: =IF($A45="","",EDATE($B$7,$A45-1)) -> 46631 | C45: =IF($A44="","",$G44) -> 212589.56 | D45: =PMT(0.05/12, 120,- 270000) -> 2863.7689 | E45: =IF($A44="","",$C45*$B$9) -> 885.78983 | F45: =IF($A44="","",$D45-$E45) -> 1977.9791 | G45: =IF($A44="","",MAX(0,$C45-$F45)) -> 210611.58 | I45: Jaar 2 | J45: =E37*30/31 -> 919.84181
A46: =IF(ROW()-13>$B$8,"",ROW()-13) -> 33 | B46: =IF($A46="","",EDATE($B$7,$A46-1)) -> 46661 | C46: =IF($A45="","",$G45) -> 210611.58 | D46: =PMT(0.05/12, 120,- 270000) -> 2863.7689 | E46: =IF($A45="","",$C46*$B$9) -> 877.54826 | F46: =IF($A45="","",$D46-$E46) -> 1986.2207 | G46: =IF($A45="","",MAX(0,$C46-$F46)) -> 208625.36 | I46: Jaar 3 | J46: =E49*30/31 -> 825.11313
A47: =IF(ROW()-13>$B$8,"",ROW()-13) -> 34 | B47: =IF($A47="","",EDATE($B$7,$A47-1)) -> 46692 | C47: =IF($A46="","",$G46) -> 208625.36 | D47: =PMT(0.05/12, 120,- 270000) -> 2863.7689 | E47: =IF($A46="","",$C47*$B$9) -> 869.27234 | F47: =IF($A46="","",$D47-$E47) -> 1994.4966 | G47: =IF($A46="","",MAX(0,$C47-$F47)) -> 206630.86 | I47: Jaar 4 | J47: =E61*30/31 -> 725.53795
A48: =IF(ROW()-13>$B$8,"",ROW()-13) -> 35 | B48: =IF($A48="","",EDATE($B$7,$A48-1)) -> 46722 | C48: =IF($A47="","",$G47) -> 206630.86 | D48: =PMT(0.05/12, 120,- 270000) -> 2863.7689 | E48: =IF($A47="","",$C48*$B$9) -> 860.96193 | F48: =IF($A47="","",$D48-$E48) -> 2002.807 | G48: =IF($A47="","",MAX(0,$C48-$F48)) -> 204628.06 | I48: Jaar 5 | J48: =E73*30/31 -> 620.86832
A49: =IF(ROW()-13>$B$8,"",ROW()-13) -> 36 | B49: =IF($A49="","",EDATE($B$7,$A49-1)) -> 46753 | C49: =IF($A48="","",$G48) -> 204628.06 | D49: =PMT(0.05/12, 120,- 270000) -> 2863.7689 | E49: =IF($A48="","",$C49*$B$9) -> 852.6169 | F49: =IF($A48="","",$D49-$E49) -> 2011.152 | G49: =IF($A48="","",MAX(0,$C49-$F49)) -> 202616.9
A50: =IF(ROW()-13>$B$8,"",ROW()-13) -> 37 | B50: =IF($A50="","",EDATE($B$7,$A50-1)) -> 46784 | C50: =IF($A49="","",$G49) -> 202616.9 | D50: =PMT(0.05/12, 120,- 270000) -> 2863.7689 | E50: =IF($A49="","",$C50*$B$9) -> 844.2371 | F50: =IF($A49="","",$D50-$E50) -> 2019.5318 | G50: =IF($A49="","",MAX(0,$C50-$F50)) -> 200597.37
A51: =IF(ROW()-13>$B$8,"",ROW()-13) -> 38 | B51: =IF($A51="","",EDATE($B$7,$A51-1)) -> 46813 | C51: =IF($A50="","",$G50) -> 200597.37 | D51: =PMT(0.05/12, 120,- 270000) -> 2863.7689 | E51: =IF($A50="","",$C51*$B$9) -> 835.82239 | F51: =IF($A50="","",$D51-$E51) -> 2027.9465 | G51: =IF($A50="","",MAX(0,$C51-$F51)) -> 198569.43
A52: =IF(ROW()-13>$B$8,"",ROW()-13) -> 39 | B52: =IF($A52="","",EDATE($B$7,$A52-1)) -> 46844 | C52: =IF($A51="","",$G51) -> 198569.43 | D52: =PMT(0.05/12, 120,- 270000) -> 2863.7689 | E52: =IF($A51="","",$C52*$B$9) -> 827.37261 | F52: =IF($A51="","",$D52-$E52) -> 2036.3963 | G52: =IF($A51="","",MAX(0,$C52-$F52)) -> 196533.03
A53: =IF(ROW()-13>$B$8,"",ROW()-13) -> 40 | B53: =IF($A53="","",EDATE($B$7,$A53-1)) -> 46874 | C53: =IF($A52="","",$G52) -> 196533.03 | D53: =PMT(0.05/12, 120,- 270000) -> 2863.7689 | E53: =IF($A52="","",$C53*$B$9) -> 818.88763 | F53: =IF($A52="","",$D53-$E53) -> 2044.8813 | G53: =IF($A52="","",MAX(0,$C53-$F53)) -> 194488.15
A54: =IF(ROW()-13>$B$8,"",ROW()-13) -> 41 | B54: =IF($A54="","",EDATE($B$7,$A54-1)) -> 46905 | C54: =IF($A53="","",$G53) -> 194488.15 | D54: =PMT(0.05/12, 120,- 270000) -> 2863.7689 | E54: =IF($A53="","",$C54*$B$9) -> 810.36729 | F54: =IF($A53="","",$D54-$E54) -> 2053.4016 | G54: =IF($A53="","",MAX(0,$C54-$F54)) -> 192434.75
A55: =IF(ROW()-13>$B$8,"",ROW()-13) -> 42 | B55: =IF($A55="","",EDATE($B$7,$A55-1)) -> 46935 | C55: =IF($A54="","",$G54) -> 192434.75 | D55: =PMT(0.05/12, 120,- 270000) -> 2863.7689 | E55: =IF($A54="","",$C55*$B$9) -> 801.81145 | F55: =IF($A54="","",$D55-$E55) -> 2061.9575 | G55: =IF($A54="","",MAX(0,$C55-$F55)) -> 190372.79
A56: =IF(ROW()-13>$B$8,"",ROW()-13) -> 43 | B56: =IF($A56="","",EDATE($B$7,$A56-1)) -> 46966 | C56: =IF($A55="","",$G55) -> 190372.79 | D56: =PMT(0.05/12, 120,- 270000) -> 2863.7689 | E56: =IF($A55="","",$C56*$B$9) -> 793.21996 | F56: =IF($A55="","",$D56-$E56) -> 2070.549 | G56: =IF($A55="","",MAX(0,$C56-$F56)) -> 188302.24
A57: =IF(ROW()-13>$B$8,"",ROW()-13) -> 44 | B57: =IF($A57="","",EDATE($B$7,$A57-1)) -> 46997 | C57: =IF($A56="","",$G56) -> 188302.24 | D57: =PMT(0.05/12, 120,- 270000) -> 2863.7689 | E57: =IF($A56="","",$C57*$B$9) -> 784.59267 | F57: =IF($A56="","",$D57-$E57) -> 2079.1762 | G57: =IF($A56="","",MAX(0,$C57-$F57)) -> 186223.06
A58: =IF(ROW()-13>$B$8,"",ROW()-13) -> 45 | B58: =IF($A58="","",EDATE($B$7,$A58-1)) -> 47027 | C58: =IF($A57="","",$G57) -> 186223.06 | D58: =PMT(0.05/12, 120,- 270000) -> 2863.7689 | E58: =IF($A57="","",$C58*$B$9) -> 775.92944 | F58: =IF($A57="","",$D58-$E58) -> 2087.8395 | G58: =IF($A57="","",MAX(0,$C58-$F58)) -> 184135.23
A59: =IF(ROW()-13>$B$8,"",ROW()-13) -> 46 | B59: =IF($A59="","",EDATE($B$7,$A59-1)) -> 47058 | C59: =IF($A58="","",$G58) -> 184135.23 | D59: =PMT(0.05/12, 120,- 270000) -> 2863.7689 | E59: =IF($A58="","",$C59*$B$9) -> 767.23011 | F59: =IF($A58="","",$D59-$E59) -> 2096.5388 | G59: =IF($A58="","",MAX(0,$C59-$F59)) -> 182038.69
A60: =IF(ROW()-13>$B$8,"",ROW()-13) -> 47 | B60: =IF($A60="","",EDATE($B$7,$A60-1)) -> 47088 | C60: =IF($A59="","",$G59) -> 182038.69 | D60: =PMT(0.05/12, 120,- 270000) -> 2863.7689 | E60: =IF($A59="","",$C60*$B$9) -> 758.49453 | F60: =IF($A59="","",$D60-$E60) -> 2105.2744 | G60: =IF($A59="","",MAX(0,$C60-$F60)) -> 179933.41
... A73: =IF(ROW()-13>$B$8,"",ROW()-13) -> 60 | B73: =IF($A73="","",EDATE($B$7,$A73-1)) -> 47484 | C73: =IF($A72="","",$G72) -> 153975.34 | D73: =PMT(0.05/12, 120,- 270000) -> 2863.7689 | E73: =IF($A72="","",$C73*$B$9) -> 641.56393 | F73: =IF($A72="","",$D73-$E73) -> 2222.205 | G73: =IF($A72="","",MAX(0,$C73-$F73)) -> 151753.14
A74: 61 | B74: =IF($A74="","",EDATE($B$7,$A74-1)) -> 47515 | C74: =G73 -> 151753.14 | D74: =PMT(0.05/12, 120,- 270000) -> 2863.7689 | E74: =C74*$B$9 -> 632.30474 | F74: =D74-E74 -> 2231.4642 | G74: =C74-F74 -> 149521.67
A75: 62 | B75: =IF($A75="","",EDATE($B$7,$A75-1)) -> 47543 | C75: =IF($A74="","",$G74) -> 149521.67 | D75: =PMT(0.05/12, 120,- 270000) -> 2863.7689 | E75: =C75*$B$9 -> 623.00697 | F75: =D75-E75 -> 2240.7619 | G75: =C75-F75 -> 147280.91
A76: 63 | B76: =IF($A76="","",EDATE($B$7,$A76-1)) -> 47574 | C76: =IF($A75="","",$G75) -> 147280.91 | D76: =PMT(0.05/12, 120,- 270000) -> 2863.7689 | E76: =C76*$B$9 -> 613.67046 | F76: =D76-E76 -> 2250.0984 | G76: =C76-F76 -> 145030.81
A77: 64 | B77: =IF($A77="","",EDATE($B$7,$A77-1)) -> 47604 | C77: =IF($A76="","",$G76) -> 145030.81 | D77: =PMT(0.05/12, 120,- 270000) -> 2863.7689 | E77: =C77*$B$9 -> 604.29505 | F77: =D77-E77 -> 2259.4739 | G77: =C77-F77 -> 142771.34
A78: 65 | B78: =IF($A78="","",EDATE($B$7,$A78-1)) -> 47635 | C78: =IF($A77="","",$G77) -> 142771.34 | D78: =PMT(0.05/12, 120,- 270000) -> 2863.7689 | E78: =C78*$B$9 -> 594.88058 | F78: =D78-E78 -> 2268.8883 | G78: =C78-F78 -> 140502.45
A79: 66 | B79: =IF($A79="","",EDATE($B$7,$A79-1)) -> 47665 | C79: =IF($A78="","",$G78) -> 140502.45 | D79: =PMT(0.05/12, 120,- 270000) -> 2863.7689 | E79: =C79*$B$9 -> 585.42688 | F79: =D79-E79 -> 2278.342 | G79: =C79-F79 -> 138224.11
A80: 67 | B80: =IF($A80="","",EDATE($B$7,$A80-1)) -> 47696 | C80: =IF($A79="","",$G79) -> 138224.11 | D80: =PMT(0.05/12, 120,- 270000) -> 2863.7689 | E80: =C80*$B$9 -> 575.93379 | F80: =D80-E80 -> 2287.8351 | G80: =C80-F80 -> 135936.27
A81: 68 | B81: =IF($A81="","",EDATE($B$7,$A81-1)) -> 47727 | C81: =IF($A80="","",$G80) -> 135936.27 | D81: =PMT(0.05/12, 120,- 270000) -> 2863.7689 | E81: =C81*$B$9 -> 566.40114 | F81: =D81-E81 -> 2297.3678 | G81: =C81-F81 -> 133638.91
A82: 69 | B82: =IF($A82="","",EDATE($B$7,$A82-1)) -> 47757 | C82: =IF($A81="","",$G81) -> 133638.91 | D82: =PMT(0.05/12, 120,- 270000) -> 2863.7689 | E82: =C82*$B$9 -> 556.82877 | F82: =D82-E82 -> 2306.9401 | G82: =C82-F82 -> 131331.97
A83: 70 | B83: =IF($A83="","",EDATE($B$7,$A83-1)) -> 47788 | C83: =IF($A82="","",$G82) -> 131331.97 | D83: =PMT(0.05/12, 120,- 270000) -> 2863.7689 | E83: =C83*$B$9 -> 547.21652 | F83: =D83-E83 -> 2316.5524 | G83: =C83-F83 -> 129015.41
A84: 71 | B84: =IF($A84="","",EDATE($B$7,$A84-1)) -> 47818 | C84: =IF($A83="","",$G83) -> 129015.41 | D84: =PMT(0.05/12, 120,- 270000) -> 2863.7689 | E84: =C84*$B$9 -> 537.56422 | F84: =D84-E84 -> 2326.2047 | G84: =C84-F84 -> 126689.21
A85: 72 | B85: =IF($A85="","",EDATE($B$7,$A85-1)) -> 47849 | C85: =IF($A84="","",$G84) -> 126689.21 | D85: =PMT(0.05/12, 120,- 270000) -> 2863.7689 | E85: =C85*$B$9 -> 527.8717 | F85: =D85-E85 -> 2335.8972 | G85: =C85-F85 -> 124353.31
A86: 73 | B86: =IF($A86="","",EDATE($B$7,$A86-1)) -> 47880 | C86: =IF($A85="","",$G85) -> 124353.31 | D86: =PMT(0.05/12, 120,- 270000) -> 2863.7689 | E86: =C86*$B$9 -> 518.1388 | F86: =D86-E86 -> 2345.6301 | G86: =C86-F86 -> 122007.68
... A133: 120 | B133: =IF($A133="","",EDATE($B$7,$A133-1)) -> 49310 | C133: =IF($A132="","",$G132) -> 2851.8861 | D133: =PMT(0.05/12, 120,- 270000) -> 2863.7689 | E133: =C133*$B$9 -> 11.882859 | F133: =D133-E133 -> 2851.8861 | G133: =C133-F133 -> 1.6825652e-11
E134: =SUM(E14:E133) -> 73652.269 | F134: =SUM(F14:F133) -> 270000

Sheet OMZET en BREAK EVEN
A1: =DETAILS!A1 -> VDO
A3: OMZETBEPALING
A7: KUNSTSTOF SPUITGIETMACHINE ENGEL 60 TON
B9: uurtarief | C9: uur/week | E9: omzet maand | F9: =#REF! -> #REF!
A10: Onbemand | B10: 25 | C10: 0 | E10: =B10*C10*4 -> 0 | F10: =E10*12 -> 0 | G10: 12 m
A12: uur per dag | B12: 16
A13: aantal dagen | B13: 6
A14: prestatie per week | B14: =B12*B13 -> 96
A17: III. BREAK EVEN
C18: Totaal | E18: VAST | F18: VARIABEL
A19: Aankopen | C19: =RESULTAAT!B20+RESULTAAT!B21 -> 558000 | F19: =C19 -> 558000
A20: Algemene kosten | C20: =RESULTAAT!B24 -> 178523.2 | E20: =DETAILS!#REF! -> #REF! | F20: =DETAILS!#REF! -> #REF!
A21: Personeelskosten | C21: =RESULTAAT!B26 -> 86195.632 | F21: =C21 -> 86195.632
A22: Afschrijvingen | C22: =RESULTAAT!B28 -> 42000 | E22: =C22 -> 42000
A23: Andere bedrijfskosten | C23: =RESULTAAT!B33 -> 4700 | E23: =C23*80% -> 3760 | F23: =C23-E23 -> 940
A24: Financieel kosten | C24: =RESULTAAT!B45 -> 12981.469 | E24: =C24 -> 12981.469
A25: Belastingen | C25: =RESULTAAT!C51 -> 0 | F25: =C25 -> 0
C26: =SUM(C19:C25) -> 882400.3 | E26: =SUM(E19:E25) -> #REF! | F26: =SUM(F19:F25) -> #REF!
F27: =E26+F26 -> #REF!
A30: Omzet € | C30: =RESULTAAT!B8 -> 930000
A32: Contributiemarge | C32: =(C30-F26) -> #REF!
A33: in % | C33: =(C32/C30) -> #REF!
A34: Break Even € | C34: =E26/C33 -> #REF!
